Workbook
Name _sc_030BAB0B_E5D3_4D88_BCF1_7F515BC46544: Performance!$F$95
Name _sc_5A374052_E185_46EA_A244_FD64BEF8FB39: NA()
Name _Toc321998231: #REF!
Name _Toc321998232: #REF!
Name _Toc321998235: Performance!#REF!
Name _Toc321998238: #REF!
Name _Toc321998240: #REF!
Name _Toc321998241: #REF!
Name _Toc321998242: #REF!
Name _Toc329613520: #REF!
Name _Toc329613521: #REF!
Name _Toc329613522: #REF!
Name _Toc329613525: Performance!#REF!
Name _Toc329613526: Performance!$B$164
Name _Toc329613527: Performance!$B$146
Name _Toc329613530: #REF!
Name _Toc329613531: #REF!
Name _Toc329613532: #REF!
Name _Toc329613533: #REF!
Name _Toc329613534: #REF!
Name _Toc329613539: #REF!
Name _Toc467444151: #REF!
Name _Toc468848071: #REF!
Name Concurrent_user: Performance!#REF!
Name concurrent_users: Performance!#REF!
Name Data_retention: NA()
Name Data_Retention_and_Archival: Performance!$B$149:$D$149
Name Expected_growth_in_users: Performance!#REF!
Name Expected_number_of_concurrent_users: Performance!#REF!
Name Growth_User: Performance!#REF!
Name Growth_users: Performance!#REF!
Name Per_Browser: NA()
Name PerfTablesLimiter: Data_Constants!$A$3:$E$22
Name Response_Time_Requirements___Business_Services: Performance!#REF!
Name Response_Time_Requirements___Test_Harness_Transactions: NA()
Name Response_Time_Requirements___Transactions: NA()
Name Response_Time_Requirements_Transactions: NA()
Name Target_of_number_of_transactions_queries: Performance!#REF!
Name Time_SQP_event: Performance!#REF!
Name Time_SQP_trans: Performance!#REF!
Name Time_test_harness: NA()
Name Time_web: Performance!$D$76
Name Transaction: Performance!#REF!
Name Web_avail: #REF!
Name Web_avail_back: #REF!

Sheet Cover Page
B2: This is a mandatory cover page to be added to all files created within the IP&E Group. Do not delete this information.
B3: Document Name | C3: IPnE_SPD_Performance_QOPD
B4: Version No | C4: V4.1.0
B5: Document Type | C5: Requirements Review Template
B7: Author | C7: Seji Thomas, Sweety Sunny, Binu S, Kavinraj M
B8: Approver | C8: Internal Team Review
B9: Authoring Group | C9: IP&E_SPD
B11: Last version released on | C11: Oct | D11: 2024
B12: Intended Audience | C12: Architects, Technical Leads, Developers, Engineering team, Performance CoE & Testing teams.
B14: File Name | C14: IPnE_SPD_Performance_QOPD_Requirements Review Template_V4.1.0_Oct-2024.xlsx
B16: Confidentiality Statement
B18: This is a controlled document. Unauthorized access, copying, and replication are prohibited.
B19: This document must not be copied in whole or in part by any means, without the written authorization of the Delivery Excellence Head – CEG.

Sheet Read me
A1: Document History
A2: Name of the Artifact | B2: IPnE_SPD_Performance_QOPD_Requirements Review Template_V4.1.0_Oct-2024.xlsx
A3: Release Date | B3: 45582
A5: Revision History
A6: Date | B6: Release No. | C6: Remarks
A7: 45582 | B7: 4.1.0 | C7: 1. Auto-approval has been extended for Desktop type application. 2. Auto-approval has been extended for applications deployed in Cloud SAAS and PAAS, which is on top of IAAS, 3. In the 'Asset Info' tab, for the question on Technology Stack, the following new entries have been added - Gen AI and Microservices, 4. A new condition check is added to the validation logic linked with 'Response Times - Data Requirements' table to check if remarks is provided when the count of records in the table is less than 100. In such a case, positive validation will occur if the remarks are provided. The validation outcome message is also changed to reflect that the rationale for less than 100 records in the table is not provided whenever a negative validation outcome results. 5. Fixed the following issues I. In the case when online transaction table is empty (i.e., without any transaction), the validation to check if the User Concurrency distribution is proper across online transactions and online report transactions as a whole was not happening. This was fixed, and the linked changes required in the validation messages and their formatting have been made. II. The App server, Webserver, and DB server List validations were refactored to avoid making changes in the validation logic whenever the list was updated.
A8: 45504 | B8: 4.0.0 | C8: 1. Introduced additional set of Servers applicable for rule evaluation in the Web Server Pool, 2. Introduced additional set of Servers applicable for rule evaluation in the Application Server Pool, 3. Introduced additional set of Servers applicable for rule evaluation in the DB Server Pool, 4. Expanded the range of concurrent users applicable for rule evaluation. From 15 to 150, the range has been expanded to between 1 and 200, 5. In the 'Response Times - Data – Requirements' table, the column heading for 'Estimated No. Of Records per table' has been updated to imply that the number of records mentioned must be of the Performance testing environment. The Input Message in that column has also been changed to inform the end user about this expectation so while filling the performance requirements of the target asset, it is clear on what data must be filled. 6. Prevent a spill error occurring in 'Deployment Requirements' table validation due to an extra entry added between Web Server and App Server line items in the 'Software Stack - Information' table.
A9: 45299 | B9: 3.1.0 | C9: 1. Cross table data dependency validations are added 2. Allow a scenario where "Response Times - Online Txns-Requirements" table is empty In the previous release of the QOPD, an Applications with no requirements in this table, results in an error message and "Not Appproved" outcome for the table in the "Report" sheet. With the change, it allows this table to be empty when any one of "Response Times - Batch Jobs-Requirements"/"Response Times - Reports-Requirements" tables, or both are non-empty with respect to requirements. 3. Validation messages across tables that must reflect the same context have been re-written for uniformity E.g., messages such as "No batch jobs are defined" and "Response time Report requirements are not filled" 4. Changes to basic validation and message output for couple requirements tables and conditional formatting changes 5. Changes or addition in Usage guidelines ("Read me" tab)
A10: 45211 | B10: 3.0.0 | C10: 1. Allow deployments in Cloud-IAAS (GCP/ AWS/ Azure) for auto approval of requirements similar to on-premise deployments 2. Added the following in the 'Asset Info' tab i. In 'Asset Information' table, separate rows for 'Asset Name' and 'Version', ii. In 'Asset Information' table, a new row for 'Brand Name', iii. In 'Technical Details' table, added the following questions a. Which is the Geographic location of the cloud datacenter? b. Is the response time requirement Transaction wise or request wise? c. Is the expected response/ completion time SLA of all online, report, and batch transactions of the asset known? 3. Modified the following i. In 'Response Times - Data – Requirements' table, the column header for upper limit for the table size, expects data to be filled in unit of mega bytes (MB) ii. Disallow comma (',') character in 'Name' and 'Version' fields of 'Software Stack - Information' table. iii. Content in the requirements table - 'Data Management – Requirements' 4. Fixed the following issues i. If 'DB Server' cell placeholder in 'Deployment Requirements' table is having 'NA' values for 'Number of Instances'/ 'CPU cores'/ 'RAM in GB' with remarks under 'Remarks'column, it is wrongly interpreted as application with no DB, and showing wrong validation message for 'Response Times - Data – Requirements' and 'Data Management – Requirements' tables. ii. In 'Response Times - Online Txns – Requirements' table, incorrect data validations for SLA/ USLA fields. iii. Validation error is not shown when concurrent users distribution is done with 0 users.
A11: 45160 | B11: 2.0.5 | C11: 1. When either of the 'Software Stack - Information' or the 'Deployment Requirements' table is missing data related to DB Server or DB Software, alert the user with the validation message to enter missing details. 2. In 'Response Times - Online Txns – Requirements' table, validation and message display for the case when response time is above 5 secs are refactored for ensuring correctness. 3. In 'Data – Requirements' table, data is not required to be filled if DB component is not part of the asset. 4. In 'Data Management – Requirements' table, data is not required to be filled if DB component is not part of the asset. 5. In 'Data Management – Requirements' table, the case where a 'NA' value in column 'D' (Requirement) was resulting in exclusion of the corresponding row of the table for validation checks is remediated. 5. In 'Data Management – Requirements' table, the case where a 'NA' value in column 'D' (Requirement) was resulting in exclusion of the corresponding row of the table for validation checks is remediated.
A12: 45127 | B12: 2.0.4 | C12: Include editable rows in 'Deployment Requirements' and 'Channels - Information' tables. Proper naming for Apache family web server in the 'Software Stack - Information' table. Exclude the need for having a Web Server in the deployment stack for considering it as a Web-based data-centric Application.
A13: 45120 | B13: 2.0.3 | C13: Refactor of the filter function that extracts asset information and addition of an experimental validation to check if there are requirements outside of auto-approval.
A14: 45114 | B14: 2.0.2 | C14: Extending the deployment Requirements table validation and change the data validation error message in 'Data – Requirements' table, aligned to the purpose of validation .
A15: 45111 | B15: 2.0.1 | C15: Changes for concurrent users range validation auto-approval
A16: 45103 | B16: 2 | C16: © Copyright [2023], Tata Consultancy Services Limited. All Rights Reserved. Document ID CGFR009395
A17: 45084 | B17: 2 | C17: Revised Release of the document
A18: 43263 | B18: 1.31 | C18: Revised Release of the document
A19: 41512 | B19: 1.2 | C19: Formal Release of the document
A21: Usage Guidelines
A22: • This template enables self-review of performance requirements, thereby improving the quality of performance requirements that are captured. • The 'Asset Info' tab must be filled by the asset team (provide details in the 'Asset Information' and 'Technical Details of the Asset' tables) The 'Performance' tab is the main tab where all performance requirements must be provided by the asset team in the respective tables. • As the asset team enters the data in the above mentioned tabs, front-end data validations at the cell level are triggered to ensure that the user provides the right type of data and the set of constraints. • Data entered by the user is also validated based on additional rules configured for checking data correctness at the table level and across tables. Such rule adherence and violations are displayed on the right side of the respective table. • Validations at the cell level, table level, and across tables must be completed successfully for the 'QOPD Evaluation Status' in the 'Report' tab to be ready for 'Cleared' status. • The 'Report' tab consists of the outcome of automated rule validations. Results of individual rule evaluations are presented, and the consolidated status of whether the QOPD has passed through automated review is displayed.
A24: Recommendations while filling the sheet
A25: • By default, the QOPD template is filled with the requirements of a sample application. This enables asset teams to understand how the template is filled so that the teams can provide requirements for their specific software asset. Asset teams must ensure that performance requirements and other information related to the specific asset are entered, and all requirements from the sample QOPD are deleted before the QOPD is submitted for further processing.
A26: • While filling this sheet from an existing Performance QOPD, associates may opt for copying and pasting data under corresponding tables. As a result, formatting changes may also get copied and reflected in the rows copied, which can affect the front-end and additional validations configured in this template. For e.g., if the cell being copied is in 'Percentage' format, the target cell where it is copied will also change to that format. If the target cell's expected format is 'Number' format, after copying & pasting the value it changes to 'Percentage' format; as a result, the validation will fail to show the desired outcome. Overcoming the issue: Right-click the cell where the incorrect format is observed. Select 'Number format...', and change the category to 'Number', setting the decimal places as 0.
A27: • Sometimes after a copy-paste attempt, front-end validations are not triggered, and it may prevent other validations from running. Overcoming the issue: Double-click within the copied cells to trigger validations.
A28: • While filling the requirements what are the general precautions to be taken? Recommendation: 1. If data validation exists for a particular column of the table, follow the guidance in the input message. 2. If the requirement is not known, as in the case of columns with no validation, leave that column blank. 3. If available, provide 'Req-Id' field value from the Architecture document, else use the convention followed in this QOPD sheet. 4. Do not alter the contents of the table in individual or merged cells that are highlighted in shades of Maroon, Black/Gray. 5. If additional rows are required under a table to complete the requirement, insert rows within the bordered region of the table. 6. Do not directly copy paste rows/columns/cell/s directly within or from another copy of the QOPD. Instead, copy paste to a notepad. Subsequently, use that as the source to put the contents in to QOPD sheet. 7. While doing a copy paste, ensure that data is pasted to the right rows and columns. 8. Ensure that columns on an entity's description are filled mandatorily. A row with an empty description column will be excluded from the requirements. This rule applies to the following columns (refer the 'Performance' tab) i. 'Transaction Description' column of 'Response Times - Online Txns – Requirements' table ii. 'Batch job/Transaction Description' column of 'Response Times - Batch Jobs – Requirements' table iii. 'Report type (adhoc/scheduled)' column of 'Response Times - Reports – Requirements' table iv. 'Transaction Description (either Online, Batch, or Report)' column of 'Response Times - Data – Requirements' table
A29: • What must be done if requirements in the following tables are not applicable to the asset? 1. Response Times - Online Txns – Requirements 2. Response Times - Batch Jobs – Requirements 3. Response Times - Reports – Requirements 4. Response Times - Data – Requirements Recommendation: Provide 'NA' against the 'Req-Id' column in the first row. Any additional information/ context can be provided in the 'Remarks' column of the same row of the corresponding table.
A30: • Auto-approval of requirements is applicable if the following conditions are met for the asset. 1. The application is a traditional 3-tier application (having a deployment comprising of traditional Servers - Web Server, Application Server, and Database Server). 2. The number of concurrent users targeted for testing is within the range 1-200. 3. The deployment environment is on-premise dedicated VMs or IaaS (Infrastructure as a Service) Cloud VMs. 4. Irrespective of whether the deployment environment is on-premise/ cloud, if the application does not require load-balancing/ clustering strategy for supporting the load requirements.
A31: File format: The auto-review features in the QOPD template work based on formulae developed for use by Microsoft Excel. The formuale that are used in the template are being verified for the version - Office 365 Pro Plus version: 2304. It has been observed that some of the formulae that are used does not work if the QOPD sheet is opened in the following spreadsheet software, 1. Office 365 Pro Plus version: 1902 2. Google Sheet 3. Apache OpenOffice Calc that are also used by asset teams within TCS at the time of this writing. Hence use the suggested version of Office 365.
A40: QOPD naming convention: Follow the naming convention for the QOPD file -> '<OU Name>_<Asset Name>_<Version>_<NFR Assessment area>_QOPD_<Month>_<Year>.<File Extension>'. As an example, for a QOPD review request raised for a software asset with the following details in the service management portal (IPAM) OU Name: Network Solutions Group Asset Name with version: Rapid Miner v1.0 Service Name: Performance QOPD Month & Year of raising the review request: November 2023 the file name will be 'Network Solutions Group_Rapid Miner_v1-0_Performance_QOPD_Nov_2023'

Sheet Asset Info
A2: Asset Information
A3: Asset Name | B3: CodeA11y | E3: =Data_Validations!E3
A4: Version | B4: v0.0.1 | E4: =Data_Validations!E35
A5: Description | B5: CodeA11y is a VS Code extension and companion Node.js/Express server for automated WCAG 2.1 accessibility analysis. It uses Azure OpenAI to audit source files (React/Angular/Vue/Svelte/HTML) for accessibility violations, generates remediation recommendations, and produces VPAT conformance reports. The server provides JWT authentication, LLM request proxying, user governance, budget controls, audit logging, and project dashboard synchronisation. Targets enterprise development teams needing WCAG A/AA compliance integrated into their VS Code workflow. | E5: =Data_Validations!E4
A6: Brand Name | B6: TCS | E6: =Data_Validations!E36
A7: Target Customer(s) | B7: Enterprise development teams and software engineers who use VS Code and require automated WCAG accessibility compliance checking integrated into their development workflow.
A8: TCS Unit | B8: IP&E SPD
A9: Location | B9: Provide the Product team location
A10: Product/ Account Owner | B10: IP&E SPD Team
A11: TIPAR ID | B11: TBD - Obtain from IPAM before submission | E11: =Data_Validations!E39
A13: Provide the technical details of the Asset, answering the following questions
A14: Technical Details of the Asset
A15: Sl.No. | B15: Question | C15: Response | D15: Remarks | E15: Note
A16: 1 | B16: Which deployment category does the asset belong? (Standalone Desktop, On-premise Web, Cloud) | C16: Cloud | E16: If the asset does not belong to any of the given types, set it as 'Others' and provide the new category name in 'Remarks' column with a short explanation following the name.
A17: 2 | B17: If the asset is deployed in Cloud, provide the Cloud vendor's name (AWS, Azure, Google Cloud, IBM, Vistara) | C17: Azure | E17: If the deployment environment is none among the given names, set it as 'Others' and provide the vendor name in 'Remarks' column with a short explanation following the name. If it does not apply, set is as 'NA'
A18: 3 | B18: If the asset is deployed in Cloud, which is Cloud Computing Stack modeled for the asset? (IAAS, PAAS, SAAS) | C18: PAAS | E18: Provide the right choice of Cloud Computing Stack model. If it does not apply, set is as 'NA'
A19: 4 | B19: Which is the Geographic location of the cloud datacenter? | C19: Azure East US | E19: Provide geographic location of the cloud datacenter
A20: 5 | B20: Irrespective of On-premise web/ Cloud, is the asset deployment architecture following a load balancing and clustering strategy? (Yes/ No) | C20: No
A21: 6 | B21: If the asset is following load balancing and clustering strategy, how does it scale? (Auto-scaling VM instance pool, Auto-scaling Containers) | C21: NA | E21: If the load balancing and clustering strategy is none among the given strategies, set it as 'Others' and provide the strategy name in the 'Remarks' column with a short explanation following the name. If it does not apply, set is as 'NA'
A22: 7 | B22: Technology Stack applicable to the asset (Normal Web, Big Data, Blockchain, AI-ML, IoT, Google API - Firebase, Power BI, Salesforce.com, SAP-based, AR-VR, Video Recording/ Streaming) | C22: AI-ML
A23: 8 | B23: Application Type applicable to the asset (Web-based, Desktop, Mobile, API-based, Web Services, Batch, Rich client) | C23: Web-based
A24: 9 | B24: Is the response time requirement Transaction wise or request wise? | C24: Request wise | E24: How the response time should be captured? Transaction wise or request wise?
A25: 10 | B25: Is the expected response/ completion time SLA of all online, report, and batch transactions of the asset known? | C25: Yes | E25: If the expected SLA is known, performance testing results will be checked for compliance with the requirements (whether the transaction passed or failed the SLA criterion). If the expected SLA is unknown, performance testing results will have only the tested response time value and not the pass/ fail information. In either case Performance testing report will be published, and subsequently the asset will be considered for review and scoring certification.

Sheet Performance
B3: Provide the deployment data to the extent it is known. Usually, this information is available if there is already an existing asset that will be replaced by this asset.
B4: Deployment Requirements | I4: =Data_Validations!E5
B5: Server | C5: Number of Instances | D5: CPU cores | E5: RAM in GB | F5: Remarks | I5: =Data_Validations!E34
B6: Web Server | C6: 1 | D6: 2 | E6: 4 | I6: =Data_Validations!E37
I7: =Data_Validations!E38
B8: Application Server | C8: 1 | D8: 2 | E8: 4
B10: Content/Image server | C10: 1 | D10: 2 | E10: 4 | F10: Static portal assets served directly by Node.js/Express; no separate content/image server
B12: DB Server | C12: 1 | D12: 2 | E12: 8
B20: Mention if the product needs to work in alternative technologies as well
B21: Software Stack - Information | I21: =Data_Validations!E6
B22: Server | C22: Category | D22: Name | E22: Version | F22: Remarks | I22: =Data_Validations!E7
B23: Software - Web Server | C23: Web server (e.g. Apache) | D23: Node.js + Express | E23: 4.18.2
B27: Application Server | C27: Application Server (e.g Jboss) | D27: Node.js | E27: 24.11.0
C29: Language (e.g JDK) | D29: TypeScript | E29: 5.3.0
C31: Javascript libraries/packages (extJs etc) | D31: VS Code Extension API | E31: 1.85.0
C33: Frameworks (e.g Spring, Struts…) | D33: Express | E33: 4.18.2
C35: Logging
C37: Middleware (e.g JMS …) | D37: Helmet + express-rate-limit | E37: 7.1.0 / 7.5.0
C39: Search Engine
C41: Content Mgmt system
C43: 3rd party products (e.g SMS gateway etc) | D43: Playwright (runtime page analysis) | E43: 1.60.0
D44: OpenAI SDK (Azure OpenAI proxy client) | E44: 6.18.0
D45: jsonwebtoken | E45: 9.0.2
D46: multer (VSIX upload handling) | E46: 2.2.0
D47: sql.js (SQLite dev / no-DB mode) | E47: 1.13.0
B53: DB Server | C53: DB Server (e.g. MySQL) | D53: Postgres | E53: 16
B58: Concurrent users is the count of users who are in the middle of business transactions at any given time. Note that a business transaction can consist of multiple web pages.
B59: User Types – Requirements | I59: =Data_Validations!E8
B60: User types available in the system (e.g Admins, customers, Supervisors etc) | C60: Total number of users of each type (whether using the system or not). i.e the expected population | D60: How many users are concurrently doing a transaction during peak usage time? | E60: Concurrent user % growth - Year 3 | F60: Concurrent user % growth - Year 5 | G60: Remarks
B61: Admin | C61: 2 | D61: 1 | E61: NA | F61: NA
B62: Developer (VS Code Extension User) | C62: 100 | D62: 50 | E62: 20 | F62: 30
B71: All the modes of accessing the asset
B72: Channels - Information | I72: =Data_Validations!E9
B73: Category | C73: What % of users will access this channel? (note - sum of percentages must remain 100) | D73: Remarks
B74: Web | C74: 30
B75: Call Centre | C75: NA
B76: Email | C76: NA
B77: Social Media | C77: NA
B78: Mobile | C78: NA
B79: Desktop | C79: 70
B82: Ensure that in the subsequent tables, all the above applicable channels are considered while arriving at Transactions
B85: A Transaction can be a business service (e.g Shopping/Purchasing on a ecommerce site) or a particular screen action (e.g. Checkout cart, File upload).
B86: If it is a business service, the transaction will be implemented over multiple web pages (e.g purchasing on a site, requries user to select items, enter shipping information, make payment)
B87: Note - Multiple transactions can be active at the same time. The sum of concurrent users for all such transactions is captured in the "User Requirements" section at the top of this sheet.
B88: Depending on the nature of the product, decide on the transactions that are time critical. Following are helpful pointers to identify such transactions:
C89: Transactions that will be used by large number of users at the same time (e.g. view products, browse, Shopping etc).
C90: Transactions with relatively lesser users but if slow may effect user experience (e.g User Registration)
C91: Typically adminsitrative actions (e.g. Upload product catalogue) will have far lesser concurrent users and may be left out, unless the business or technical logic for that action is time consuming in which case you want to test and measure it.
C92: For the maximum simultaneous users, keep in mind that peaks can occur at certain times of the day or week or month or year. (e.g salesClerk login to Point of Sale terminals in a shopping chain will be maximum at the opening of the shops)
C93: Transactions that contribute to 'business critical' parameters whose throughput is known (e.g Need to process 500 orders in an hour. In this case identify the transactions that are required to make the orders).
B94: Ensure all interaction Channels are covered in the below transaction list
B95: Response Times - Online Txns – Requirements | O95: =Data_Validations!E10
B96: Req-Id | C96: Transaction Description | D96: No of pages visited per transaction | E96: No of Interactions per Transaction | F96: 90th Percentile Response Time of requests (in seconds) | H96: # of concurrent users accessing the function | I96: Throughput (per hr). E.g 1440 txns/hr | J96: Throughput %Growth in Year 3 | K96: Throughput % Growth in size - Year 5 | L96: Remarks | O96: =Data_Validations!E11
F97: SLA | G97: USLA | O97: =Data_Validations!E12
B98: Req-001 | C98: User Login | D98: 1 | E98: 1 | F98: 2 | G98: 3 | H98: 20 | I98: 200 | J98: 20 | K98: 20 | O98: =Data_Validations!E13
B99: Req-002 | C99: Accessibility Analysis (LLM Audit) | D99: 1 | E99: 1 | F99: 60 | G99: 90 | H99: 5 | I99: 10 | J99: 30 | K99: 50 | L99: LLM-driven accessibility analysis via Azure OpenAI; response exceeds 5s standard due to inference latency. 90th-percentile target: 60s. Hard server timeout: 150s (LLM_REQUEST_TIMEOUT_MS). Concurrent users limited to 5 to respect Azure OpenAI rate limits and manage cost. | O99: =Data_Validations!E14
B100: Req-003 | C100: Project Dashboard Sync | D100: 2 | E100: 2 | F100: 3 | G100: 4 | H100: 10 | I100: 50 | J100: 30 | K100: 50 | O100: =Data_Validations!E15
O101: =Data_Validations!E16
O102: =Data_Validations!E40
B114: Response Times - Batch Jobs – Requirements | O114: =Data_Validations!E23
B115: Req-Id | C115: Batch job/Transaction Description | D115: Scheduling pattern (hourly / daily / weekly / fortnightly/ monthly/ on-demand) | E115: Available time for completion of batch job(in minutes) | G115: Expected count of records processed | H115: Average Size of data processed for the batch job in Mb | I115: Where is the bulk of batch output Data written to - DB or File? | J115: % Growth in size - Year 3 | K115: % Growth in size - Year 5 | L115: Remarks | O115: =Data_Validations!E24
E116: SLA | F116: USLA | O116: =Data_Validations!E25
B117: NA | L117: Not applicable. CodeA11y has no scheduled batch jobs; all processing is request-driven via REST API. | O117: =Data_Validations!E17
O118: =Data_Validations!E41
E122: Provide the unit of time used – sec/ min/ hr
B123: Response Times - Reports – Requirements | O123: =Data_Validations!E31
B124: Req-Id | C124: Report Description | D124: Report type (adhoc/scheduled) | E124: 90th Percentile Response time for Report (in seconds) | G124: Average Report generation per hour | H124: Number of records in the input data set of the report | I124: Number of records in the output data set of the report | J124: Average size of Report data generated in Mb | K124: # of Concurrent Report users | L124: %Growth in record count or size - Year 3 | M124: %Growth in record count or size - Year 5 | N124: Remarks | O124: =Data_Validations!E32
E125: SLA | F125: USLA | O125: =Data_Validations!E33
B126: Req-021 | C126: VPAT Accessibility Conformance Report | D126: Adhoc | E126: 10 | F126: 15 | G126: 2 | H126: 100 | I126: 100 | J126: 500 | K126: 2 | L126: 20 | M126: 20 | N126: WCAG VPAT (.docx) generation; response exceeds 5s standard due to document assembly and accessibility criteria mapping across WCAG 2.1 A/AA success criteria. Max (USLA) is 15s. | O126: =Data_Validations!E18
B127: Req-022 | C127: Project Audit Dashboard Report | D127: Adhoc | E127: 5 | F127: 8 | G127: 10 | H127: 500 | I127: 500 | J127: 200 | K127: 5 | L127: 30 | M127: 50 | O127: =Data_Validations!E42
O128: =Data_Validations!E43
E133: Provide the unit of time used – sec/ min/ hr
B134: Response Times - Data – Requirements | O134: =Data_Validations!E19
B135: Req-Id | C135: Transaction Description (either Online, Batch, or Report) | D135: Tables accessed for the performance critical transactions (Online, Batch, or Report) | E135: Estimated No. Of Records per table ( in PT Env) | F135: Table size in MB | G135: If this table grows with txn, what is the upper limit for the table size (in MB)? | H135: Archival plans for this table? (i.e after how much data or time should the data be archived?) | I135: %Growth in record count or size - Year 3 | J135: %Growth in record count or size - Year 5 | K135: Remarks
B136: Req-031 | C136: Online - Accessibility Analysis | D136: llm_calls | E136: 1000 | F136: 20 | G136: 1000 | H136: 2 years | I136: 30 | J136: 50
B137: Req-032 | C137: Online - Accessibility Analysis | D137: project_issue_records | E137: 5000 | F137: 50 | G137: 2000 | H137: 1 year | I137: 30 | J137: 50
B138: Req-033 | C138: Online - User Management | D138: users | E138: 200 | F138: 1 | G138: 50 | H138: Retained indefinitely (compliance audit data) | I138: 20 | J138: 20
B148: Data Management – Requirements | I148: =Data_Validations!E20
B149: Category | C149: Requirement ID | D149: Requirement | E149: Remarks
B150: Data Back-up Planning (indicate frequency, online/offline backup, scope of data to be backedup) | C150: Req-041 | D150: PostgreSQL automated backup via Azure Database for PostgreSQL. Full daily backups retained for 7 days with point-in-time recovery to any second within the retention window. For SQLite dev mode: daily file export to encrypted cloud storage.
B151: Frequency | C151: Req-042 | D151: Daily full backup + continuous WAL archiving (point-in-time recovery)
B152: Backup type (offline, online) | C152: Req-043 | D152: Online (cloud-managed, automated by Azure Database for PostgreSQL)
B153: Scope of data to be backed up | C153: Req-044 | D153: All tables: users, llm_sessions, llm_calls, user_sessions, audit_logs, password_reset_requests, budget_requests, api_configs, vsix_files, projects, project_snapshots, project_file_stats, project_issue_records
B154: Time window allowed for backup | C154: Req-045 | D154: Managed by Azure Database for PostgreSQL; no manual maintenance window required for cloud mode. SQLite mode: 1-hour backup window during off-peak hours.
B158: Provide this data only if utilization numbers are known from the existing asset deployed in production (or equivalent) - so that the new version should not exceed the existing utilization.
B159: If not provided, Standard utilization figures will be used (average CPU < 60%, average Memory < 70%)
B160: Resource Utilization – Requirements
B161: Category | C161: Requirement ID | D161: Requirement | E161: Remarks
B162: CPU Utilization | C162: Req-051 | D162: 60 | I162: =Data_Validations!E21
B163: Memory Utilization | C163: Req-052 | D163: 70 | I163: =Data_Validations!E22
B164: Input / Output devices Utilization | C164: Req-053 | E164: Disk I/O or network I/O

Sheet Data_Validations
B2: Sl. No. | C2: Table | D2: Validation Rule | E2: Validation Message | F2: Validation Status | H2: Sl. No. | I2: Validation Rule | J2: Validation Message | K2: Validation Staus | M2: Has Web Server? | N2: Has Application Server? | O2: Has DB Server? | P2: Programming Language? | T2: Deployment Category | U2: LB & Clustering Strategy | V2: Auto-scaling Strategy | W2: Technology Stack | X2: Application Type | Y2: Concurrent User Distribution If it is a Desktop Application
B3: 1 | C3: Asset Information | D3: =Data_Constants!C101 | E3: =IF(LEN(B51)>=Data_Constants!N5, Data_Constants!C75, Data_Constants!D75) | F3: =IF(E3=Data_Constants!D75, FALSE, TRUE) | H3: 1 | I3: Checks if the Application Software Stack has Web, App, and DB Servers | J3: {=_xlfn.LET(_xlpm.hasWebserver, M3, _xlpm.hasAppserver, N3,_xlpm.hasDbserver, O3, IF(AND(_xlpm.hasAppserver, _xlpm.hasDbserver), INDEX(Table_Messages[Valid case Message],21),INDEX(Table_Messages[Invalid case Message],21)))} | K3: =IF(J3=Data_Constants!D49, FALSE, TRUE) | M3: {=_xlfn.LET( _xlpm.fullrnge1, INDIRECT(CONCATENATE("Performance!B",Data_Constants!N25,":F", Data_Constants!N25)), _xlpm.softwarestackColumnrnge, INDIRECT(CONCATENATE("Performance!D",Data_Constants!N25,":D", Data_Constants!N25)), _xlpm.WebServerRange, INDIRECT(CONCATENATE("Data_Constants!AI3",":AI33")), _xlpm.WebServerCheckOutcomeList, COUNTIF(_xlpm.softwarestackColumnrnge,"*"&_xlpm.WebServerRange&"*"), _xlpm.hasWebServer, IF(MAX(_xlpm.WebServerCheckOutcomeList)=0,FALSE, TRUE), _xlpm.hasWebServer)} | N3: {=_xlfn.LET( _xlpm.fullrnge1, INDIRECT(CONCATENATE("Performance!B",Data_Constants!N27+1,":F", Data_Constants!N27+1)), _xlpm.softwarestackColumnrnge, INDIRECT(CONCATENATE("Performance!D",Data_Constants!N27+1,":D", Data_Constants!N27+1)), _xlpm.AppServerRange, INDIRECT(CONCATENATE("Data_Constants!AF3",":AF36")), _xlpm.AppServerCheckOutcomeList, COUNTIF(_xlpm.softwarestackColumnrnge,"*"&_xlpm.AppServerRange&"*"), _xlpm.hasAppServer, IF(MAX(_xlpm.AppServerCheckOutcomeList)=0,FALSE, TRUE), _xlpm.hasAppServer)} | O3: {=_xlfn.LET(_xlpm.fullrnge1, INDIRECT(CONCATENATE("Performance!B",Data_Constants!N20,":F", Data_Constants!N20)),_xlpm.softwarestackColumnrnge, INDIRECT(CONCATENATE("Performance!D",Data_Constants!N20,":D", Data_Constants!N20)), _xlpm.DBServerRange, INDIRECT(CONCATENATE("Data_Constants!AC3",":AC32")), _xlpm.DBServerCheckOutcomeList, COUNTIF(_xlpm.softwarestackColumnrnge,"*"&_xlpm.DBServerRange&"*"), _xlpm.hasDbServer, IF(MAX(_xlpm.DBServerCheckOutcomeList)=0,FALSE, TRUE), _xlpm.hasDbServer)} | T3: {=_xlfn.LET(_xlpm.minindex, MATCH(Data_Constants!C7, $V$2:$V$300,0)+3,_xlpm.fullcolumnrnge, INDIRECT(CONCATENATE("V",_xlpm.minindex,":V300")), _xlpm.maxindex, MIN(IF(_xlpm.fullcolumnrnge="",ROW(_xlpm.fullcolumnrnge)))-1, _xlpm.usertypesColumnrnge, INDIRECT(CONCATENATE("V",_xlpm.minindex,":V",_xlpm.maxindex)), _xlpm.totalusersColumnrnge, INDIRECT(CONCATENATE("W",_xlpm.minindex,":W",_xlpm.maxindex)), _xlpm.concusersColumnrnge, INDIRECT(CONCATENATE("X",_xlpm.minindex,":X",_xlpm.maxindex)), _xlpm.rnge1, IF(SUM(VALUE(_xlpm.concusersColumnrnge))= 1, 1,0), OR(('Asset Info'!C16=Data_Constants!K50),AND(('Asset Info'!C16=Data_Constants!K51), OR(('Asset Info'!C17=Data_Constants!H57),('Asset Info'!C17=Data_Constants!H58),('Asset Info'!C17=Data_Constants!H59)), OR(('Asset Info'!C18=Data_Constants!K60),('Asset Info'!C18=Data_Constants!K61),('Asset Info'!C18=Data_Constants!K62))), AND(('Asset Info'!C16=Data_Constants!K49), MIN(_xlpm.rnge1)=1)))} | U3: =('Asset Info'!C20=Data_Constants!H69) | V3: =('Asset Info'!C21=Data_Constants!K72) | W3: =('Asset Info'!C22=Data_Constants!H75) | X3: =('Asset Info'!C23=Data_Constants!K78) | Y3: {=_xlfn.LET(_xlpm.minindex, MATCH(Data_Constants!C7, $V$2:$V$300,0)+3,_xlpm.fullcolumnrnge, INDIRECT(CONCATENATE("V",_xlpm.minindex,":V300")), _xlpm.maxindex, MIN(IF(_xlpm.fullcolumnrnge="",ROW(_xlpm.fullcolumnrnge)))-1, _xlpm.usertypesColumnrnge, INDIRECT(CONCATENATE("V",_xlpm.minindex,":V",_xlpm.maxindex)), _xlpm.totalusersColumnrnge, INDIRECT(CONCATENATE("W",_xlpm.minindex,":W",_xlpm.maxindex)), _xlpm.concusersColumnrnge, INDIRECT(CONCATENATE("X",_xlpm.minindex,":X",_xlpm.maxindex)), _xlpm.rnge1, IF(SUM(VALUE(_xlpm.concusersColumnrnge))= 1, TRUE,FALSE), _xlpm.rnge1)}
B4: 2 | C4: Asset Information | D4: =Data_Constants!C102 | E4: =IF(LEN(B53)>=Data_Constants!N3, Data_Constants!C30, Data_Constants!D30) | F4: =IF(E4=Data_Constants!D30, FALSE, TRUE) | H4: 2 | I4: Checks if the user concurrency distribution is done following the laid down constraints, and if the total user concurrency for the performance assessment is greater than or equal to 15, and less than or equal to 100. | J4: {=_xlfn.LET(_xlpm.minindex1, MATCH(Data_Constants!C7, $V$2:$V$300,0)+3,_xlpm.fullcolumnrnge1, INDIRECT(CONCATENATE("V",_xlpm.minindex1,":V300")), _xlpm.maxindex1, MIN(IF(_xlpm.fullcolumnrnge1="",ROW(_xlpm.fullcolumnrnge1)))-1, _xlpm.peakallconusersColumnrnge, INDIRECT(CONCATENATE("X",_xlpm.minindex1,":X",_xlpm.maxindex1)), _xlpm.minindex2, MATCH(Data_Constants!C11, $AJ$2:$AJ$300,0)+3,_xlpm.fullcolumnrnge2, INDIRECT(CONCATENATE("AJ",_xlpm.minindex2,":AJ300")), _xlpm.t_maxindex2, MIN(IF(_xlpm.fullcolumnrnge2="",ROW(_xlpm.fullcolumnrnge2)))-1, _xlpm.maxindex2, IF(_xlpm.t_maxindex2 < _xlpm.minindex2, _xlpm.minindex2, _xlpm.t_maxindex2), _xlpm.onlinetxnconusersColumnrnge, IF(_xlpm.t_maxindex2 < _xlpm.minindex2, 0, INDIRECT(CONCATENATE("AP",_xlpm.minindex2,":AP",_xlpm.maxindex2))), _xlpm.minindex3, MATCH(Data_Constants!C14, $BJ$2:$BJ$300,0)+3,_xlpm.fullcolumnrnge3, INDIRECT(CONCATENATE("BJ",_xlpm.minindex3,":BJ300")), _xlpm.t_maxindex3, MIN(IF(_xlpm.fullcolumnrnge3="",ROW(_xlpm.fullcolumnrnge3)))-1, _xlpm.maxindex3, IF(_xlpm.t_maxindex3 < _xlpm.minindex3, _xlpm.minindex3, _xlpm.t_maxindex3), _xlpm.onlinerptconusersColumnrnge, IF(_xlpm.t_maxindex3 < _xlpm.minindex3, 0, INDIRECT(CONCATENATE("BS",_xlpm.minindex3,":BS",_xlpm.maxindex3))), _xlpm.maxConcusers, IF(AND(ISNUMBER(_xlpm.peakallconusersColumnrnge),ISNUMBER(_xlpm.onlinetxnconusersColumnrnge),ISNUMBER(_xlpm.onlinerptconusersColumnrnge)), IF(SUM(_xlpm.peakallconusersColumnrnge)>=SUM(_xlpm.onlinetxnconusersColumnrnge)+SUM(_xlpm.onlinerptconusersColumnrnge), SUM(_xlpm.peakallconusersColumnrnge), -1), -1), IF(_xlpm.maxConcusers>=Data_Constants!N10, IF(_xlpm.maxConcusers<=Data_Constants!N11, Data_Constants!C50, Data_Constants!D50), Data_Constants!D50))} | K4: =IF(J4=Data_Constants!D50, FALSE, TRUE) | M4: {=_xlfn.LET( _xlpm.fullrnge1,INDIRECT(CONCATENATE("Performance!B",Data_Constants!N25,":F",Data_Constants!N25)), _xlpm.softwarestackColumnrnge,INDIRECT(CONCATENATE("Performance!D",Data_Constants!N25,":D",Data_Constants!N25)),_xlpm.softwareversCol,INDIRECT(CONCATENATE("Performance!E",Data_Constants!N25,":E",Data_Constants!N25)),_xlpm.WebServerRange,INDIRECT(CONCATENATE("Data_Constants!AI3",":AI33")),_xlpm.WebServerCheckOutcomeList,COUNTIF(_xlpm.softwarestackColumnrnge,"*"&_xlpm.WebServerRange&"*"),IF(MAX(_xlpm.WebServerCheckOutcomeList)=0,"",_xlpm.softwarestackColumnrnge&" "&_xlpm.softwareversCol))} | N4: {=_xlfn.LET( _xlpm.fullrnge1, INDIRECT(CONCATENATE("Performance!B",Data_Constants!N27+1,":F", Data_Constants!N27+1)), _xlpm.softwarestackColumnrnge, INDIRECT(CONCATENATE("Performance!D",Data_Constants!N27+1,":D", Data_Constants!N27+1)), _xlpm.softwareversCol, INDIRECT(CONCATENATE("Performance!E",Data_Constants!N27+1,":E", Data_Constants!N27+1)), _xlpm.AppServerRange, INDIRECT(CONCATENATE("Data_Constants!AF3",":AF36")), _xlpm.AppServerCheckOutcomeList, COUNTIF(_xlpm.softwarestackColumnrnge,"*"&_xlpm.AppServerRange&"*"), IF(MAX(_xlpm.AppServerCheckOutcomeList)=0,"",_xlpm.softwarestackColumnrnge&" "&_xlpm.softwareversCol))} | O4: {=_xlfn.LET(_xlpm.fullrnge1, INDIRECT(CONCATENATE("Performance!B",Data_Constants!N20,":F", Data_Constants!N20)),_xlpm.softwarestackColumnrnge, INDIRECT(CONCATENATE("Performance!D",Data_Constants!N20,":D", Data_Constants!N20)), _xlpm.softwareversCol, INDIRECT(CONCATENATE("Performance!E",Data_Constants!N20,":E", Data_Constants!N20)), _xlpm.DBServerRange, INDIRECT(CONCATENATE("Data_Constants!AC3",":AC32")), _xlpm.DBServerCheckOutcomeList, COUNTIF(_xlpm.softwarestackColumnrnge,"*"&_xlpm.DBServerRange&"*"), IF(MAX(_xlpm.DBServerCheckOutcomeList)=0,"",_xlpm.softwarestackColumnrnge&" "&_xlpm.softwareversCol))} | P4: {=_xlfn.LET(_xlpm.fullrnge1, INDIRECT(CONCATENATE("Performance!B",Data_Constants!E5,":F", Data_Constants!E6)), _xlpm.softwarestackColumnrnge, INDIRECT(CONCATENATE("Performance!D",Data_Constants!E5,":D", Data_Constants!E6)), _xlpm.filteredfullrange, _xlfn._xlws.FILTER(_xlpm.fullrnge1, ISNUMBER(SEARCH(""&Data_Constants!H49&"", _xlpm.softwarestackColumnrnge))+ISNUMBER(SEARCH(""&Data_Constants!H50&"", _xlpm.softwarestackColumnrnge)), INDIRECT(CONCATENATE("A9999",":F9999"))), _xlpm.softwareCol, _xlfn.CHOOSECOLS(_xlpm.filteredfullrange, 3), _xlpm.softwareversCol, _xlfn.CHOOSECOLS(_xlpm.filteredfullrange, 4), _xlpm.softwareCol&" "&_xlpm.softwareversCol)}
B5: 3 | C5: Deployment Requirements | D5: =Data_Constants!C103 | E5: {=_xlfn.LET(_xlpm.fullcolumnrnge, INDIRECT(CONCATENATE("H50",":H300")), _xlpm.minindex, MATCH(Data_Constants!C3, $H$2:$H$300,0)+3, _xlpm.maxindex, MIN(IF(_xlpm.fullcolumnrnge="",ROW(_xlpm.fullcolumnrnge)))-1, _xlpm.serverColumnrnge, INDIRECT(CONCATENATE("H",_xlpm.minindex,":H",_xlpm.maxindex)), _xlpm.numInstancesrnge, INDIRECT(CONCATENATE("I",_xlpm.minindex,":I",_xlpm.maxindex)), _xlpm.cpuCoresrnge, INDIRECT(CONCATENATE("J",_xlpm.minindex,":J",_xlpm.maxindex)), _xlpm.ramCaprnge, INDIRECT(CONCATENATE("K",_xlpm.minindex,":K",_xlpm.maxindex)), IF(AND(NOT(ISBLANK(_xlpm.serverColumnrnge)),_xlpm.serverColumnrnge<>0, NOT(ISBLANK(_xlpm.numInstancesrnge)), _xlpm.numInstancesrnge<>0,NOT(ISBLANK(_xlpm.cpuCoresrnge)),_xlpm.cpuCoresrnge<>0, NOT(ISBLANK(_xlpm.ramCaprnge)),_xlpm.ramCaprnge<>0, IF(ISNUMBER(_xlpm.numInstancesrnge), IF(ISNUMBER(_xlpm.cpuCoresrnge), 1, 0), IF(_xlpm.cpuCoresrnge="NA", 1, 0)), IF(ISNUMBER(_xlpm.numInstancesrnge), IF(ISNUMBER(_xlpm.ramCaprnge), 1, 0), IF(_xlpm.ramCaprnge="NA", 1, 0)), IF(AND(E34=Data_Constants!C70,E37=Data_Constants!C79,E38=Data_Constants!C82),1,0)), Data_Constants!C31, Data_Constants!D31))} | F5: =IF(E5=Data_Constants!D31, FALSE, TRUE) | H5: 3 | I5: Checks if the Application is a normal web application based on the answer to the questionnaire in the 'Asset Info' sheet | J5: {=_xlfn.LET(_xlpm.deplomentCategoryAllowed, T3, _xlpm.lbcStrategyAllowed, U3,_xlpm.autoScaleAllowed, V3, _xlpm.techStackAllowed, W3, _xlpm.appTypeAllowed, X3,IF(AND(_xlpm.deplomentCategoryAllowed, _xlpm.lbcStrategyAllowed, _xlpm.autoScaleAllowed, _xlpm.techStackAllowed, _xlpm.appTypeAllowed), INDEX(Table_Messages[Valid case Message],29),INDEX(Table_Messages[Invalid case Message],29)))} | K5: =IF(J5=Data_Constants!D57, FALSE, TRUE)
B6: 4 | C6: Software Stack - Information | D6: =Data_Constants!C104 | E6: {=_xlfn.LET( _xlpm.minindex, MATCH(Data_Constants!C5, $O$2:$O$300,0)+3, _xlpm.fullcolumnrnge, INDIRECT(CONCATENATE("O",_xlpm.minindex,":O300")), _xlpm.maxindex, MIN(IF(_xlpm.fullcolumnrnge="",ROW(_xlpm.fullcolumnrnge)))-1, _xlpm.softwareNameColumnrnge, INDIRECT(CONCATENATE("Q",_xlpm.minindex,":Q",_xlpm.maxindex)), _xlpm.versionNameColumnrnge, INDIRECT(CONCATENATE("R",_xlpm.minindex,":R",_xlpm.maxindex)), _xlpm.range1, IF(ISNUMBER(SEARCH(",",_xlpm.softwareNameColumnrnge)),0,1), IF(AND(COUNTBLANK(_xlpm.softwareNameColumnrnge)=0, _xlpm.versionNameColumnrnge<>0, COUNTBLANK(_xlpm.versionNameColumnrnge)=0,MIN(_xlpm.range1)=1), Data_Constants!C32, Data_Constants!D32))} | F6: =IF(E6=Data_Constants!D32, FALSE, TRUE)
B7: 5 | C7: Software Stack - Information | D7: =Data_Constants!C105 | E7: {=_xlfn.LET(_xlpm.minindex, MATCH(Data_Constants!C5, $O$2:$O$300,0)+3,_xlpm.fullcolumnrnge, INDIRECT(CONCATENATE("O",_xlpm.minindex,":O200")), _xlpm.t_maxindex, MIN(IF(_xlpm.fullcolumnrnge="",ROW(_xlpm.fullcolumnrnge)))-1, _xlpm.maxindex, IF(_xlpm.t_maxindex < _xlpm.minindex, _xlpm.minindex, _xlpm.t_maxindex), _xlpm.versionNameColumnrnge, INDIRECT(CONCATENATE("R",_xlpm.minindex,":R",_xlpm.maxindex)), _xlpm.rnge1, IF(_xlfn.VALUETOTEXT(_xlpm.versionNameColumnrnge)="NA",1, IF(_xlfn.VALUETOTEXT(_xlpm.versionNameColumnrnge)="0",0, IF(ISTEXT(_xlpm.versionNameColumnrnge), 1, IF(ISNUMBER(_xlpm.versionNameColumnrnge), 1,0)))), IF(MIN(_xlpm.rnge1)=0, Data_Constants!D33, Data_Constants!C33))} | F7: =IF(E7=Data_Constants!D33, FALSE, TRUE) | I7: Is there additional requirements out of the scope of auto-approval? | J7: =_xlfn.LET(_xlpm.sheetsinQOPD, INDIRECT(CONCATENATE("Data_Constants!H",92,":H",99)),IF(COUNTA(_xlpm.sheetsinQOPD)=_xlfn.SHEETS(), FALSE, TRUE))
B8: 6 | C8: User Types – Requirements | D8: =Data_Constants!C106 | E8: {=_xlfn.LET(_xlpm.minindex, MATCH(Data_Constants!C7, $V$2:$V$300,0)+3,_xlpm.fullcolumnrnge, INDIRECT(CONCATENATE("V",_xlpm.minindex,":V300")), _xlpm.maxindex, MIN(IF(_xlpm.fullcolumnrnge="",ROW(_xlpm.fullcolumnrnge)))-1, _xlpm.usertypesColumnrnge, INDIRECT(CONCATENATE("V",_xlpm.minindex,":V",_xlpm.maxindex)), _xlpm.totalusersColumnrnge, INDIRECT(CONCATENATE("W",_xlpm.minindex,":W",_xlpm.maxindex)), _xlpm.concusersColumnrnge, INDIRECT(CONCATENATE("X",_xlpm.minindex,":X",_xlpm.maxindex)), _xlpm.evalRnge, IF(OR(NOT(_xlfn.VALUETOTEXT(_xlpm.usertypesColumnrnge)<>""), NOT(_xlfn.VALUETOTEXT(_xlpm.totalusersColumnrnge)<>""), NOT(_xlfn.VALUETOTEXT(_xlpm.concusersColumnrnge)<>"")),0, IF(OR(NOT(_xlfn.VALUETOTEXT(_xlpm.usertypesColumnrnge)<>"0"), NOT(_xlfn.VALUETOTEXT(_xlpm.totalusersColumnrnge)<>"0")), 1, IF(NOT(ISNUMBER(_xlpm.totalusersColumnrnge)), 2, IF(NOT(ISNUMBER(_xlpm.concusersColumnrnge)), 3, IF(VALUE(_xlpm.totalusersColumnrnge)>=VALUE(_xlpm.concusersColumnrnge), 5, 4))))), IF(OR(MIN(_xlpm.evalRnge)=0,MIN(_xlpm.evalRnge)=1), Data_Constants!D52, IF(MIN(_xlpm.evalRnge)=2, Data_Constants!D53, IF(MIN(_xlpm.evalRnge)=3, Data_Constants!D54, IF(MIN(_xlpm.evalRnge)=5, Data_Constants!C34, Data_Constants!D55)))))} | F8: =IF(E8=Data_Constants!C34, TRUE, FALSE)
B9: 7 | C9: Channels - Information | D9: =Data_Constants!C107 | E9: {=_xlfn.LET(_xlpm.minindex, MATCH(Data_Constants!C9, $AD$2:$AD$300,0)+3,_xlpm.fullcolumnrnge, INDIRECT(CONCATENATE("AD",_xlpm.minindex,":AD300")), _xlpm.maxindex, MIN(IF(_xlpm.fullcolumnrnge="",ROW(_xlpm.fullcolumnrnge)))-1, _xlpm.percentofuserscolumnrnge, INDIRECT(CONCATENATE("AE",_xlpm.minindex,":AE",_xlpm.maxindex)), _xlpm.percentagesum, IF(AND( NOT(ISBLANK(_xlpm.percentofuserscolumnrnge)),ISNUMBER(_xlpm.percentofuserscolumnrnge)),SUM(VALUE(_xlpm.percentofuserscolumnrnge)), "INVALID_SUM"), IF(_xlpm.percentagesum=100, Data_Constants!C35, Data_Constants!D35))} | F9: =IF(E9=Data_Constants!D35, FALSE, TRUE)
B10: 8 | C10: Response Times - Online Txns – Requirements | D10: =Data_Constants!C108 | E10: {=_xlfn.LET( _xlpm.minindex1, MATCH(Data_Constants!C11, $AJ$2:$AJ$300,0)+3, _xlpm.fullcolumnrnge1,INDIRECT(CONCATENATE("AJ",_xlpm.minindex1,":AJ300")), _xlpm.maxindex1, MIN(IF(_xlpm.fullcolumnrnge1="",ROW(_xlpm.fullcolumnrnge1)))-1, _xlpm.txnDesccolumnrnge, INDIRECT(CONCATENATE("AK",_xlpm.minindex1,":AK",_xlpm.maxindex1)), _xlpm.addminx1, INDIRECT(CONCATENATE("AJ", _xlpm.minindex1,":AP", _xlpm.maxindex1)), _xlpm.minindex2, MATCH(Data_Constants!C13, $AW$2:$AW$300,0)+3, _xlpm.fullcolumnrnge2, INDIRECT(CONCATENATE("AW",_xlpm.minindex2,":AW300")), _xlpm.maxindex2, MIN(IF(_xlpm.fullcolumnrnge2="",ROW(_xlpm.fullcolumnrnge2)))-1, _xlpm.addminx2, INDIRECT(CONCATENATE("AW", _xlpm.minindex2,":BD", _xlpm.maxindex2)), _xlpm.minindex3, MATCH(Data_Constants!C15, $BJ$2:$BJ$300,0)+3, _xlpm.fullcolumnrnge3, INDIRECT(CONCATENATE("BJ",_xlpm.minindex3,":BJ300")), _xlpm.maxindex3, MIN(IF(_xlpm.fullcolumnrnge3="",ROW(_xlpm.fullcolumnrnge3)))-1, _xlpm.addminx3, INDIRECT(CONCATENATE("BJ", _xlpm.minindex3,":BN", _xlpm.maxindex3)), _xlpm.rnge1, IF(OR(ISBLANK(_xlpm.addminx1),(_xlfn.CHOOSECOLS(_xlpm.addminx1,1,2,5,6,7))="NA"),0,1), _xlpm.rnge2, IF(OR(ISBLANK(_xlpm.addminx2),(_xlpm.addminx2)="NA"),0,1), _xlpm.rnge3, IF(OR(ISBLANK(_xlpm.addminx3),(_xlpm.addminx3)="NA"),0,1), IF(AND(MIN(_xlpm.rnge1)=0,MIN(_xlpm.rnge2)=0,MIN(_xlpm.rnge3)=0),Data_Constants!D83, IF( AND(MIN(_xlpm.rnge1)=0,OR(MIN(_xlpm.rnge2)=1,MIN(_xlpm.rnge3)=1) ),Data_Constants!C83, IF(MIN(_xlpm.rnge1)=1,IF(AND(_xlpm.txnDesccolumnrnge<>"", LEN(_xlpm.txnDesccolumnrnge)>=Data_Constants!N7), Data_Constants!C36, Data_Constants!D36),"This will not happen"))))} | F10: =IF(OR(E10=Data_Constants!D36,E10=Data_Constants!D83,), FALSE, TRUE) | M10: {=_xlfn.LET(_xlpm.fullrnge1, INDIRECT(CONCATENATE("Performance!B",Data_Constants!E5,":F", Data_Constants!E6)), _xlpm.softwarestackColumnrnge, INDIRECT(CONCATENATE("Performance!D",Data_Constants!E5,":D", Data_Constants!E6)), _xlpm.filteredfullrange, _xlfn._xlws.FILTER(_xlpm.fullrnge1, ISNUMBER(SEARCH("*"&Data_Constants!$H$27:$H$29&"*", _xlpm.softwarestackColumnrnge)), INDIRECT(CONCATENATE("A9999",":F9999"))), _xlpm.softwareCol, _xlfn.CHOOSECOLS(_xlpm.filteredfullrange, 3), _xlpm.softwareversCol, _xlfn.CHOOSECOLS(_xlpm.filteredfullrange, 4), _xlpm.softwareCol&" "&_xlpm.softwareversCol)}
B11: 9 | C11: Response Times - Online Txns – Requirements | D11: =Data_Constants!C109 | E11: {=_xlfn.LET( _xlpm.minindex1, MATCH(Data_Constants!C11, $AJ$2:$AJ$300,0)+3, _xlpm.fullcolumnrnge1,INDIRECT(CONCATENATE("AJ",_xlpm.minindex1,":AJ300")), _xlpm.maxindex1, MIN(IF(_xlpm.fullcolumnrnge1="",ROW(_xlpm.fullcolumnrnge1)))-1, _xlpm.slaColumnrnge, INDIRECT(CONCATENATE("AN",_xlpm.minindex1,":AN",_xlpm.maxindex1)), _xlpm.addminx1, INDIRECT(CONCATENATE("AJ", _xlpm.minindex1,":AP", _xlpm.maxindex1)), _xlpm.minindex2, MATCH(Data_Constants!C13, $AW$2:$AW$300,0)+3, _xlpm.fullcolumnrnge2, INDIRECT(CONCATENATE("AW",_xlpm.minindex2,":AW300")), _xlpm.maxindex2, MIN(IF(_xlpm.fullcolumnrnge2="",ROW(_xlpm.fullcolumnrnge2)))-1, _xlpm.addminx2, INDIRECT(CONCATENATE("AW", _xlpm.minindex2,":BD", _xlpm.maxindex2)), _xlpm.minindex3, MATCH(Data_Constants!C15, $BJ$2:$BJ$300,0)+3, _xlpm.fullcolumnrnge3, INDIRECT(CONCATENATE("BJ",_xlpm.minindex3,":BJ300")), _xlpm.maxindex3, MIN(IF(_xlpm.fullcolumnrnge3="",ROW(_xlpm.fullcolumnrnge3)))-1, _xlpm.addminx3, INDIRECT(CONCATENATE("BJ", _xlpm.minindex3,":BN", _xlpm.maxindex3)), _xlpm.rnge1, IF(OR(ISBLANK(_xlpm.addminx1),(_xlfn.CHOOSECOLS(_xlpm.addminx1,1,2,5,6,7))="NA"),0,1), _xlpm.rnge2, IF(OR(ISBLANK(_xlpm.addminx2),(_xlpm.addminx2)="NA"),0,1), _xlpm.rnge3, IF(OR(ISBLANK(_xlpm.addminx3),(_xlpm.addminx3)="NA"),0,1), _xlpm.rnge4, IF(ISNUMBER(MIN(_xlpm.slaColumnrnge)), IF(MIN(_xlpm.slaColumnrnge)=0,0,1),0), IF(AND(MIN(_xlpm.rnge1)=0,MIN(_xlpm.rnge2)=0,MIN(_xlpm.rnge3)=0),Data_Constants!D83, IF(AND(MIN(_xlpm.rnge1)=0,OR(MIN(_xlpm.rnge2)=1,MIN(_xlpm.rnge3)=1) ),Data_Constants!C83, IF(AND(MIN(_xlpm.rnge1)=1, _xlpm.rnge4=1), Data_Constants!C37, IF(AND(MIN(_xlpm.rnge1)=1, _xlpm.rnge4=0), Data_Constants!D37,Data_Constants!C37 )))))} | F11: =IF(OR(E11=Data_Constants!D37,E11=Data_Constants!D83,), FALSE, TRUE)
B12: 10 | C12: Response Times - Online Txns – Requirements | D12: =Data_Constants!C110 | E12: {=_xlfn.LET( _xlpm.minindex1, MATCH(Data_Constants!C11, $AJ$2:$AJ$300,0)+3, _xlpm.fullcolumnrnge1, INDIRECT(CONCATENATE("AJ",_xlpm.minindex1,":AJ300")), _xlpm.maxindex1, MIN(IF(_xlpm.fullcolumnrnge1="",ROW(_xlpm.fullcolumnrnge1)))-1, _xlpm.uslaColumnrnge, INDIRECT(CONCATENATE("AO",_xlpm.minindex1,":AO",_xlpm.maxindex1)), _xlpm.addminx1, INDIRECT(CONCATENATE("AJ", _xlpm.minindex1,":AP", _xlpm.maxindex1)), _xlpm.minindex2, MATCH(Data_Constants!C13, $AW$2:$AW$300,0)+3, _xlpm.fullcolumnrnge2, INDIRECT(CONCATENATE("AW",_xlpm.minindex2,":AW300")), _xlpm.maxindex2, MIN(IF(_xlpm.fullcolumnrnge2="",ROW(_xlpm.fullcolumnrnge2)))-1, _xlpm.addminx2, INDIRECT(CONCATENATE("AW", _xlpm.minindex2,":BD", _xlpm.maxindex2)), _xlpm.minindex3, MATCH(Data_Constants!C15, $BJ$2:$BJ$300,0)+3, _xlpm.fullcolumnrnge3, INDIRECT(CONCATENATE("BJ",_xlpm.minindex3,":BJ300")), _xlpm.maxindex3, MIN(IF(_xlpm.fullcolumnrnge3="",ROW(_xlpm.fullcolumnrnge3)))-1, _xlpm.addminx3, INDIRECT(CONCATENATE("BJ", _xlpm.minindex3,":BN", _xlpm.maxindex3)), _xlpm.rnge1, IF(OR(ISBLANK(_xlpm.addminx1),(_xlfn.CHOOSECOLS(_xlpm.addminx1,1,2,5,6,7))="NA"),0,1), _xlpm.rnge2, IF(OR(ISBLANK(_xlpm.addminx2),(_xlpm.addminx2)="NA"),0,1), _xlpm.rnge3, IF(OR(ISBLANK(_xlpm.addminx3),(_xlpm.addminx3)="NA"),0,1), _xlpm.rnge4, IF(ISNUMBER(_xlpm.uslaColumnrnge), IF(_xlpm.uslaColumnrnge=0, 0,1)), IF(AND(MIN(_xlpm.rnge1)=0,MIN(_xlpm.rnge2)=0,MIN(_xlpm.rnge3)=0),Data_Constants!D83, IF(AND(MIN(_xlpm.rnge1)=0,OR(MIN(_xlpm.rnge2)=1,MIN(_xlpm.rnge3)=1) ),Data_Constants!C83, IF(MIN(_xlpm.rnge4)=1, Data_Constants!C38, Data_Constants!D38))))} | F12: =IF(OR(E12=Data_Constants!D38,E12=Data_Constants!D83,), FALSE, TRUE)
B13: 11 | C13: Response Times - Online Txns – Requirements | D13: =Data_Constants!C111 | E13: {=_xlfn.LET( _xlpm.minindex1, MATCH(Data_Constants!C11, $AJ$2:$AJ$300,0)+3, _xlpm.fullcolumnrnge1, INDIRECT(CONCATENATE("AJ",_xlpm.minindex1,":AJ300")), _xlpm.maxindex1, MIN(IF(_xlpm.fullcolumnrnge1="",ROW(_xlpm.fullcolumnrnge1)))-1, _xlpm.slaColumnrnge, INDIRECT(CONCATENATE("AN",_xlpm.minindex1,":AN",_xlpm.maxindex1)), _xlpm.uslaColumnrnge, INDIRECT(CONCATENATE("AO",_xlpm.minindex1,":AO",_xlpm.maxindex1)), _xlpm.addminx1, INDIRECT(CONCATENATE("AJ", _xlpm.minindex1,":AP", _xlpm.maxindex1)), _xlpm.minindex2, MATCH(Data_Constants!C13, $AW$2:$AW$300,0)+3, _xlpm.fullcolumnrnge2, INDIRECT(CONCATENATE("AW",_xlpm.minindex2,":AW300")), _xlpm.maxindex2, MIN(IF(_xlpm.fullcolumnrnge2="",ROW(_xlpm.fullcolumnrnge2)))-1, _xlpm.addminx2, INDIRECT(CONCATENATE("AW", _xlpm.minindex2,":BD", _xlpm.maxindex2)), _xlpm.minindex3, MATCH(Data_Constants!C15, $BJ$2:$BJ$300,0)+3, _xlpm.fullcolumnrnge3, INDIRECT(CONCATENATE("BJ",_xlpm.minindex3,":BJ300")), _xlpm.maxindex3, MIN(IF(_xlpm.fullcolumnrnge3="",ROW(_xlpm.fullcolumnrnge3)))-1, _xlpm.addminx3, INDIRECT(CONCATENATE("BJ", _xlpm.minindex3,":BN", _xlpm.maxindex3)), _xlpm.rnge1, IF(OR(ISBLANK(_xlpm.addminx1),(_xlfn.CHOOSECOLS(_xlpm.addminx1,1,2,5,6,7))="NA"),0,1), _xlpm.rnge2, IF(OR(ISBLANK(_xlpm.addminx2),(_xlpm.addminx2)="NA"),0,1), _xlpm.rnge3, IF(OR(ISBLANK(_xlpm.addminx3),(_xlpm.addminx3)="NA"),0,1), _xlpm.rnge4, IF(ISNUMBER(_xlpm.slaColumnrnge), IF(MOD(_xlpm.slaColumnrnge,1)=0, 1, 0), 0), _xlpm.rnge5, IF(ISNUMBER(_xlpm.uslaColumnrnge), IF(MOD(_xlpm.uslaColumnrnge,1)=0, 1, 0), 0), _xlpm.isSLAUSLAValid, IF(AND(MIN(_xlpm.rnge4)<>0, MIN(_xlpm.rnge5)<>0), IF(AND(_xlpm.uslaColumnrnge<=_xlpm.slaColumnrnge*1.6, _xlpm.uslaColumnrnge>=_xlpm.slaColumnrnge), 1, 0), 0), IF(AND(MIN(_xlpm.rnge1)=0,MIN(_xlpm.rnge2)=0,MIN(_xlpm.rnge3)=0),Data_Constants!D83, IF(AND(MIN(_xlpm.rnge1)=0,OR(MIN(_xlpm.rnge2)=1,MIN(_xlpm.rnge3)=1) ),Data_Constants!C83, IF(_xlpm.isSLAUSLAValid, Data_Constants!C39, Data_Constants!D39))))} | F13: =IF(OR(E13=Data_Constants!D39,E13=Data_Constants!D83,), FALSE, TRUE)
B14: 12 | C14: Response Times - Online Txns – Requirements | D14: =Data_Constants!C112 | E14: {=_xlfn.LET( _xlpm.minindex1, MATCH(Data_Constants!C11, $AJ$2:$AJ$300,0)+3, _xlpm.fullcolumnrnge1, INDIRECT(CONCATENATE("AJ",_xlpm.minindex1,":AJ300")), _xlpm.maxindex1, MIN(IF(_xlpm.fullcolumnrnge1="",ROW(_xlpm.fullcolumnrnge1)))-1, _xlpm.concusersColumnrnge, INDIRECT(CONCATENATE("AP",_xlpm.minindex1,":AP",_xlpm.maxindex1)), _xlpm.addminx1, INDIRECT(CONCATENATE("AJ", _xlpm.minindex1,":AP", _xlpm.maxindex1)), _xlpm.minindex2, MATCH(Data_Constants!C13, $AW$2:$AW$300,0)+3, _xlpm.fullcolumnrnge2, INDIRECT(CONCATENATE("AW",_xlpm.minindex2,":AW300")), _xlpm.maxindex2, MIN(IF(_xlpm.fullcolumnrnge2="",ROW(_xlpm.fullcolumnrnge2)))-1, _xlpm.addminx2, INDIRECT(CONCATENATE("AW", _xlpm.minindex2,":BD", _xlpm.maxindex2)), _xlpm.minindex3, MATCH(Data_Constants!C15, $BJ$2:$BJ$300,0)+3, _xlpm.fullcolumnrnge3, INDIRECT(CONCATENATE("BJ",_xlpm.minindex3,":BJ300")), _xlpm.maxindex3, MIN(IF(_xlpm.fullcolumnrnge3="",ROW(_xlpm.fullcolumnrnge3)))-1, _xlpm.addminx3, INDIRECT(CONCATENATE("BJ", _xlpm.minindex3,":BN", _xlpm.maxindex3)), _xlpm.rnge1, IF(OR(ISBLANK(_xlpm.addminx1),(_xlfn.CHOOSECOLS(_xlpm.addminx1,1,2,5,6,7))="NA"),0,1), _xlpm.rnge2, IF(OR(ISBLANK(_xlpm.addminx2),(_xlpm.addminx2)="NA"),0,1), _xlpm.rnge3, IF(OR(ISBLANK(_xlpm.addminx3),(_xlpm.addminx3)="NA"),0,1), _xlpm.rnge4, IF(ISNUMBER(_xlpm.concusersColumnrnge), IF(MOD(_xlpm.concusersColumnrnge,1)=0, 1, 0), 0), IF(AND(MIN(_xlpm.rnge1)=0,MIN(_xlpm.rnge2)=0,MIN(_xlpm.rnge3)=0),Data_Constants!D83, IF(AND(MIN(_xlpm.rnge1)=0,OR(MIN(_xlpm.rnge2)=1,MIN(_xlpm.rnge3)=1) ),Data_Constants!C83, IF(MIN(_xlpm.rnge4)=0, Data_Constants!D40, Data_Constants!C40))))} | F14: =IF(OR(E14=Data_Constants!D40,E14=Data_Constants!D83,), FALSE, TRUE)
B15: 13 | C15: Response Times - Online Txns – Requirements | D15: =Data_Constants!C113 | E15: {=_xlfn.LET( _xlpm.minindex1, MATCH(Data_Constants!C7, $V$2:$V$300,0)+3, _xlpm.fullcolumnrnge1, INDIRECT(CONCATENATE("V",_xlpm.minindex1,":V300")), _xlpm.maxindex1, MIN(IF(_xlpm.fullcolumnrnge1="",ROW(_xlpm.fullcolumnrnge1)))-1, _xlpm.peakallwconusersColumnrnge, INDIRECT(CONCATENATE("X",_xlpm.minindex1,":X",_xlpm.maxindex1)), _xlpm.minindex2, MATCH(Data_Constants!C11, $AJ$2:$AJ$300,0)+3, _xlpm.fullcolumnrnge2, INDIRECT(CONCATENATE("AJ",_xlpm.minindex2,":AJ300")), _xlpm.t_maxindex2, MIN(IF(_xlpm.fullcolumnrnge2="",ROW(_xlpm.fullcolumnrnge2)))-1, _xlpm.maxindex2, IF(_xlpm.t_maxindex2 < _xlpm.minindex2, _xlpm.minindex2, _xlpm.t_maxindex2), _xlpm.addminx2, INDIRECT(CONCATENATE("AJ", _xlpm.minindex2,":AP", _xlpm.maxindex2)), _xlpm.onlinetxnconusersColumnrnge, IF(_xlpm.t_maxindex2 < _xlpm.minindex2, 0, INDIRECT(CONCATENATE("AP",_xlpm.minindex2,":AP",_xlpm.maxindex2))), _xlpm.minindex3, MATCH(Data_Constants!C14, $BJ$2:$BJ$300,0)+3, _xlpm.fullcolumnrnge3, INDIRECT(CONCATENATE("BJ",_xlpm.minindex3,":BJ300")), _xlpm.t_maxindex3, MIN(IF(_xlpm.fullcolumnrnge3="",ROW(_xlpm.fullcolumnrnge3)))-1, _xlpm.maxindex3, IF(_xlpm.t_maxindex3 < _xlpm.minindex3, _xlpm.minindex3, _xlpm.t_maxindex3), _xlpm.onlinerptconusersColumnrnge, IF(_xlpm.t_maxindex3 < _xlpm.minindex3, 0, INDIRECT(CONCATENATE("BS",_xlpm.minindex3,":BS",_xlpm.maxindex3))), _xlpm.addminx3, INDIRECT(CONCATENATE("BJ", _xlpm.minindex3,":BN", _xlpm.maxindex3)), _xlpm.minindex4, MATCH(Data_Constants!C13, $AW$2:$AW$300,0)+3, _xlpm.fullcolumnrnge4, INDIRECT(CONCATENATE("AW",_xlpm.minindex4,":AW300")), _xlpm.maxindex4, MIN(IF(_xlpm.fullcolumnrnge4="",ROW(_xlpm.fullcolumnrnge4)))-1, _xlpm.addminx4, INDIRECT(CONCATENATE("AW", _xlpm.minindex4,":BD", _xlpm.maxindex4)), _xlpm.rnge1, IF(OR(ISBLANK(_xlpm.addminx2),(_xlfn.CHOOSECOLS(_xlpm.addminx2,1,2,5,6,7))="NA"),0,1), _xlpm.rnge2, IF(OR(ISBLANK(_xlpm.addminx3),(_xlpm.addminx3)="NA"),0,1), _xlpm.rnge3, IF(OR(ISBLANK(_xlpm.addminx4),(_xlpm.addminx4)="NA"),0,1), IF(AND(MIN(_xlpm.rnge1)=0,MIN(_xlpm.rnge2)=0,MIN(_xlpm.rnge3)=0),Data_Constants!D83, IF(AND(MIN(_xlpm.rnge1)=0,OR(MIN(_xlpm.rnge2)=1,MIN(_xlpm.rnge3)=1) ),Data_Constants!C83, IF(AND(ISNUMBER(_xlpm.peakallwconusersColumnrnge),ISNUMBER(_xlpm.onlinetxnconusersColumnrnge),ISNUMBER(_xlpm.onlinerptconusersColumnrnge)), IF(SUM(VALUE(_xlpm.peakallwconusersColumnrnge))=SUM(VALUE(_xlpm.onlinetxnconusersColumnrnge))+SUM(_xlpm.onlinerptconusersColumnrnge), Data_Constants!C41, Data_Constants!D41), Data_Constants!D41))))} | F15: =IF(OR(E15=Data_Constants!D41,E15=Data_Constants!D83,), FALSE, TRUE)
B16: 14 | C16: Response Times - Online Txns – Requirements | D16: =Data_Constants!C114 | E16: {=_xlfn.LET( _xlpm.minindex1, MATCH(Data_Constants!C11, $AJ$2:$AJ$300,0)+3, _xlpm.fullcolumnrnge1, INDIRECT(CONCATENATE("AJ",_xlpm.minindex1,":AJ300")), _xlpm.maxindex1, MIN(IF(_xlpm.fullcolumnrnge1="",ROW(_xlpm.fullcolumnrnge1)))-1, _xlpm.slaColumnrnge, INDIRECT(CONCATENATE("AN",_xlpm.minindex1,":AN",_xlpm.maxindex1)), _xlpm.remarksColumnrnge, INDIRECT(CONCATENATE("AT",_xlpm.minindex1,":AT",_xlpm.maxindex1)), _xlpm.addminx1, INDIRECT(CONCATENATE("AJ", _xlpm.minindex1,":AP", _xlpm.maxindex1)), _xlpm.minindex2, MATCH(Data_Constants!C13, $AW$2:$AW$300,0)+3, _xlpm.fullcolumnrnge2, INDIRECT(CONCATENATE("AW",_xlpm.minindex2,":AW300")), _xlpm.maxindex2, MIN(IF(_xlpm.fullcolumnrnge2="",ROW(_xlpm.fullcolumnrnge2)))-1, _xlpm.addminx2, INDIRECT(CONCATENATE("AW", _xlpm.minindex2,":BD", _xlpm.maxindex2)), _xlpm.minindex3, MATCH(Data_Constants!C15, $BJ$2:$BJ$300,0)+3, _xlpm.fullcolumnrnge3, INDIRECT(CONCATENATE("BJ",_xlpm.minindex3,":BJ300")), _xlpm.maxindex3, MIN(IF(_xlpm.fullcolumnrnge3="",ROW(_xlpm.fullcolumnrnge3)))-1, _xlpm.addminx3, INDIRECT(CONCATENATE("BJ", _xlpm.minindex3,":BN", _xlpm.maxindex3)), _xlpm.rnge1, IF(OR(ISBLANK(_xlpm.addminx1),(_xlfn.CHOOSECOLS(_xlpm.addminx1,1,2,5,6,7))="NA"),0,1), _xlpm.rnge2, IF(OR(ISBLANK(_xlpm.addminx2),(_xlpm.addminx2)="NA"),0,1), _xlpm.rnge3, IF(OR(ISBLANK(_xlpm.addminx3),(_xlpm.addminx3)="NA"),0,1), _xlpm.rnge4, IF(_xlpm.slaColumnrnge=0, 0,1), _xlpm.rnge5, IF(_xlpm.slaColumnrnge<=5, 1,0), _xlpm.rnge6, IF(_xlpm.slaColumnrnge>5, IF(LEN(_xlpm.remarksColumnrnge)>=10, 1,0),1), IF(AND(MIN(_xlpm.rnge1)=0,MIN(_xlpm.rnge2)=0,MIN(_xlpm.rnge3)=0),Data_Constants!D83, IF(AND(MIN(_xlpm.rnge1)=0,OR(MIN(_xlpm.rnge2)=1,MIN(_xlpm.rnge3)=1) ),Data_Constants!C83, IF(MIN(_xlpm.rnge4)=0, Data_Constants!D37, IF(MIN(_xlpm.rnge5)=1, Data_Constants!C68, IF(MIN(_xlpm.rnge5)=0, IF(MIN(_xlpm.rnge6)=0, Data_Constants!D42, Data_Constants!C42)))))))} | F16: =IF(OR(E16=Data_Constants!D42,E16=Data_Constants!D37,E16=Data_Constants!D83,), FALSE, TRUE)
B17: 15 | C17: Response Times - Batch Jobs – Requirements | D17: =Data_Constants!C118 | E17: {=_xlfn.LET( _xlpm.minindex1, MATCH(Data_Constants!C11, $AJ$2:$AJ$300,0)+3, _xlpm.fullcolumnrnge1, INDIRECT(CONCATENATE("AJ",_xlpm.minindex1,":AJ300")), _xlpm.maxindex1, MIN(IF(_xlpm.fullcolumnrnge1="",ROW(_xlpm.fullcolumnrnge1)))-1, _xlpm.addminx1, INDIRECT(CONCATENATE("AJ", _xlpm.minindex1,":AP", _xlpm.maxindex1)), _xlpm.minindex3, MATCH(Data_Constants!C15, $BJ$2:$BJ$300,0)+3, _xlpm.fullcolumnrnge3, INDIRECT(CONCATENATE("BJ",_xlpm.minindex3,":BJ300")), _xlpm.maxindex3, MIN(IF(_xlpm.fullcolumnrnge3="",ROW(_xlpm.fullcolumnrnge3)))-1, _xlpm.addminx3, INDIRECT(CONCATENATE("BJ", _xlpm.minindex3,":BN", _xlpm.maxindex3)), _xlpm.minindex2, MATCH(Data_Constants!C13, $AW$2:$AW$300,0)+3, _xlpm.fullcolumnrnge2, INDIRECT(CONCATENATE("AW",_xlpm.minindex2,":AW300")), _xlpm.maxindex2,MIN(IF(_xlpm.fullcolumnrnge2="",ROW(_xlpm.fullcolumnrnge2)))-1, _xlpm.addminx2, INDIRECT(CONCATENATE("AW", _xlpm.minindex2,":BD", _xlpm.maxindex2)), _xlpm.avgtimeforbatchColumnrnge, INDIRECT(CONCATENATE("AZ",_xlpm.minindex2,":AZ",_xlpm.maxindex2)), _xlpm.timeval, IF(NOT(ISERROR(FIND(Data_Constants!I11, _xlpm.avgtimeforbatchColumnrnge))), CONVERT(LEFT(_xlpm.avgtimeforbatchColumnrnge, FIND(Data_Constants!I11, _xlpm.avgtimeforbatchColumnrnge)-2), "min", Data_Constants!I13), IF(NOT(ISERROR(FIND(Data_Constants!I10, _xlpm.avgtimeforbatchColumnrnge))), CONVERT(LEFT(_xlpm.avgtimeforbatchColumnrnge, FIND(Data_Constants!I10, _xlpm.avgtimeforbatchColumnrnge)-2), "hr", Data_Constants!I13), IF(NOT(ISERROR(FIND(Data_Constants!I12, _xlpm.avgtimeforbatchColumnrnge))), CONVERT(LEFT(_xlpm.avgtimeforbatchColumnrnge, FIND(Data_Constants!I12, _xlpm.avgtimeforbatchColumnrnge)-2), "sec", Data_Constants!I13)))), _xlpm.rnge1, IF(OR(ISBLANK(_xlpm.addminx1),(_xlfn.CHOOSECOLS(_xlpm.addminx1,1,2,5,6,7))="NA"),0,1), _xlpm.rnge3, IF(OR(ISBLANK(_xlpm.addminx3),(_xlpm.addminx3)="NA"),0,1), _xlpm.rnge2, IF(OR(ISBLANK(_xlpm.addminx2),(_xlpm.addminx2)="NA"),0,1), _xlpm.rnge4, IF(_xlpm.timeval>=60, 1, 0), IF(AND(MIN(_xlpm.rnge1)=0,MIN(_xlpm.rnge2)=0,MIN(_xlpm.rnge3)=0),Data_Constants!D65, IF(AND(MIN(_xlpm.rnge2)=0,OR(MIN(_xlpm.rnge1)=1,MIN(_xlpm.rnge3)=1) ),Data_Constants!C65, IF(AND(MIN(_xlpm.rnge2)=1, MIN(_xlpm.rnge4)=1),Data_Constants!C43, Data_Constants!D43))))} | F17: =IF(OR(E17=Data_Constants!D43,E17=Data_Constants!D65), FALSE, TRUE) | I17: =IF(AND(F3:F22, K3:K4), Data_Constants!C51,Data_Constants!D51)
B18: 16 | C18: Response Times - Reports – Requirements | D18: =Data_Constants!C122 | E18: {=_xlfn.LET( _xlpm.minindex1, MATCH(Data_Constants!C11, $AJ$2:$AJ$300,0)+3, _xlpm.fullcolumnrnge1, INDIRECT(CONCATENATE("AJ",_xlpm.minindex1,":AJ300")), _xlpm.maxindex1, MIN(IF(_xlpm.fullcolumnrnge1="",ROW(_xlpm.fullcolumnrnge1)))-1, _xlpm.addminx1, INDIRECT(CONCATENATE("AJ", _xlpm.minindex1,":AP", _xlpm.maxindex1)), _xlpm.minindex2, MATCH(Data_Constants!C13, $AW$2:$AW$300,0)+3, _xlpm.fullcolumnrnge2, INDIRECT(CONCATENATE("AW",_xlpm.minindex2,":AW300")), _xlpm.maxindex2, MIN(IF(_xlpm.fullcolumnrnge2="",ROW(_xlpm.fullcolumnrnge2)))-1, _xlpm.addminx2, INDIRECT(CONCATENATE("AW", _xlpm.minindex2,":BD", _xlpm.maxindex2)), _xlpm.minindex3, MATCH(Data_Constants!C15, $BJ$2:$BJ$300,0)+3, _xlpm.fullcolumnrnge3, INDIRECT(CONCATENATE("BJ",_xlpm.minindex3,":BJ300")), _xlpm.maxindex3, MIN(IF(_xlpm.fullcolumnrnge3="",ROW(_xlpm.fullcolumnrnge3)))-1, _xlpm.reporttypeColumnrnge, INDIRECT(CONCATENATE("BL",_xlpm.minindex3,":BL",_xlpm.maxindex3)), _xlpm.addminx3, INDIRECT(CONCATENATE("BJ", _xlpm.minindex3,":BN", _xlpm.maxindex3)), _xlpm.rnge1, IF(OR(ISBLANK(_xlpm.addminx1),(_xlfn.CHOOSECOLS(_xlpm.addminx1,1,2,5,6,7))="NA"),0,1), _xlpm.rnge2, IF(OR(ISBLANK(_xlpm.addminx2),(_xlpm.addminx2)="NA"),0,1), _xlpm.rnge3, IF(OR(ISBLANK(_xlpm.addminx3),(_xlpm.addminx3)="NA"),0,1), _xlpm.rnge4, IF(COUNTIF(Data_Constants!$H$17:$H$18,_xlpm.reporttypeColumnrnge)=1, 1, 0), IF(AND(MIN(_xlpm.rnge1)=0,MIN(_xlpm.rnge2)=0,MIN(_xlpm.rnge3)=0),Data_Constants!D56, IF(AND(MIN(_xlpm.rnge3)=0,OR(MIN(_xlpm.rnge1)=1,MIN(_xlpm.rnge2)=1) ),Data_Constants!C56, IF(AND(MIN(_xlpm.rnge3)=1, MIN(_xlpm.rnge4)=1),Data_Constants!C44, Data_Constants!D44))))} | F18: =IF(OR(E18=Data_Constants!D44,E18=Data_Constants!D56), FALSE, TRUE)
B19: 17 | C19: Response Times - Data – Requirements | D19: =Data_Constants!C123 | E19: {=_xlfn.LET( _xlpm.minindex, MATCH(Data_Constants!C17, $BY$2:$BY$300,0)+3, _xlpm.fullcolumnrnge, INDIRECT(CONCATENATE("BY",_xlpm.minindex,":BY300")), _xlpm.maxindex, MIN(IF(_xlpm.fullcolumnrnge="",ROW(_xlpm.fullcolumnrnge)))-1, _xlpm.addminx, INDIRECT(CONCATENATE("BY", _xlpm.minindex,":CG", _xlpm.maxindex)), _xlpm.estrecordsColumnrnge, INDIRECT(CONCATENATE("CB",_xlpm.minindex,":CB",_xlpm.maxindex)), _xlpm.tablesizeColumnrnge, INDIRECT(CONCATENATE("CC",_xlpm.minindex,":CC",_xlpm.maxindex)), _xlpm.tablesizeulimitColumnrnge, INDIRECT(CONCATENATE("CD",_xlpm.minindex,":CD",_xlpm.maxindex)), _xlpm.tablenamesrnge, INDIRECT(CONCATENATE("CA",_xlpm.minindex,":CA",_xlpm.maxindex)), _xlpm.remarksrnge, INDIRECT(CONCATENATE("CH",_xlpm.minindex,":CH",_xlpm.maxindex)), _xlpm.minindex1, MATCH(Data_Constants!C5, $DE$1:$DE$300,0)+1, _xlpm.fullcolumnrnge1, INDIRECT(CONCATENATE("DE",_xlpm.minindex1,":DE300")), _xlpm.maxindex1, MIN(IF(_xlpm.fullcolumnrnge1="",ROW(_xlpm.fullcolumnrnge1)))-1, _xlpm.t_deploymentdb, INDIRECT(CONCATENATE("DG",_xlpm.minindex1,":DG",_xlpm.maxindex1)), _xlpm.deploymentdb, IF(DE52=0, 0, _xlpm.t_deploymentdb), _xlpm.rnge1, IF(OR(DE52=0, INDEX(_xlpm.deploymentdb, 1, 1)=0), 0,1), _xlpm.rnge2, IF(ISBLANK(_xlpm.addminx),0,1), _xlpm.range3, IF(ISERROR(SEARCH(",",_xlpm.tablenamesrnge)),0,1), _xlpm.rnge4, IF(_xlpm.estrecordsColumnrnge<100, IF(LEN(_xlpm.remarksrnge)>=10, 1,0),1), _xlpm.evalRnge, IF(NOT(_xlfn.VALUETOTEXT(_xlpm.estrecordsColumnrnge)<>""),2, IF(NOT(_xlfn.VALUETOTEXT(_xlpm.estrecordsColumnrnge)<>"0"), 2, IF(NOT(ISNUMBER(_xlpm.tablesizeColumnrnge)), 3, IF(NOT(_xlfn.VALUETOTEXT(_xlpm.tablesizeColumnrnge)<>"0"), 3, IF(NOT(ISNUMBER(_xlpm.tablesizeulimitColumnrnge)), 4, IF(VALUE(_xlpm.tablesizeulimitColumnrnge)<VALUE(_xlpm.tablesizeColumnrnge), 5, IF(VALUE(_xlpm.estrecordsColumnrnge)<Data_Constants!N9,6, IF(OR(COUNTIF(_xlpm.tablenamesrnge,_xlpm.tablenamesrnge)>1) = TRUE,7,8)))))))), IF(AND(MIN(_xlpm.rnge1)=0, MIN(_xlpm.rnge2)=0), Data_Constants!C45, IF(AND(MIN(_xlpm.rnge1)=0, MIN(_xlpm.rnge2)=1), Data_Constants!K45, IF(AND(MIN(_xlpm.rnge1)=1, MIN(_xlpm.rnge2)=0), Data_Constants!D45, IF(AND(MIN(_xlpm.rnge1)=1, MAX(_xlpm.range3)=1), Data_Constants!D88, IF(AND(MIN(_xlpm.rnge1)=0, MIN(_xlpm.evalRnge)=1), Data_Constants!D74, IF(AND(MIN(_xlpm.rnge1)=1,MIN(_xlpm.evalRnge)=2), Data_Constants!E45, IF(AND(MIN(_xlpm.rnge1)=1,MIN(_xlpm.evalRnge)=3), Data_Constants!F45, IF(AND(MIN(_xlpm.rnge1)=1,MIN(_xlpm.evalRnge)=4), Data_Constants!G45, IF(AND(MIN(_xlpm.rnge1)=1,MIN(_xlpm.evalRnge)=5), Data_Constants!H45, IF(AND(MIN(_xlpm.rnge1)=1, MIN(_xlpm.rnge4)=1), Data_Constants!C45, IF(AND(MIN(_xlpm.rnge1)=1,MIN(_xlpm.evalRnge)=6), Data_Constants!I45, IF(AND(MIN(_xlpm.rnge1)=1,MIN(_xlpm.evalRnge)=7), Data_Constants!J45, Data_Constants!C45)))))))))))))} | F19: =IF(OR(E19=Data_Constants!D45,E19=Data_Constants!E45,E19=Data_Constants!F45,E19=Data_Constants!G45,E19=Data_Constants!H45,E19=Data_Constants!I45,E19=Data_Constants!J45,E19=Data_Constants!K45,E19=Data_Constants!D74,E19=Data_Constants!D88), FALSE, TRUE) | K19: {=_xlfn.LET( _xlpm.minindex, MATCH(Data_Constants!C17, $BY$2:$BY$300,0)+3, _xlpm.fullcolumnrnge, INDIRECT(CONCATENATE("BY",_xlpm.minindex,":BY300")), _xlpm.maxindex, MIN(IF(_xlpm.fullcolumnrnge="",ROW(_xlpm.fullcolumnrnge)))-1, _xlpm.addminx, INDIRECT(CONCATENATE("BY", _xlpm.minindex,":CG", _xlpm.maxindex)), _xlpm.estrecordsColumnrnge, INDIRECT(CONCATENATE("CB",_xlpm.minindex,":CB",_xlpm.maxindex)), _xlpm.tablesizeColumnrnge, INDIRECT(CONCATENATE("CC",_xlpm.minindex,":CC",_xlpm.maxindex)), _xlpm.tablesizeulimitColumnrnge, INDIRECT(CONCATENATE("CD",_xlpm.minindex,":CD",_xlpm.maxindex)), _xlpm.tablenamesrnge, INDIRECT(CONCATENATE("CA",_xlpm.minindex,":CA",_xlpm.maxindex)), _xlpm.minindex1, MATCH(Data_Constants!C5, $DE$1:$DE$300,0)+1, _xlpm.fullcolumnrnge1, INDIRECT(CONCATENATE("DE",_xlpm.minindex1,":DE300")), _xlpm.maxindex1, MIN(IF(_xlpm.fullcolumnrnge1="",ROW(_xlpm.fullcolumnrnge1)))-1, _xlpm.t_deploymentdb, INDIRECT(CONCATENATE("DG",_xlpm.minindex1,":DG",_xlpm.maxindex1)), _xlpm.deploymentdb, IF(DE52=0, 0, _xlpm.t_deploymentdb), _xlpm.rnge1, IF(OR(DE52=0, INDEX(_xlpm.deploymentdb, 1, 1)=0), 0,1), _xlpm.rnge2, IF(ISBLANK(_xlpm.addminx),0,1), _xlpm.evalRnge, IF(NOT(_xlfn.VALUETOTEXT(_xlpm.estrecordsColumnrnge)<>""),0, IF(NOT(_xlfn.VALUETOTEXT(_xlpm.estrecordsColumnrnge)<>"0"), 0, IF(NOT(ISNUMBER(_xlpm.tablesizeColumnrnge)), 0, IF(NOT(ISNUMBER(_xlpm.tablesizeulimitColumnrnge)), 0, IF(VALUE(_xlpm.tablesizeulimitColumnrnge)<VALUE(_xlpm.tablesizeColumnrnge), 0, IF(VALUE(_xlpm.estrecordsColumnrnge)<Data_Constants!N9,0, IF(OR(COUNTIF(_xlpm.tablenamesrnge,_xlpm.tablenamesrnge)>1) = TRUE,0,1))))))), IF(AND(MIN(_xlpm.rnge1)=0, MIN(_xlpm.rnge2)=0), Data_Constants!C45, IF(AND(MIN(_xlpm.rnge1)=0, MIN(_xlpm.evalRnge)=1), Data_Constants!D74, IF(AND(MIN(_xlpm.rnge1)=1,MIN(_xlpm.evalRnge)=0), Data_Constants!D45, Data_Constants!C45))))}
B20: 18 | C20: Data Management – Requirements | D20: =Data_Constants!C124 | E20: {=_xlfn.LET( _xlpm.minindex, MATCH(Data_Constants!C19, $CJ$2:$CJ$300,0)+3, _xlpm.fullcolumnrnge, INDIRECT(CONCATENATE("CJ",_xlpm.minindex,":CJ300")), _xlpm.maxindex,MIN(IF(_xlpm.fullcolumnrnge="",ROW(_xlpm.fullcolumnrnge)))-1, _xlpm.categoryColumnrnge, INDIRECT(CONCATENATE("CJ",_xlpm.minindex,":CJ",_xlpm.maxindex)), _xlpm.dmreqColumnrnge, INDIRECT(CONCATENATE("CL",_xlpm.minindex,":CL",_xlpm.maxindex)), _xlpm.minindex1, MATCH(Data_Constants!C3, $CV$1:$CV$300,0)+1, _xlpm.fullcolumnrnge1, INDIRECT(CONCATENATE("CV",_xlpm.minindex1,":CV300")), _xlpm.maxindex1, MIN(IF(_xlpm.fullcolumnrnge1="",ROW(_xlpm.fullcolumnrnge1)))-1, _xlpm.t_deploymentdb, INDIRECT(CONCATENATE("CW",_xlpm.minindex1,":CW",_xlpm.maxindex1)), _xlpm.deploymentdb, IF(CV52=0, 0, _xlpm.t_deploymentdb), _xlpm.rnge1, IF(OR(CV52=0, INDEX(_xlpm.deploymentdb, 1, 1)="NA"), 0,1), _xlpm.rnge2, IF(_xlpm.dmreqColumnrnge=0, 0,1), IF(AND(MIN(_xlpm.rnge1)=0,MAX(_xlpm.rnge2)=0), Data_Constants!D46, IF(AND(MIN(_xlpm.rnge1)=0,MAX(_xlpm.rnge2)=1), Data_Constants!C46, IF(AND(MIN(_xlpm.rnge1)=1,MIN(_xlpm.rnge2)=1), Data_Constants!C46, Data_Constants!D46))))} | F20: =IF(OR(E20=Data_Constants!D46,E20=Data_Constants!D73), FALSE, TRUE)
B21: 19 | C21: Resource Utilization – Requirements | D21: =Data_Constants!C125 | E21: {=_xlfn.LET( _xlpm.minindex, MATCH(Data_Constants!C21, $CP$2:$CP$300,0)+3, _xlpm.fullcolumnrnge, INDIRECT(CONCATENATE("CP",_xlpm.minindex,":CP300")), _xlpm.maxindex, MIN(IF(_xlpm.fullcolumnrnge="",ROW(_xlpm.fullcolumnrnge)))-1, _xlpm.rucategoryColumnrnge, INDIRECT(CONCATENATE("CP",_xlpm.minindex,":CP",_xlpm.maxindex)), _xlpm.rureqColumnrnge, INDIRECT(CONCATENATE("CR",_xlpm.minindex,":CR",_xlpm.maxindex)), _xlpm.cpuresutilIndx, MATCH(Data_Constants!H21, _xlpm.rucategoryColumnrnge,0), _xlpm.cpuresutilValue, INDEX(_xlpm.rureqColumnrnge, _xlpm.cpuresutilIndx), _xlpm.rnge1, IF(OR(ISTEXT(_xlpm.cpuresutilValue), _xlpm.cpuresutilValue=0), 0,1), _xlpm.rnge2, IF(VALUE(_xlpm.cpuresutilValue)<=Data_Constants!I21, 1,0), IF(MIN(_xlpm.rnge1)=0,Data_Constants!D66, IF(MIN(_xlpm.rnge1)=1, IF(MIN(_xlpm.rnge2)=1, Data_Constants!C47, Data_Constants!D47))))} | F21: =IF(OR(E21=Data_Constants!D47,E21=Data_Constants!D66), FALSE, TRUE)
B22: 20 | C22: Resource Utilization – Requirements | D22: =Data_Constants!C126 | E22: {=_xlfn.LET( _xlpm.minindex, MATCH(Data_Constants!C21, $CP$2:$CP$300,0)+3, _xlpm.fullcolumnrnge, INDIRECT(CONCATENATE("CP",_xlpm.minindex,":CP300")), _xlpm.maxindex, MIN(IF(_xlpm.fullcolumnrnge="",ROW(_xlpm.fullcolumnrnge)))-1, _xlpm.rucategoryColumnrnge, INDIRECT(CONCATENATE("CP",_xlpm.minindex,":CP",_xlpm.maxindex)), _xlpm.rureqColumnrnge, INDIRECT(CONCATENATE("CR",_xlpm.minindex,":CR",_xlpm.maxindex)), _xlpm.cpuresutilIndx, MATCH(Data_Constants!H22, _xlpm.rucategoryColumnrnge,0), _xlpm.cpuresutilValue, INDEX(_xlpm.rureqColumnrnge, _xlpm.cpuresutilIndx), _xlpm.rnge1, IF(OR(ISTEXT(_xlpm.cpuresutilValue),_xlpm.cpuresutilValue=0), 0,1), _xlpm.rnge2, IF(VALUE(_xlpm.cpuresutilValue)<=Data_Constants!I22, 1,0), IF(MIN(_xlpm.rnge1)=0, Data_Constants!D67, IF(MIN(_xlpm.rnge1)=1, IF(MIN(_xlpm.rnge2)=1, Data_Constants!C48, Data_Constants!D48))))} | F22: =IF(OR(E22=Data_Constants!D48,E22=Data_Constants!D67), FALSE, TRUE)
B23: 21 | C23: Response Times - Batch Jobs – Requirements | D23: =Data_Constants!C115 | E23: {=_xlfn.LET( _xlpm.minindex1, MATCH(Data_Constants!C11, $AJ$2:$AJ$300,0)+3, _xlpm.fullcolumnrnge1, INDIRECT(CONCATENATE("AJ",_xlpm.minindex1,":AJ300")), _xlpm.maxindex1, MIN(IF(_xlpm.fullcolumnrnge1="",ROW(_xlpm.fullcolumnrnge1)))-1, _xlpm.addminx1, INDIRECT(CONCATENATE("AJ", _xlpm.minindex1,":AP", _xlpm.maxindex1)), _xlpm.minindex3, MATCH(Data_Constants!C15, $BJ$2:$BJ$300,0)+3, _xlpm.fullcolumnrnge3, INDIRECT(CONCATENATE("BJ",_xlpm.minindex3,":BJ300")), _xlpm.maxindex3, MIN(IF(_xlpm.fullcolumnrnge3="",ROW(_xlpm.fullcolumnrnge3)))-1, _xlpm.addminx3, INDIRECT(CONCATENATE("BJ", _xlpm.minindex3,":BN", _xlpm.maxindex3)), _xlpm.minindex2, MATCH(Data_Constants!C13, $AW$2:$AW$300,0)+3, _xlpm.fullcolumnrnge2, INDIRECT(CONCATENATE("AW",_xlpm.minindex2,":AW300")), _xlpm.maxindex2, MIN(IF(_xlpm.fullcolumnrnge2="",ROW(_xlpm.fullcolumnrnge2)))-1, _xlpm.addminx2, INDIRECT(CONCATENATE("AW", _xlpm.minindex2,":BD", _xlpm.maxindex2)), _xlpm.slaColumnrnge, INDIRECT(CONCATENATE("AZ",_xlpm.minindex2,":AZ",_xlpm.maxindex2)), _xlpm.rnge1, IF(OR(ISBLANK(_xlpm.addminx1),(_xlfn.CHOOSECOLS(_xlpm.addminx1,1,2,5,6,7))="NA"),0,1), _xlpm.rnge3, IF(OR(ISBLANK(_xlpm.addminx3),(_xlpm.addminx3)="NA"),0,1), _xlpm.rnge2, IF(OR(ISBLANK(_xlpm.addminx2),(_xlpm.addminx2)="NA"),0,1), IF(AND(MIN(_xlpm.rnge1)=0,MIN(_xlpm.rnge2)=0,MIN(_xlpm.rnge3)=0),Data_Constants!D65, IF(AND(MIN(_xlpm.rnge2)=0,OR(MIN(_xlpm.rnge1)=1,MIN(_xlpm.rnge3)=1) ),Data_Constants!C65, IF(AND(MIN(_xlpm.rnge2)=1,_xlpm.slaColumnrnge<>0),Data_Constants!C58, Data_Constants!D58))))} | F23: =IF(OR(E23=Data_Constants!D58,E23=Data_Constants!D65), FALSE, TRUE)
B24: 22 | C24: Response Times - Batch Jobs – Requirements | D24: =Data_Constants!C116 | E24: {=_xlfn.LET( _xlpm.minindex1, MATCH(Data_Constants!C11, $AJ$2:$AJ$300,0)+3, _xlpm.fullcolumnrnge1, INDIRECT(CONCATENATE("AJ",_xlpm.minindex1,":AJ300")), _xlpm.maxindex1, MIN(IF(_xlpm.fullcolumnrnge1="",ROW(_xlpm.fullcolumnrnge1)))-1, _xlpm.addminx1, INDIRECT(CONCATENATE("AJ", _xlpm.minindex1,":AP", _xlpm.maxindex1)), _xlpm.minindex3, MATCH(Data_Constants!C15, $BJ$2:$BJ$300,0)+3, _xlpm.fullcolumnrnge3, INDIRECT(CONCATENATE("BJ",_xlpm.minindex3,":BJ300")), _xlpm.maxindex3, MIN(IF(_xlpm.fullcolumnrnge3="",ROW(_xlpm.fullcolumnrnge3)))-1, _xlpm.addminx3, INDIRECT(CONCATENATE("BJ", _xlpm.minindex3,":BN", _xlpm.maxindex3)), _xlpm.minindex2, MATCH(Data_Constants!C13, $AW$2:$AW$300,0)+3, _xlpm.fullcolumnrnge2, INDIRECT(CONCATENATE("AW",_xlpm.minindex2,":AW300")), _xlpm.maxindex2, MIN(IF(_xlpm.fullcolumnrnge2="",ROW(_xlpm.fullcolumnrnge2)))-1, _xlpm.addminx2, INDIRECT(CONCATENATE("AW", _xlpm.minindex2,":BD", _xlpm.maxindex2)), _xlpm.uslaColumnrnge, INDIRECT(CONCATENATE("BA",_xlpm.minindex2,":BA",_xlpm.maxindex2)), _xlpm.rnge1, IF(OR(ISBLANK(_xlpm.addminx1),(_xlfn.CHOOSECOLS(_xlpm.addminx1,1,2,5,6,7))="NA"),0,1), _xlpm.rnge3, IF(OR(ISBLANK(_xlpm.addminx3),(_xlpm.addminx3)="NA"),0,1), _xlpm.rnge2, IF(OR(ISBLANK(_xlpm.addminx2),(_xlpm.addminx2)="NA"),0,1), IF(AND(MIN(_xlpm.rnge1)=0,MIN(_xlpm.rnge2)=0,MIN(_xlpm.rnge3)=0),Data_Constants!D65, IF(AND(MIN(_xlpm.rnge2)=0,OR(MIN(_xlpm.rnge1)=1,MIN(_xlpm.rnge3)=1) ),Data_Constants!C65, IF(AND(MIN(_xlpm.rnge2)=1,_xlpm.uslaColumnrnge<>0),Data_Constants!C59, Data_Constants!D59))))} | F24: =IF(OR(E24=Data_Constants!D59,E24=Data_Constants!D65), FALSE, TRUE)
B25: 23 | C25: Response Times - Batch Jobs – Requirements | D25: =Data_Constants!C117 | E25: {=_xlfn.LET( _xlpm.minindex1, MATCH(Data_Constants!C11, $AJ$2:$AJ$300,0)+3, _xlpm.fullcolumnrnge1, INDIRECT(CONCATENATE("AJ",_xlpm.minindex1,":AJ300")), _xlpm.maxindex1, MIN(IF(_xlpm.fullcolumnrnge1="",ROW(_xlpm.fullcolumnrnge1)))-1, _xlpm.addminx1, INDIRECT(CONCATENATE("AJ", _xlpm.minindex1,":AP", _xlpm.maxindex1)), _xlpm.minindex3, MATCH(Data_Constants!C15, $BJ$2:$BJ$300,0)+3, _xlpm.fullcolumnrnge3, INDIRECT(CONCATENATE("BJ",_xlpm.minindex3,":BJ300")), _xlpm.maxindex3, MIN(IF(_xlpm.fullcolumnrnge3="",ROW(_xlpm.fullcolumnrnge3)))-1, _xlpm.addminx3, INDIRECT(CONCATENATE("BJ", _xlpm.minindex3,":BN", _xlpm.maxindex3)), _xlpm.minindex2, MATCH(Data_Constants!C13, $AW$2:$AW$300,0)+3, _xlpm.fullcolumnrnge2, INDIRECT(CONCATENATE("AW",_xlpm.minindex2,":AW300")), _xlpm.maxindex2, MIN(IF(_xlpm.fullcolumnrnge2="",ROW(_xlpm.fullcolumnrnge2)))-1, _xlpm.addminx2, INDIRECT(CONCATENATE("AW", _xlpm.minindex2,":BD", _xlpm.maxindex2)), _xlpm.slaColumnrnge, INDIRECT(CONCATENATE("AZ",_xlpm.minindex2,":AZ",_xlpm.maxindex2)), _xlpm.uslaColumnrnge, INDIRECT(CONCATENATE("BA",_xlpm.minindex2,":BA",_xlpm.maxindex2)), _xlpm.rnge1, IF(OR(ISBLANK(_xlpm.addminx1),(_xlfn.CHOOSECOLS(_xlpm.addminx1,1,2,5,6,7))="NA"),0,1), _xlpm.rnge3, IF(OR(ISBLANK(_xlpm.addminx3),(_xlpm.addminx3)="NA"),0,1), _xlpm.rnge2, IF(OR(ISBLANK(_xlpm.addminx2),(_xlpm.addminx2)="NA"),0,1), IF(AND(MIN(_xlpm.rnge1)=0,MIN(_xlpm.rnge2)=0,MIN(_xlpm.rnge3)=0),Data_Constants!D65, IF(AND(MIN(_xlpm.rnge2)=0,OR(MIN(_xlpm.rnge1)=1,MIN(_xlpm.rnge3)=1) ),Data_Constants!C65, IF(MIN(_xlpm.rnge2)=1, IF(AND(_xlpm.uslaColumnrnge<=_xlpm.slaColumnrnge*1.6, _xlpm.uslaColumnrnge>=_xlpm.slaColumnrnge), Data_Constants!C60, Data_Constants!D60)))))} | F25: =IF(OR(E25=Data_Constants!D60,E25=Data_Constants!D65), FALSE, TRUE)
B31: 24 | C31: Response Times - Reports – Requirements | D31: =Data_Constants!C119 | E31: {=_xlfn.LET( _xlpm.minindex1, MATCH(Data_Constants!C11, $AJ$2:$AJ$300,0)+3, _xlpm.fullcolumnrnge1, INDIRECT(CONCATENATE("AJ",_xlpm.minindex1,":AJ300")), _xlpm.maxindex1, MIN(IF(_xlpm.fullcolumnrnge1="",ROW(_xlpm.fullcolumnrnge1)))-1, _xlpm.addminx1, INDIRECT(CONCATENATE("AJ", _xlpm.minindex1,":AP", _xlpm.maxindex1)), _xlpm.minindex2, MATCH(Data_Constants!C13, $AW$2:$AW$300,0)+3, _xlpm.fullcolumnrnge2, INDIRECT(CONCATENATE("AW",_xlpm.minindex2,":AW300")), _xlpm.maxindex2, MIN(IF(_xlpm.fullcolumnrnge2="",ROW(_xlpm.fullcolumnrnge2)))-1, _xlpm.addminx2, INDIRECT(CONCATENATE("AW", _xlpm.minindex2,":BD", _xlpm.maxindex2)), _xlpm.minindex3, MATCH(Data_Constants!C15, $BJ$2:$BJ$300,0)+3, _xlpm.fullcolumnrnge3, INDIRECT(CONCATENATE("BJ",_xlpm.minindex3,":BJ300")), _xlpm.maxindex3, MIN(IF(_xlpm.fullcolumnrnge3="",ROW(_xlpm.fullcolumnrnge3)))-1, _xlpm.addminx3, INDIRECT(CONCATENATE("BJ", _xlpm.minindex3,":BN", _xlpm.maxindex3)), _xlpm.slaColumnrnge, INDIRECT(CONCATENATE("BM",_xlpm.minindex3,":BM",_xlpm.maxindex3)), _xlpm.rnge1, IF(OR(ISBLANK(_xlpm.addminx1),(_xlfn.CHOOSECOLS(_xlpm.addminx1,1,2,5,6,7))="NA"),0,1), _xlpm.rnge2, IF(OR(ISBLANK(_xlpm.addminx2),(_xlpm.addminx2)="NA"),0,1), _xlpm.rnge3, IF(OR(ISBLANK(_xlpm.addminx3),(_xlpm.addminx3)="NA"),0,1), _xlpm.rnge4, IF(ISNUMBER(_xlpm.slaColumnrnge), IF(_xlpm.slaColumnrnge=0, 0,1)), IF(AND(MIN(_xlpm.rnge1)=0,MIN(_xlpm.rnge2)=0,MIN(_xlpm.rnge3)=0),Data_Constants!D56, IF(AND(MIN(_xlpm.rnge3)=0,OR(MIN(_xlpm.rnge1)=1,MIN(_xlpm.rnge2)=1) ),Data_Constants!C56, IF(MIN(_xlpm.rnge3)=1, IF(MIN(_xlpm.rnge4)=1,Data_Constants!C61, Data_Constants!D61)))))} | F31: =IF(OR(E31=Data_Constants!D61,E31=Data_Constants!D56), FALSE, TRUE)
B32: 25 | C32: Response Times - Reports – Requirements | D32: =Data_Constants!C120 | E32: {=_xlfn.LET( _xlpm.minindex1, MATCH(Data_Constants!C11, $AJ$2:$AJ$300,0)+3, _xlpm.fullcolumnrnge1, INDIRECT(CONCATENATE("AJ",_xlpm.minindex1,":AJ300")), _xlpm.maxindex1, MIN(IF(_xlpm.fullcolumnrnge1="",ROW(_xlpm.fullcolumnrnge1)))-1, _xlpm.addminx1, INDIRECT(CONCATENATE("AJ", _xlpm.minindex1,":AP", _xlpm.maxindex1)), _xlpm.minindex2, MATCH(Data_Constants!C13, $AW$2:$AW$300,0)+3, _xlpm.fullcolumnrnge2, INDIRECT(CONCATENATE("AW",_xlpm.minindex2,":AW300")), _xlpm.maxindex2, MIN(IF(_xlpm.fullcolumnrnge2="",ROW(_xlpm.fullcolumnrnge2)))-1, _xlpm.addminx2, INDIRECT(CONCATENATE("AW", _xlpm.minindex2,":BD", _xlpm.maxindex2)), _xlpm.minindex3, MATCH(Data_Constants!C15, $BJ$2:$BJ$300,0)+3, _xlpm.fullcolumnrnge3, INDIRECT(CONCATENATE("BJ",_xlpm.minindex3,":BJ300")), _xlpm.maxindex3, MIN(IF(_xlpm.fullcolumnrnge3="",ROW(_xlpm.fullcolumnrnge3)))-1, _xlpm.addminx3, INDIRECT(CONCATENATE("BJ", _xlpm.minindex3,":BN", _xlpm.maxindex3)), _xlpm.uslaColumnrnge, INDIRECT(CONCATENATE("BN",_xlpm.minindex3,":BN",_xlpm.maxindex3)), _xlpm.rnge1, IF(OR(ISBLANK(_xlpm.addminx1),(_xlfn.CHOOSECOLS(_xlpm.addminx1,1,2,5,6,7))="NA"),0,1), _xlpm.rnge2, IF(OR(ISBLANK(_xlpm.addminx2),(_xlpm.addminx2)="NA"),0,1), _xlpm.rnge3, IF(OR(ISBLANK(_xlpm.addminx3),(_xlpm.addminx3)="NA"),0,1), _xlpm.rnge4, IF(ISNUMBER(_xlpm.uslaColumnrnge), IF(_xlpm.uslaColumnrnge=0, 0,1)), IF(AND(MIN(_xlpm.rnge1)=0,MIN(_xlpm.rnge2)=0,MIN(_xlpm.rnge3)=0),Data_Constants!D56, IF(AND(MIN(_xlpm.rnge3)=0,OR(MIN(_xlpm.rnge1)=1,MIN(_xlpm.rnge2)=1) ),Data_Constants!C56, IF(MIN(_xlpm.rnge3)=1, IF(MIN(_xlpm.rnge4)=1,Data_Constants!C62, Data_Constants!D62)))))} | F32: =IF(OR(E32=Data_Constants!D62,E32=Data_Constants!D56), FALSE, TRUE)
B33: 26 | C33: Response Times - Reports – Requirements | D33: =Data_Constants!C121 | E33: {=_xlfn.LET( _xlpm.minindex1, MATCH(Data_Constants!C11, $AJ$2:$AJ$300,0)+3, _xlpm.fullcolumnrnge1, INDIRECT(CONCATENATE("AJ",_xlpm.minindex1,":AJ300")), _xlpm.maxindex1, MIN(IF(_xlpm.fullcolumnrnge1="",ROW(_xlpm.fullcolumnrnge1)))-1, _xlpm.addminx1, INDIRECT(CONCATENATE("AJ", _xlpm.minindex1,":AP", _xlpm.maxindex1)), _xlpm.minindex2, MATCH(Data_Constants!C13, $AW$2:$AW$300,0)+3, _xlpm.fullcolumnrnge2, INDIRECT(CONCATENATE("AW",_xlpm.minindex2,":AW300")), _xlpm.maxindex2, MIN(IF(_xlpm.fullcolumnrnge2="",ROW(_xlpm.fullcolumnrnge2)))-1, _xlpm.addminx2, INDIRECT(CONCATENATE("AW", _xlpm.minindex2,":BD", _xlpm.maxindex2)), _xlpm.minindex3, MATCH(Data_Constants!C15, $BJ$2:$BJ$300,0)+3, _xlpm.fullcolumnrnge3, INDIRECT(CONCATENATE("BJ",_xlpm.minindex3,":BJ300")), _xlpm.maxindex3, MIN(IF(_xlpm.fullcolumnrnge3="",ROW(_xlpm.fullcolumnrnge3)))-1, _xlpm.addminx3, INDIRECT(CONCATENATE("BJ", _xlpm.minindex3,":BN", _xlpm.maxindex3)), _xlpm.slaColumnrnge, INDIRECT(CONCATENATE("BM",_xlpm.minindex3,":BM",_xlpm.maxindex3)), _xlpm.uslaColumnrnge, INDIRECT(CONCATENATE("BN",_xlpm.minindex3,":BN",_xlpm.maxindex3)), _xlpm.rnge1, IF(OR(ISBLANK(_xlpm.addminx1),(_xlfn.CHOOSECOLS(_xlpm.addminx1,1,2,5,6,7))="NA"),0,1), _xlpm.rnge2, IF(OR(ISBLANK(_xlpm.addminx2),(_xlpm.addminx2)="NA"),0,1), _xlpm.rnge3, IF(OR(ISBLANK(_xlpm.addminx3),(_xlpm.addminx3)="NA"),0,1), _xlpm.rnge4, IF(AND(_xlpm.uslaColumnrnge<=_xlpm.slaColumnrnge*1.6, _xlpm.uslaColumnrnge>=_xlpm.slaColumnrnge), 1, 0), IF(AND(MIN(_xlpm.rnge1)=0,MIN(_xlpm.rnge2)=0,MIN(_xlpm.rnge3)=0),Data_Constants!D56, IF(AND(MIN(_xlpm.rnge3)=0,OR(MIN(_xlpm.rnge1)=1,MIN(_xlpm.rnge2)=1) ),Data_Constants!C56, IF(MIN(_xlpm.rnge3)=1, IF(MIN(_xlpm.rnge4)=1, Data_Constants!C63, Data_Constants!D63)))))} | F33: =IF(OR(E33=Data_Constants!D63,E33=Data_Constants!D56), FALSE, TRUE)
B34: 27 | C34: Deployment Requirements | D34: =Data_Constants!C127 | E34: {=_xlfn.LET( _xlpm.minindex1, MATCH(Data_Constants!C3, $CV$1:$CV$300,0)+1, _xlpm.fullcolumnrnge1, INDIRECT(CONCATENATE("CV",_xlpm.minindex1,":CV300")), _xlpm.maxindex1, MIN(IF(_xlpm.fullcolumnrnge1="",ROW(_xlpm.fullcolumnrnge1)))-1, _xlpm.minindex2, MATCH(Data_Constants!C5, $DE$1:$DE$300,0)+1, _xlpm.fullcolumnrnge2, INDIRECT(CONCATENATE("DE",_xlpm.minindex1,":DE300")), _xlpm.maxindex2, MIN(IF(_xlpm.fullcolumnrnge2="",ROW(_xlpm.fullcolumnrnge2)))-1, _xlpm.t_softstackdb, INDIRECT(CONCATENATE("DG",_xlpm.minindex2,":DG",_xlpm.maxindex2)), _xlpm.softstackdb, IF(DE52=0, 0, INDEX(_xlpm.t_softstackdb,1)), _xlpm.t_deploymentdb, INDIRECT(CONCATENATE("CW",_xlpm.minindex1,":CW",_xlpm.maxindex1)), _xlpm.deploymentdb, IF(CV52=0, 0, INDEX(_xlpm.t_deploymentdb,1)), _xlpm.t_deploymentremarks, INDIRECT(CONCATENATE("CZ",_xlpm.minindex1,":CZ",_xlpm.maxindex1)), _xlpm.deploymentremarks, IF(CV52=0, 0, INDEX(_xlpm.t_deploymentremarks,1)), _xlpm.rnge1, IF(_xlpm.softstackdb=0,0,1), _xlpm.rnge2, IF(_xlpm.deploymentdb=0,0,1), _xlpm.rnge3, IF(_xlpm.deploymentremarks=0,0,1), IF(OR(AND(_xlpm.deploymentdb="NA",_xlpm.rnge3=1,_xlpm.rnge1=1,_xlpm.deploymentremarks<>"NA"), AND(_xlpm.deploymentdb="NA",OR(_xlpm.rnge3=0,_xlpm.deploymentremarks="NA"),_xlpm.rnge1=0)), Data_Constants!C70, IF(AND(_xlpm.deploymentdb="NA",OR(_xlpm.rnge3=0,_xlpm.deploymentremarks="NA"),_xlpm.rnge1=1),Data_Constants!E69, IF(AND(_xlpm.deploymentdb="NA",_xlpm.rnge3=1,_xlpm.deploymentremarks<>"NA",_xlpm.rnge1=0),Data_Constants!D72, IF(AND(MIN(_xlpm.rnge1)=0, MIN(_xlpm.rnge2)=0), Data_Constants!D70, IF(AND(MIN(_xlpm.rnge1)=0, MIN(_xlpm.rnge2)=1), Data_Constants!D72, IF(AND(MIN(_xlpm.rnge1)=1, MIN(_xlpm.rnge2)=0), Data_Constants!D69, IF(AND(MAX(_xlpm.rnge1)=1, MIN(_xlpm.rnge2)=1), Data_Constants!C70, Data_Constants!D71))))))))} | F34: =IF(OR(E34=Data_Constants!D69, E34=Data_Constants!D72), FALSE, TRUE)
B35: 28 | C35: Asset Information | D35: =Data_Constants!C101 | E35: =_xlfn.LET( _xlpm.dotPos, IF(ISERROR(FIND(Data_Constants!I6,B52,1)), -1, FIND(Data_Constants!I6,B52,1)), _xlpm.bracBeginPos, IF(ISERROR(FIND(Data_Constants!I3,B52,1)), -1, FIND(Data_Constants!I3,B52,1)), _xlpm.spacePos, IF(ISERROR(FIND(Data_Constants!I5,B52,1)), -1, FIND(Data_Constants!I5,B52,1)), _xlpm.bracEndPos, IF(ISERROR(FIND(Data_Constants!I4,B52,1)), -1, FIND(Data_Constants!I4,B52,1)), _xlpm.versionnum, IF(_xlpm.dotPos=-1,"-1",IF(_xlpm.bracBeginPos=-1, MID(B52, _xlpm.dotPos-1, IF(ISERROR(FIND(Data_Constants!I5,B52,_xlpm.dotPos)), LEN(B52) + 1, FIND(Data_Constants!I5,B52,_xlpm.dotPos)) - _xlpm.dotPos + 1),MID(B52,_xlpm.bracBeginPos+1,_xlpm.bracEndPos-_xlpm.bracBeginPos-1))), IF(_xlfn.VALUETOTEXT(_xlpm.versionnum)="-1", Data_Constants!D29, Data_Constants!C29)) | F35: =IF(E35=Data_Constants!D29, FALSE, TRUE)
B36: 29 | C36: Asset Information | D36: =Data_Constants!C128 | E36: =IF(LEN(B54)>=Data_Constants!N12, Data_Constants!C76, Data_Constants!D76) | F36: =IF(E36=Data_Constants!D76, FALSE, TRUE)
B37: 30 | C37: Deployment Requirements | D37: =Data_Constants!C129 | E37: {=_xlfn.LET( _xlpm.minindex1, MATCH(Data_Constants!C3, $CV$1:$CV$300,0)+1, _xlpm.fullcolumnrnge1, INDIRECT(CONCATENATE("CV",_xlpm.minindex1,":CV300")), _xlpm.maxindex1, MIN(IF(_xlpm.fullcolumnrnge1="",ROW(_xlpm.fullcolumnrnge1)))-1, _xlpm.minindex2, MATCH(Data_Constants!C5, $DE$1:$DE$300,0)+1, _xlpm.fullcolumnrnge2, INDIRECT(CONCATENATE("DE",_xlpm.minindex1,":DE300")), _xlpm.maxindex2, MIN(IF(_xlpm.fullcolumnrnge2="",ROW(_xlpm.fullcolumnrnge2)))-1, _xlpm.t_softstackweb, INDIRECT(CONCATENATE("DG",_xlpm.minindex2,":DG",_xlpm.maxindex2)), _xlpm.softstackweb, IF(DE53=0, 0, INDEX(_xlpm.t_softstackweb,2)), _xlpm.t_deploymentweb, INDIRECT(CONCATENATE("CW",_xlpm.minindex1,":CW",_xlpm.maxindex1)), _xlpm.deploymentweb, IF(CV53=0, 0, INDEX(_xlpm.t_deploymentweb,2)), _xlpm.t_deploymentremarks, INDIRECT(CONCATENATE("CZ",_xlpm.minindex1,":CZ",_xlpm.maxindex1)), _xlpm.deploymentremarks, IF(CV53=0, 0, INDEX(_xlpm.t_deploymentremarks,2)), _xlpm.rnge1, IF(_xlpm.softstackweb=0,0,1), _xlpm.rnge2, IF(_xlpm.deploymentweb=0,0,1), _xlpm.rnge3, IF(_xlpm.deploymentremarks=0,0,1), IF(OR(AND(_xlpm.deploymentweb="NA",_xlpm.rnge3=1,_xlpm.rnge1=1,_xlpm.deploymentremarks<>"NA"), AND(_xlpm.deploymentweb="NA",OR(_xlpm.rnge3=0,_xlpm.deploymentremarks="NA"),_xlpm.rnge1=0)), Data_Constants!C79, IF(AND(_xlpm.deploymentweb="NA",OR(_xlpm.rnge3=0,_xlpm.deploymentremarks="NA"),_xlpm.rnge1=1),Data_Constants!E78, IF(AND(_xlpm.deploymentweb="NA",_xlpm.rnge3=1,_xlpm.rnge1=0),Data_Constants!D77, IF(AND(MIN(_xlpm.rnge1)=0, MIN(_xlpm.rnge2)=0), Data_Constants!D79, IF(AND(MIN(_xlpm.rnge1)=0, MIN(_xlpm.rnge2)=1), Data_Constants!D77, IF(AND(MIN(_xlpm.rnge1)=1, MIN(_xlpm.rnge2)=0), Data_Constants!D78, IF(AND(MAX(_xlpm.rnge1)=1, MIN(_xlpm.rnge2)=1), Data_Constants!C79, Data_Constants!D71))))))))} | F37: =IF(OR(E37=Data_Constants!E78, E37=Data_Constants!D77,E37=Data_Constants!D78, E37=Data_Constants!D71), FALSE, TRUE)
B38: 31 | C38: Deployment Requirements | D38: =Data_Constants!C130 | E38: {=_xlfn.LET( _xlpm.minindex1, MATCH(Data_Constants!C3, $CV$1:$CV$300,0)+1, _xlpm.fullcolumnrnge1, INDIRECT(CONCATENATE("CV",_xlpm.minindex1,":CV300")), _xlpm.maxindex1, MIN(IF(_xlpm.fullcolumnrnge1="",ROW(_xlpm.fullcolumnrnge1)))-1, _xlpm.minindex2, MATCH(Data_Constants!C5, $DE$1:$DE$300,0)+1, _xlpm.fullcolumnrnge2, INDIRECT(CONCATENATE("DE",_xlpm.minindex1,":DE300")), _xlpm.maxindex2, MIN(IF(_xlpm.fullcolumnrnge2="",ROW(_xlpm.fullcolumnrnge2)))-1, _xlpm.t_softstackapp, INDIRECT(CONCATENATE("DG",_xlpm.minindex2,":DG",_xlpm.maxindex2)), _xlpm.softstackapp, IF(DE54=0, 0, INDEX(_xlpm.t_softstackapp,3)), _xlpm.t_deploymentapp, INDIRECT(CONCATENATE("CW",_xlpm.minindex1,":CW",_xlpm.maxindex1)), _xlpm.deploymentapp, IF(CV54=0, 0, INDEX(_xlpm.t_deploymentapp,3)), _xlpm.t_deploymentremarks, INDIRECT(CONCATENATE("CZ",_xlpm.minindex1,":CZ",_xlpm.maxindex1)), _xlpm.deploymentremarks, IF(CV54=0, 0, INDEX(_xlpm.t_deploymentremarks,3)), _xlpm.rnge1, IF(_xlpm.softstackapp=0,0,1), _xlpm.rnge2, IF(_xlpm.deploymentapp=0,0,1), _xlpm.rnge3, IF(_xlpm.deploymentremarks=0,0,1), IF(OR(AND(_xlpm.deploymentapp="NA",_xlpm.rnge3=1,_xlpm.rnge1=1,_xlpm.deploymentremarks<>"NA"), AND(_xlpm.deploymentapp="NA",OR(_xlpm.rnge3=0,_xlpm.deploymentremarks="NA"),_xlpm.rnge1=0)), Data_Constants!C82, IF(AND(_xlpm.deploymentapp="NA",OR(_xlpm.rnge3=0,_xlpm.deploymentremarks="NA"),_xlpm.rnge1=1),Data_Constants!E81, IF(AND(_xlpm.deploymentapp="NA",_xlpm.rnge3=1,_xlpm.rnge1=0),Data_Constants!D80, IF(AND(MIN(_xlpm.rnge1)=0, MIN(_xlpm.rnge2)=0), Data_Constants!D82, IF(AND(MIN(_xlpm.rnge1)=0, MIN(_xlpm.rnge2)=1), Data_Constants!D80,IF(AND(MIN(_xlpm.rnge1)=1, MIN(_xlpm.rnge2)=0), Data_Constants!D81, IF(AND(MAX(_xlpm.rnge1)=1, MIN(_xlpm.rnge2)=1), Data_Constants!C82, Data_Constants!D71))))))))} | F38: =IF(OR(E38=Data_Constants!E81, E38=Data_Constants!D80,E38=Data_Constants!D81, E38=Data_Constants!D71), FALSE, TRUE)
B39: 32 | C39: Asset Information | D39: =Data_Constants!C131 | E39: =IF(LEN(B59)<>Data_Constants!N13,Data_Constants!D84,IF(EXACT(LEFT(B59,5),"TIPAR"),Data_Constants!C84,Data_Constants!D84)) | F39: =IF(E39=Data_Constants!D84, FALSE, TRUE)
B40: 33 | C40: Response Times - Online Txns – Requirements | D40: =Data_Constants!C132 | E40: {=_xlfn.LET( _xlpm.minindex1, MATCH(Data_Constants!C11, $AJ$2:$AJ$300,0)+3, _xlpm.fullcolumnrnge1,INDIRECT(CONCATENATE("AJ",_xlpm.minindex1,":AJ300")), _xlpm.maxindex1, MIN(IF(_xlpm.fullcolumnrnge1="",ROW(_xlpm.fullcolumnrnge1)))-1, _xlpm.txnDesccolumnrnge, INDIRECT(CONCATENATE("AK",_xlpm.minindex1,":AK",_xlpm.maxindex1)), _xlpm.addminx1, INDIRECT(CONCATENATE("AJ", _xlpm.minindex1,":AP", _xlpm.maxindex1)), _xlpm.minindex2, MATCH(Data_Constants!C13, $AW$2:$AW$300,0)+3, _xlpm.fullcolumnrnge2, INDIRECT(CONCATENATE("AW",_xlpm.minindex2,":AW300")), _xlpm.maxindex2, MIN(IF(_xlpm.fullcolumnrnge2="",ROW(_xlpm.fullcolumnrnge2)))-1, _xlpm.addminx2, INDIRECT(CONCATENATE("AW", _xlpm.minindex2,":BD", _xlpm.maxindex2)), _xlpm.minindex3, MATCH(Data_Constants!C15, $BJ$2:$BJ$300,0)+3, _xlpm.fullcolumnrnge3, INDIRECT(CONCATENATE("BJ",_xlpm.minindex3,":BJ300")), _xlpm.maxindex3, MIN(IF(_xlpm.fullcolumnrnge3="",ROW(_xlpm.fullcolumnrnge3)))-1, _xlpm.addminx3, INDIRECT(CONCATENATE("BJ", _xlpm.minindex3,":BN", _xlpm.maxindex3)), _xlpm.rnge1, IF(OR(ISBLANK(_xlpm.addminx1),(_xlfn.CHOOSECOLS(_xlpm.addminx1,1,2,5,6,7))="NA"),0,1), _xlpm.rnge2, IF(OR(ISBLANK(_xlpm.addminx2),(_xlpm.addminx2)="NA"),0,1), _xlpm.rnge3, IF(OR(ISBLANK(_xlpm.addminx3),(_xlpm.addminx3)="NA"),0,1), IF(AND(MIN(_xlpm.rnge1)=0,MIN(_xlpm.rnge2)=0,MIN(_xlpm.rnge3)=0),Data_Constants!D83, IF( AND(MIN(_xlpm.rnge1)=0,OR(MIN(_xlpm.rnge2)=1,MIN(_xlpm.rnge3)=1) ),Data_Constants!C83, IF(MIN(_xlpm.rnge1)=1,IF(OR(COUNTIF(_xlpm.txnDesccolumnrnge,_xlpm.txnDesccolumnrnge)>1) = TRUE,Data_Constants!D85,Data_Constants!C85)))))} | F40: =IF(E40=Data_Constants!D85, FALSE, TRUE)
B41: 34 | C41: Response Times - Batch Jobs – Requirements | D41: =Data_Constants!C133 | E41: {=_xlfn.LET( _xlpm.minindex1, MATCH(Data_Constants!C11, $AJ$2:$AJ$300,0)+3, _xlpm.fullcolumnrnge1, INDIRECT(CONCATENATE("AJ",_xlpm.minindex1,":AJ300")), _xlpm.maxindex1, MIN(IF(_xlpm.fullcolumnrnge1="",ROW(_xlpm.fullcolumnrnge1)))-1, _xlpm.addminx1, INDIRECT(CONCATENATE("AJ", _xlpm.minindex1,":AP", _xlpm.maxindex1)), _xlpm.minindex3, MATCH(Data_Constants!C15, $BJ$2:$BJ$300,0)+3, _xlpm.fullcolumnrnge3, INDIRECT(CONCATENATE("BJ",_xlpm.minindex3,":BJ300")), _xlpm.maxindex3, MIN(IF(_xlpm.fullcolumnrnge3="",ROW(_xlpm.fullcolumnrnge3)))-1, _xlpm.addminx3, INDIRECT(CONCATENATE("BJ", _xlpm.minindex3,":BN", _xlpm.maxindex3)), _xlpm.minindex2, MATCH(Data_Constants!C13, $AW$2:$AW$300,0)+3, _xlpm.fullcolumnrnge2, INDIRECT(CONCATENATE("AW",_xlpm.minindex2,":AW300")), _xlpm.maxindex2, MIN(IF(_xlpm.fullcolumnrnge2="",ROW(_xlpm.fullcolumnrnge2)))-1, _xlpm.addminx2, INDIRECT(CONCATENATE("AW", _xlpm.minindex2,":BD", _xlpm.maxindex2)), _xlpm.slaColumnrnge, INDIRECT(CONCATENATE("AZ",_xlpm.minindex2,":AZ",_xlpm.maxindex2)), _xlpm.batchjobs, INDIRECT(CONCATENATE("AX",_xlpm.minindex2,":AX",_xlpm.maxindex2)), _xlpm.rnge1, IF(OR(ISBLANK(_xlpm.addminx1),(_xlfn.CHOOSECOLS(_xlpm.addminx1,1,2,5,6,7))="NA"),0,1), _xlpm.rnge3, IF(OR(ISBLANK(_xlpm.addminx3),(_xlpm.addminx3)="NA"),0,1), _xlpm.rnge2, IF(OR(ISBLANK(_xlpm.addminx2),(_xlpm.addminx2)="NA"),0,1), IF(AND(MIN(_xlpm.rnge1)=0,MIN(_xlpm.rnge2)=0,MIN(_xlpm.rnge3)=0),Data_Constants!D65, IF(AND(MIN(_xlpm.rnge2)=0,OR(MIN(_xlpm.rnge1)=1,MIN(_xlpm.rnge3)=1) ),Data_Constants!C65, IF(MIN(_xlpm.rnge2)=1,IF(OR(COUNTIF(_xlpm.batchjobs,_xlpm.batchjobs)>1) = TRUE,Data_Constants!D86,Data_Constants!C86)))))} | F41: =IF(E41=Data_Constants!D86, FALSE, TRUE)
B42: 35 | C42: Response Times - Reports – Requirements | D42: =Data_Constants!C134 | E42: {=_xlfn.LET( _xlpm.minindex1, MATCH(Data_Constants!C11, $AJ$2:$AJ$300,0)+3, _xlpm.fullcolumnrnge1, INDIRECT(CONCATENATE("AJ",_xlpm.minindex1,":AJ300")), _xlpm.maxindex1, MIN(IF(_xlpm.fullcolumnrnge1="",ROW(_xlpm.fullcolumnrnge1)))-1, _xlpm.addminx1, INDIRECT(CONCATENATE("AJ", _xlpm.minindex1,":AP", _xlpm.maxindex1)), _xlpm.minindex2, MATCH(Data_Constants!C13, $AW$2:$AW$300,0)+3, _xlpm.fullcolumnrnge2, INDIRECT(CONCATENATE("AW",_xlpm.minindex2,":AW300")), _xlpm.maxindex2, MIN(IF(_xlpm.fullcolumnrnge2="",ROW(_xlpm.fullcolumnrnge2)))-1, _xlpm.addminx2, INDIRECT(CONCATENATE("AW", _xlpm.minindex2,":BD", _xlpm.maxindex2)), _xlpm.minindex3, MATCH(Data_Constants!C15, $BJ$2:$BJ$300,0)+3, _xlpm.fullcolumnrnge3, INDIRECT(CONCATENATE("BJ",_xlpm.minindex3,":BJ300")), _xlpm.maxindex3, MIN(IF(_xlpm.fullcolumnrnge3="",ROW(_xlpm.fullcolumnrnge3)))-1, _xlpm.addminx3, INDIRECT(CONCATENATE("BJ", _xlpm.minindex3,":BN", _xlpm.maxindex3)), _xlpm.slaColumnrnge, INDIRECT(CONCATENATE("BM",_xlpm.minindex3,":BM",_xlpm.maxindex3)), _xlpm.reportdes, INDIRECT(CONCATENATE("BK",_xlpm.minindex3,":BK",_xlpm.maxindex3)), _xlpm.rnge1, IF(OR(ISBLANK(_xlpm.addminx1),(_xlfn.CHOOSECOLS(_xlpm.addminx1,1,2,5,6,7))="NA"),0,1), _xlpm.rnge2, IF(OR(ISBLANK(_xlpm.addminx2),(_xlpm.addminx2)="NA"),0,1), _xlpm.rnge3, IF(OR(ISBLANK(_xlpm.addminx3),(_xlpm.addminx3)="NA"),0,1), _xlpm.rnge4, IF(ISNUMBER(_xlpm.slaColumnrnge), IF(_xlpm.slaColumnrnge=0, 0,1)), IF(AND(MIN(_xlpm.rnge1)=0,MIN(_xlpm.rnge2)=0,MIN(_xlpm.rnge3)=0),Data_Constants!D56, IF(AND(MIN(_xlpm.rnge3)=0,OR(MIN(_xlpm.rnge1)=1,MIN(_xlpm.rnge2)=1) ),Data_Constants!C56, IF(MIN(_xlpm.rnge3)=1, IF(OR(COUNTIF(_xlpm.reportdes,_xlpm.reportdes)>1) = TRUE,Data_Constants!D87,Data_Constants!C87)))))} | F42: =IF(E42=Data_Constants!D87, FALSE, TRUE)
B43: 36 | C43: Response Times - Reports – Requirements | D43: Validates the following 1. The sum of concurrent users for report transactions must be less than or equal to the sum of concurrent users at peak load anticipated for the system | E43: {=_xlfn.LET( _xlpm.minindex1, MATCH(Data_Constants!C7, $V$2:$V$300,0)+3, _xlpm.fullcolumnrnge1, INDIRECT(CONCATENATE("V",_xlpm.minindex1,":V300")), _xlpm.maxindex1, MIN(IF(_xlpm.fullcolumnrnge1="",ROW(_xlpm.fullcolumnrnge1)))-1, _xlpm.peakallwconusersColumnrnge, INDIRECT(CONCATENATE("X",_xlpm.minindex1,":X",_xlpm.maxindex1)), _xlpm.minindex2, MATCH(Data_Constants!C11, $AJ$2:$AJ$300,0)+3, _xlpm.fullcolumnrnge2, INDIRECT(CONCATENATE("AJ",_xlpm.minindex2,":AJ300")), _xlpm.t_maxindex2, MIN(IF(_xlpm.fullcolumnrnge2="",ROW(_xlpm.fullcolumnrnge2)))-1, _xlpm.maxindex2, IF(_xlpm.t_maxindex2 < _xlpm.minindex2, _xlpm.minindex2, _xlpm.t_maxindex2), _xlpm.addminx2, INDIRECT(CONCATENATE("AJ", _xlpm.minindex2,":AP", _xlpm.maxindex2)), _xlpm.onlinetxnconusersColumnrnge, IF(_xlpm.t_maxindex2 < _xlpm.minindex2, 0, INDIRECT(CONCATENATE("AP",_xlpm.minindex2,":AP",_xlpm.maxindex2))), _xlpm.minindex3, MATCH(Data_Constants!C14, $BJ$2:$BJ$300,0)+3, _xlpm.fullcolumnrnge3, INDIRECT(CONCATENATE("BJ",_xlpm.minindex3,":BJ300")), _xlpm.t_maxindex3, MIN(IF(_xlpm.fullcolumnrnge3="",ROW(_xlpm.fullcolumnrnge3)))-1, _xlpm.maxindex3, IF(_xlpm.t_maxindex3 < _xlpm.minindex3, _xlpm.minindex3, _xlpm.t_maxindex3), _xlpm.onlinerptconusersColumnrnge, IF(_xlpm.t_maxindex3 < _xlpm.minindex3, 0, INDIRECT(CONCATENATE("BS",_xlpm.minindex3,":BS",_xlpm.maxindex3))), _xlpm.addminx3, INDIRECT(CONCATENATE("BJ", _xlpm.minindex3,":BN", _xlpm.maxindex3)), _xlpm.minindex4, MATCH(Data_Constants!C13, $AW$2:$AW$300,0)+3, _xlpm.fullcolumnrnge4, INDIRECT(CONCATENATE("AW",_xlpm.minindex4,":AW300")), _xlpm.maxindex4, MIN(IF(_xlpm.fullcolumnrnge4="",ROW(_xlpm.fullcolumnrnge4)))-1, _xlpm.addminx4, INDIRECT(CONCATENATE("AW", _xlpm.minindex4,":BD", _xlpm.maxindex4)), _xlpm.rnge1, IF(OR(ISBLANK(_xlpm.addminx2),(_xlfn.CHOOSECOLS(_xlpm.addminx2,1,2,5,6,7))="NA"),0,1), _xlpm.rnge2, IF(OR(ISBLANK(_xlpm.addminx3),(_xlpm.addminx3)="NA"),0,1), _xlpm.rnge3, IF(OR(ISBLANK(_xlpm.addminx4),(_xlpm.addminx4)="NA"),0,1), _xlpm.rnge4, IF(AND(MIN(_xlpm.rnge1)=0,MIN(_xlpm.rnge2)=1), 0,1), _xlpm.rnge5, IF(AND(MIN(_xlpm.rnge1)=0,MIN(_xlpm.rnge2)=0), 0,1), IF(AND(MIN(_xlpm.rnge1)=0,MIN(_xlpm.rnge2)=0,MIN(_xlpm.rnge3)=0),Data_Constants!D56, IF(MIN(_xlpm.rnge1)=1, "", IF(MIN(_xlpm.rnge5)=0, Data_Constants!C56, IF(MIN(_xlpm.rnge4)=0, IF(SUM(VALUE(_xlpm.peakallwconusersColumnrnge))=SUM(_xlpm.onlinerptconusersColumnrnge), Data_Constants!C41, Data_Constants!D41))))))} | F43: =IF(OR(E43=Data_Constants!D41,E43=Data_Constants!D56), FALSE, TRUE)
D46: Check Name of the QOPD file | E46: {=_xlfn.LET(_xlpm.tcsUnitRaw, 'Asset Info'!B8, _xlpm.tcsUnitLeftBraceSubs, SUBSTITUTE(_xlpm.tcsUnitRaw,"(","-",1), _xlpm.tcsUnitLeftRightBraceSubs, SUBSTITUTE(_xlpm.tcsUnitLeftBraceSubs,")","",1), _xlpm.tcsUnitLeftRightBraceDotSubs, SUBSTITUTE(_xlpm.tcsUnitLeftBraceSubs,".","-",1), _xlpm.tcsUnit_Space_L_R_BraceDotSubs, SUBSTITUTE(_xlpm.tcsUnitLeftRightBraceDotSubs," ","",1), _xlpm.tcsUnit_Amp_S_L_R_BraceDotSubs, SUBSTITUTE(_xlpm.tcsUnit_Space_L_R_BraceDotSubs,"&","_n_",1), _xlpm.assetNameRaw, 'Asset Info'!B3, _xlpm.assetNameLeftBraceSubs, SUBSTITUTE(_xlpm.assetNameRaw,"(","-",1), _xlpm.assetNameLeftRightBraceSubs, SUBSTITUTE(_xlpm.assetNameLeftBraceSubs,")","",1), _xlpm.assetNameLeftRightBraceDotSubs, SUBSTITUTE(_xlpm.assetNameLeftBraceSubs,".","-",1), _xlpm.assetName_Space_L_R_BraceDotSubs, SUBSTITUTE(_xlpm.assetNameLeftRightBraceDotSubs," ","",1), _xlpm.assetName_Amp_S_L_R_BraceDotSubs, SUBSTITUTE(_xlpm.assetName_Space_L_R_BraceDotSubs,"&","_n_",1), _xlpm.versionNoRaw, 'Asset Info'!B4, _xlpm.versionNoLeftBraceSubs, SUBSTITUTE(_xlpm.versionNoRaw,"(","-",1), _xlpm.versionNoLeftRightBraceSubs, SUBSTITUTE(_xlpm.versionNoLeftBraceSubs,")","",1), _xlpm.versionNoLeftRightBraceDotSubs, SUBSTITUTE(_xlpm.versionNoLeftBraceSubs,".","-",1), _xlpm.monthMMMM, LEFT(TEXT(TODAY(),"MMMM"),3), _xlpm.yearYYYY, YEAR(TODAY()), _xlpm.fileNameFinal, CONCATENATE(_xlpm.tcsUnit_Amp_S_L_R_BraceDotSubs,"_",_xlpm.assetName_Amp_S_L_R_BraceDotSubs,"_",_xlpm.versionNoLeftRightBraceDotSubs,"_Performance_QOPD_",_xlpm.monthMMMM,"_",_xlpm.yearYYYY,".xlsx"), _xlpm.fileNameFinal)}
A50: Product/ Project Synopsis | H50: Deployment Requirements | O50: Software Stack - Information | V50: User Types – Requirements | AD50: Channels - Information | AJ50: Response Times - Online Txns – Requirements | AW50: Response Times - Batch Jobs – Requirements | BJ50: Response Times - Reports – Requirements | BY50: Response Times - Data – Requirements | CJ50: Data Management – Requirements | CP50: Resource Utilization – Requirements
A51: {=_xlfn.LET(_xlpm.fullrnge1, INDIRECT(CONCATENATE("'Asset Info'!A",Data_Constants!E23,":B", Data_Constants!E24)), _xlpm.arnge1, INDIRECT(CONCATENATE("'Asset Info'!A",Data_Constants!E23,":A", Data_Constants!E24)), _xlfn._xlws.FILTER(_xlpm.fullrnge1,(_xlpm.arnge1<>Data_Constants!C24)*(_xlpm.arnge1<>""), "No Match"))} | H51: {=_xlfn.LET(_xlpm.fullrnge1, INDIRECT(CONCATENATE("Performance!B",Data_Constants!E3,":F", Data_Constants!E4)), _xlpm.brnge1, INDIRECT(CONCATENATE("Performance!B",Data_Constants!E3,":B", Data_Constants!E4)), _xlpm.crnge1, INDIRECT(CONCATENATE("Performance!C",Data_Constants!E3,":C", Data_Constants!E4)), _xlfn._xlws.FILTER(_xlpm.fullrnge1,(_xlpm.brnge1<>Data_Constants!C3)*(_xlpm.brnge1<>Data_Constants!C4)*(_xlpm.brnge1<>""), "No Match"))} | O51: {=_xlfn.LET(_xlpm.fullrnge1, INDIRECT(CONCATENATE("Performance!B",Data_Constants!E5,":F", Data_Constants!E6)), _xlpm.drnge1, INDIRECT(CONCATENATE("Performance!D",Data_Constants!E5,":D", Data_Constants!E6)), _xlpm.brnge1, INDIRECT(CONCATENATE("Performance!B",Data_Constants!E5,":B", Data_Constants!E6)), _xlfn._xlws.FILTER(_xlpm.fullrnge1,(_xlpm.drnge1<>""), "Software Stack is improperly defined"))} | V51: {=_xlfn.LET(_xlpm.fullrnge1, INDIRECT(CONCATENATE("Performance!B",Data_Constants!E7,":G", Data_Constants!E8)), _xlpm.brnge1, INDIRECT(CONCATENATE("Performance!B",Data_Constants!E7,":B", Data_Constants!E8)), _xlfn._xlws.FILTER(_xlpm.fullrnge1,(_xlpm.brnge1<>"")*(_xlpm.brnge1<>Data_Constants!C6)*(_xlpm.brnge1<>Data_Constants!C7)*(_xlpm.brnge1<>Data_Constants!C8), "User Types – Requirements is improperly defined"))} | AD51: {=_xlfn.LET(_xlpm.fullrnge1, INDIRECT(CONCATENATE("Performance!B",Data_Constants!E9,":D", Data_Constants!E10)), _xlpm.brnge1, INDIRECT(CONCATENATE("Performance!B",Data_Constants!E9,":B", Data_Constants!E10)), _xlpm.crnge1, INDIRECT(CONCATENATE("Performance!C",Data_Constants!E9,":C", Data_Constants!E10)),_xlfn._xlws.FILTER(_xlpm.fullrnge1,((_xlpm.brnge1<>Data_Constants!C8)*(_xlpm.brnge1<>Data_Constants!C9)*(_xlpm.brnge1<>Data_Constants!C10))*(_xlpm.crnge1<>"NA"), "Channels - Information is improperly defined"))} | AJ51: {=_xlfn.LET(_xlpm.fullrnge1, INDIRECT(CONCATENATE("Performance!B",Data_Constants!E11,":L", Data_Constants!E12)), _xlpm.brnge1, INDIRECT(CONCATENATE("Performance!B",Data_Constants!E11,":B", Data_Constants!E12)), _xlpm.mandatoryrnge1, INDIRECT(CONCATENATE("Performance!C",Data_Constants!E11,":C", Data_Constants!E12)), _xlpm.frnge1, INDIRECT(CONCATENATE("Performance!F",Data_Constants!E11,":F", Data_Constants!E12)), _xlfn._xlws.FILTER(_xlpm.fullrnge1,(_xlpm.mandatoryrnge1<>0)*(_xlpm.brnge1<>Data_Constants!C11)*(_xlpm.brnge1<>Data_Constants!C12), "Response Times - Online Txns – Requirements is improperly defined"))} | AW51: {=_xlfn.LET(_xlpm.fullrnge1, INDIRECT(CONCATENATE("Performance!B",Data_Constants!E13,":L", Data_Constants!E14)), _xlpm.brnge1, INDIRECT(CONCATENATE("Performance!B",Data_Constants!E13,":B", Data_Constants!E14)), _xlpm.mandatoryrnge1, INDIRECT(CONCATENATE("Performance!C",Data_Constants!E13,":C", Data_Constants!E14)), _xlfn._xlws.FILTER(_xlpm.fullrnge1,(_xlpm.mandatoryrnge1<>0)*(_xlpm.brnge1<>Data_Constants!C13)*(_xlpm.brnge1<>Data_Constants!C14), "Response Times - Batch Jobs – Requirements is improperly defined"))} | BJ51: {=_xlfn.LET(_xlpm.fullrnge1, INDIRECT(CONCATENATE("Performance!B",Data_Constants!E15,":N", Data_Constants!E16)), _xlpm.brnge1, INDIRECT(CONCATENATE("Performance!B",Data_Constants!E15,":B", Data_Constants!E16)), _xlpm.mandatoryrnge1, INDIRECT(CONCATENATE("Performance!C",Data_Constants!E15,":C",Data_Constants!E16)), _xlfn._xlws.FILTER(_xlpm.fullrnge1,(_xlpm.mandatoryrnge1<>0)*(_xlpm.brnge1<>Data_Constants!C15)*(_xlpm.brnge1<>Data_Constants!C16), "Response Times - Reports – Requirements is improperly defined"))} | BY51: {=_xlfn.LET(_xlpm.fullrnge1, INDIRECT(CONCATENATE("Performance!B",Data_Constants!E17,":K",Data_Constants!E18)), _xlpm.brnge1, INDIRECT(CONCATENATE("Performance!B",Data_Constants!E17,":B",Data_Constants!E18)), _xlpm.mandatoryrnge1, INDIRECT(CONCATENATE("Performance!D",Data_Constants!E17,":D",Data_Constants!E18)), _xlfn._xlws.FILTER(_xlpm.fullrnge1,(_xlpm.mandatoryrnge1<>0)*(_xlpm.brnge1<>Data_Constants!C17)*(_xlpm.brnge1<>Data_Constants!C18),"Response Times - Data - Requirements is improperly defined"))} | CJ51: {=_xlfn.LET(_xlpm.fullrnge1, INDIRECT(CONCATENATE("Performance!B",Data_Constants!E19,":E", Data_Constants!E20)), _xlpm.brnge1, INDIRECT(CONCATENATE("Performance!B",Data_Constants!E19,":B", Data_Constants!E20)), _xlpm.drnge1, INDIRECT(CONCATENATE("Performance!D",Data_Constants!E19,":D", Data_Constants!E20)), _xlfn._xlws.FILTER(_xlpm.fullrnge1,((_xlpm.brnge1<>0)*(_xlpm.brnge1<>Data_Constants!C19)*(_xlpm.brnge1<>Data_Constants!C20)), "Data Management – Requirements is improperly defined"))} | CP51: {=_xlfn.LET(_xlpm.fullrnge1, INDIRECT(CONCATENATE("Performance!B",Data_Constants!E21,":E", Data_Constants!E22)), _xlpm.brnge1, INDIRECT(CONCATENATE("Performance!B",Data_Constants!E21,":B", Data_Constants!E22)), _xlpm.drnge1, INDIRECT(CONCATENATE("Performance!D",Data_Constants!E21,":D", Data_Constants!E22)), _xlfn._xlws.FILTER(_xlpm.fullrnge1,((_xlpm.brnge1<>0)*(_xlpm.brnge1<>Data_Constants!C21)*(_xlpm.brnge1<>Data_Constants!C25)), "Resource Utilization is improperly defined"))} | CV51: Deployment Requirements | DE51: Software Stack - Information
CV52: {=_xlfn.LET( _xlpm.fullrnge1, INDIRECT(CONCATENATE("Performance!B",Data_Constants!O18,":F", Data_Constants!O18)), _xlpm.crnge1, INDIRECT(CONCATENATE("Performance!C",Data_Constants!O18,":C", Data_Constants!O18)), _xlpm.brnge1, INDIRECT(CONCATENATE("Performance!B",Data_Constants!O18,":B", Data_Constants!O18)), _xlfn._xlws.FILTER(_xlpm.fullrnge1,(_xlpm.crnge1<>""), 0))} | DE52: {=_xlfn.LET( _xlpm.fullrnge1, INDIRECT(CONCATENATE("Performance!B",Data_Constants!N20,":F", Data_Constants!N20)), _xlpm.drnge1, INDIRECT(CONCATENATE("Performance!D",Data_Constants!N20,":D", Data_Constants!N20)), _xlpm.brnge1, INDIRECT(CONCATENATE("Performance!B",Data_Constants!N20,":B", Data_Constants!N20)), _xlfn._xlws.FILTER(_xlpm.fullrnge1,(_xlpm.drnge1<>""), "0"))}
CV53: {=_xlfn.LET( _xlpm.fullrnge1, INDIRECT(CONCATENATE("Performance!B",Data_Constants!N24,":F", Data_Constants!N24)), _xlpm.crnge1, INDIRECT(CONCATENATE("Performance!C",Data_Constants!N24,":C", Data_Constants!N24)), _xlpm.brnge1, INDIRECT(CONCATENATE("Performance!B",Data_Constants!N24,":B", Data_Constants!N24)), _xlfn._xlws.FILTER(_xlpm.fullrnge1,(_xlpm.crnge1<>""), 0))} | DE53: {=_xlfn.LET( _xlpm.fullrnge1, INDIRECT(CONCATENATE("Performance!B",Data_Constants!N25,":F", Data_Constants!N25)), _xlpm.crnge1, INDIRECT(CONCATENATE("Performance!C",Data_Constants!N25,":C", Data_Constants!N25)), _xlpm.brnge1, INDIRECT(CONCATENATE("Performance!B",Data_Constants!N25,":B", Data_Constants!N25)), _xlfn._xlws.FILTER(_xlpm.fullrnge1,(_xlpm.crnge1<>""), 0))}
CV54: {=_xlfn.LET( _xlpm.fullrnge1, INDIRECT(CONCATENATE("Performance!B",Data_Constants!N26,":F", Data_Constants!N26)), _xlpm.crnge1, INDIRECT(CONCATENATE("Performance!C",Data_Constants!N26,":C", Data_Constants!N26)), _xlpm.brnge1, INDIRECT(CONCATENATE("Performance!B",Data_Constants!N26,":B", Data_Constants!N26)), _xlfn._xlws.FILTER(_xlpm.fullrnge1,(_xlpm.crnge1<>""), 0))} | DE54: {=_xlfn.LET( _xlpm.fullrnge1, INDIRECT(CONCATENATE("Performance!B",Data_Constants!N27,":F", (Data_Constants!N27)+1)), _xlpm.crnge1, INDIRECT(CONCATENATE("Performance!C",Data_Constants!N27,":C", (Data_Constants!N27)+1)), _xlpm.brnge1, INDIRECT(CONCATENATE("Performance!B",Data_Constants!N27,":B", (Data_Constants!N27)+1)), _xlfn._xlws.FILTER(_xlpm.fullrnge1,(_xlpm.crnge1<>""), 0))}
M120: {=_xlfn.LET( _xlpm.fullrnge1, INDIRECT(CONCATENATE("Performance!B",Data_Constants!N25,":F", Data_Constants!N25)), _xlpm.softwarestackColumnrnge, INDIRECT(CONCATENATE("Performance!D",Data_Constants!N25,":D", Data_Constants!N25)), _xlpm.WebServerRange, INDIRECT(CONCATENATE("Data_Constants!AI3",":AI31")), _xlpm.WebServerCheckOutcomeList, COUNTIF(_xlpm.softwarestackColumnrnge,"*"&_xlpm.WebServerRange&"*"), _xlpm.hasWebServer, IF(MAX(_xlpm.WebServerCheckOutcomeList)=0,FALSE, TRUE), _xlpm.hasWebServer)}

Sheet Data_Constants
A2: Sl. No. | B2: Table | C2: Table Limiters | D2: Attribute | E2: Value | G2: Sl. No. | H2: Symbol | I2: Value | J2: Code | L2: Sl. No. | M2: Utility Constant | N2: Value | Q2: Column1 | R2: Column2 | S2: Column3 | T2: Column4 | U2: Column5 | V2: Column6 | W2: Column7 | X2: Column8 | AB2: Sl. No. | AC2: Database | AE2: Sl. No. | AF2: Application Server | AH2: Sl. No. | AI2: Web Server
A3: 1 | B3: Deployment Requirements | C3: Deployment Requirements | D3: Row Position | E3: =MATCH(C3, Performance!$B$2:$B$313,0)+1 | G3: 1 | H3: Opening Brace | I3: =""&CHAR(40) | J3: =CODE(I3) | L3: 1 | M3: Number of characters in 'Product Description' | N3: 100 | Q3: Sl. No. | R3: Table | S3: Column Heading | T3: Input Message | V3: Error Alert | X3: Formula | AB3: 1 | AC3: Azure CosmosDB | AE3: 1 | AF3: Amazon web services | AH3: 1 | AI3: Amazon Web services
A4: 2 | B4: Deployment Requirements | C4: Mention if the product needs to work in alternative technologies as well | D4: Row Position | E4: =MATCH(C4, Performance!$B$2:$B$313,0)+1 | G4: 2 | H4: Closing Brace | I4: =""&CHAR(41) | J4: =CODE(I4) | L4: 2 | M4: Sum percentage of load through Channels | N4: 100 | T4: Title | U4: Message | V4: Alert Title | W4: Alert Message | AB4: 2 | AC4: Azure SQL | AE4: 2 | AF4: Apache Tomcat | AH4: 2 | AI4: Angular
A5: 3 | B5: Software Stack - Information | C5: Software Stack - Information | D5: Row Position | E5: =MATCH(C5, Performance!$B$2:$B$313,0)+1 | G5: 3 | H5: Space | I5: =""&CHAR(32) | J5: =CODE(I5) | L5: 3 | M5: Transaction Description | N5: 5 | Q5: 1 | R5: Asset Info | S5: Description | T5: Description | U5: Provide the description - text value of length greater than or equal to 100 is allowed. | V5: Description | W5: The description is not a text value complying to the character length constraints. | X5: AND(ISTEXT(B4),LEN(B4)>=100) | AB5: 3 | AC5: Azure SQL Database | AE5: 3 | AF5: apache-tomcat | AH5: 3 | AI5: Apache HTTP Server
A6: 4 | B6: Software Stack - Information | C6: Concurrent users is the count of users who are in the middle of business transactions at any given time. Note that a business transaction can consist of multiple web pages. | D6: Row Position | E6: =MATCH(C6, Performance!$B$2:$B$313,0)+1 | G6: 4 | H6: Dot | I6: =""&CHAR(46) | J6: =CODE(I6) | L6: 4 | M6: SLA to USLA ratio | N6: 1.6 | Q6: 2 | R6: Deployment Requirements | S6: Server | T6: Server | U6: Provide the category of Server - text value of length greater than or equal to 5 is allowed. | V6: Server | W6: The category of Server is not a text value complying to the character length constraints. | X6: AND(ISTEXT(B6),LEN(B6)>=5) | AB6: 4 | AC6: Azure SQL DB | AE6: 4 | AF6: C Sharp | AH6: 4 | AI6: Apache Tomcat
A7: 5 | B7: User Types – Requirements | C7: User Types – Requirements | D7: Row Position | E7: =MATCH(C7, Performance!$B$2:$B$313,0)+1 | L7: 5 | M7: Standard Web page response time in seconds | N7: 5 | Q7: 3 | R7: Deployment Requirements | S7: Number of Instances | T7: Number of Instances | U7: Number of Instances must be a non-zero numeric integer value. Enter "NA" if that does not apply. | V7: Number of Instances | W7: Number of Instances is neither a non-zero numeric integer value, nor entered as "NA". | X7: OR(C6="NA", IF(AND(ISNUMBER(C6),C6<>0), INT(C6)=C6, FALSE)) | AB7: 5 | AC7: CosmosDB | AE7: 5 | AF7: CDP Dashboard | AH7: 5 | AI7: Apache Tomcat Embeded(API) and Apache Tomcat for UI
A8: 6 | B8: User Types – Requirements | C8: All the modes of accessing the asset | D8: Row Position | E8: =MATCH(C8, Performance!$B$2:$B$313,0)+1 | L8: 6 | M8: Minimum time threshold in seconds for batch job completion | N8: 60 | Q8: 4 | R8: Deployment Requirements | S8: CPU cores | T8: CPU cores | U8: CPU cores must be a non-zero numeric integer or decimal value. Enter "NA" if that does not apply. | V8: CPU cores | W8: CPU cores is neither a non-zero numeric integer or decimal value, nor entered as "NA". | X8: IF(ISNUMBER(C6), AND(ISNUMBER(D6),D6<>0), IF(C6="NA", D6="NA", FALSE)) | AB8: 6 | AC8: CouchDB | AE8: 6 | AF8: Django | AH8: 6 | AI8: Apache-Tomcat
A9: 7 | B9: Channels - Information | C9: Channels - Information | D9: Row Position | E9: =MATCH(C9, Performance!$B$2:$B$313,0)+1 | G9: Sl. No. | H9: Time Unit | I9: Notation | L9: 7 | M9: Minimum count of estimated records in top three largest populated tables | N9: 100 | Q9: 5 | R9: Deployment Requirements | S9: RAM | T9: RAM | U9: RAM must be a non-zero numeric integer or decimal value. Enter "NA" if that does not apply. | V9: RAM | W9: RAM is neither a non-zero numeric integer or decimal value, nor entered as "NA". | X9: IF(ISNUMBER(C6), AND(ISNUMBER(E6),E6<>0), IF(C6="NA", E6="NA", FALSE)) | AB9: 7 | AC9: DocumentDB | AE9: 7 | AF9: Embedded Tomcat | AH9: 7 | AI9: AWS CloudFront
A10: 8 | B10: Channels - Information | C10: Ensure that in the subsequent tables, all the above applicable channels are considered while arriving at Transactions | D10: Row Position | E10: =MATCH(C10, Performance!$B$2:$B$313,0)+1 | G10: 1 | H10: hour | I10: h | L10: 8 | M10: Minimum count of concurrent users for auto-approval | N10: 1 | Q10: 6 | R10: Software Stack - Information | S10: Name | T10: Name | U10: Provide the name of the Software component - alpha numeric value of length greater than or equal to 3 is allowed. | V10: Name | W10: The value of name of the Software component is not an alpha-numeric value complying to the character length constraints. | X10: AND(ISTEXT(D20), LEN(D20)>=3) | AB10: 8 | AC10: Dynamo DB | AE10: 8 | AF10: Express JS | AH10: 8 | AI10: Azure App Service
A11: 9 | B11: Response Times - Online Txns – Requirements | C11: Response Times - Online Txns – Requirements | D11: Row Position | E11: =MATCH(C11, Performance!$B$2:$B$313,0)+1 | G11: 2 | H11: minute | I11: m | L11: 9 | M11: Maximum count of concurrent users for auto-approval | N11: 200 | Q11: 7 | R11: Software Stack - Information | S11: Version | T11: Version | U11: Provide the version of the Software component - alpha numeric value allowed | V11: Version | W11: The value of version is not an alpha-numeric value | X11: IF(E20="", TRUE, IF(AND(ISTEXT(E20), LEN(E20)>=1, E20<>"NA"),TRUE,IF(AND(ISNUMBER(E20),E20<>0),TRUE,FALSE))) | AB11: 9 | AC11: Elasticsearch | AE11: 9 | AF11: FAST API | AH11: 9 | AI11: Azure AppService (Azure Cloud)
A12: 10 | B12: Response Times - Online Txns – Requirements | C12: Response Times - Batch Jobs – Requirements | D12: Row Position | E12: =MATCH(C12, Performance!$B$2:$B$313,0)+1 | G12: 3 | H12: second | I12: s | L12: 3 | M12: Minimum brand name length | N12: 3 | Q12: 8 | R12: User Types – Requirements | S12: Total number of users | T12: Total number of users | U12: Total number of users of each type must be numeric integer value greater than or equal to 1. | V12: Total number of users | W12: Total number of users of each type is not a numeric integer value greater than or equal to 1. | X12: Whole number >= 1 | AB12: 10 | AC12: EnterpriseDB Advanced Server | AE12: 10 | AF12: FastAPI | AH12: 10 | AI12: Azure Data Factory
A13: 11 | B13: Response Times - Batch Jobs – Requirements | C13: Response Times - Batch Jobs – Requirements | D13: Row Position | E13: =MATCH(C13, Performance!$B$2:$B$313,0)+1 | G13: 4 | H13: second | I13: sec | L13: 4 | M13: TIPAR ID length | N13: 19 | Q13: 9 | R13: User Types – Requirements | S13: Users concurrenctly doing a txn | T13: Users concurrenctly doing a txn | U13: Users concurrently doing a transaction during peak usage time must be equal to or less than total number of users in each type. | V13: Users concurrenctly doing a txn | W13: Users concurrently doing a transaction during peak usage time is not equal to or less than the total number of users in each type. | X13: Whole number <= Total number of users | AB13: 11 | AC13: IBM DB2 LUW | AE13: 11 | AF13: Flask | AH13: 11 | AI13: Azure ML Studio
A14: 12 | B14: Response Times - Batch Jobs – Requirements | C14: Response Times - Reports – Requirements | D14: Row Position | E14: =MATCH(C14, Performance!$B$2:$B$313,0)+1 | Q14: 10 | R14: User Types – Requirements | S14: Concurrent user % growth - Year 3 | T14: Concurrent user % growth-Year 3 | U14: Concurrent user % growth-Year 3' is not a mandatory field. If known, provide its value as a whole number, else enter "NA". | V14: Concurrent user % growth-Year 3 | W14: Concurrent user % growth-Year 3' is neither a whole number, nor entered as "NA". | X14: OR(E51="NA", IF(ISNUMBER(E51), INT(E51)=E51, FALSE)) | AB14: 12 | AC14: influxdb client | AE14: 12 | AF14: Flask-RESTPlus | AH14: 12 | AI14: Azure Web Apps
A15: 13 | B15: Response Times - Reports – Requirements | C15: Response Times - Reports – Requirements | D15: Row Position | E15: =MATCH(C15, Performance!$B$2:$B$313,0)+1 | Q15: 11 | R15: User Types – Requirements | S15: Concurrent user % growth - Year 5 | T15: Concurrent user % growth-Year 5 | U15: Concurrent user % growth-Year 5' is not a mandatory field. If known, provide its value as a whole number, else enter "NA". | V15: Concurrent user % growth-Year 5 | W15: Concurrent user % growth-Year 5' is neither a whole number, nor entered as "NA". | X15: OR(F51="NA", IF(ISNUMBER(F51), INT(F51)=F51, FALSE)) | AB15: 13 | AC15: Kafka | AE15: 13 | AF15: Google.Events.Protobuf | AH15: 13 | AI15: CDP Dashboard (web)
A16: 14 | B16: Response Times - Reports – Requirements | C16: Response Times - Data – Requirements | D16: Row Position | E16: =MATCH(C16, Performance!$B$2:$B$313,0)+1 | G16: Sl. No. | H16: Report Type | L16: DB Server check | Q16: 12 | R16: Channels - Information | S16: What % of users will access this channel? | T16: % of users access this channel | U16: % of users accessing this channel must be numeric integer value. If not applicable, enter "NA". | V16: % of users access this channel | W16: % of users access this channel is neither a numeric integer or decimal value, nor entered as "NA". | X16: OR(C68="NA", IF(ISNUMBER(C68), INT(C68)=C68, FALSE)) | AB16: 14 | AC16: MARIA DB | AE16: 14 | AF16: Gunicorn | AH16: 14 | AI16: Django
A17: 15 | B17: Response Times - Data – Requirements | C17: Response Times - Data – Requirements | D17: Row Position | E17: =MATCH(C17, Performance!$B$2:$B$313,0)+1 | G17: 1 | H17: Scheduled | L17: Sl. No. | M17: Table Limiters | N17: Row position value | Q17: 13 | R17: Response Times - Online Txns – Requirements | S17: Transaction Description | T17: Transaction Description | U17: Provide the transaction description - text value of length greater than or equal to 5 is allowed. If the field is left blank, the corresponding row will not be considered part of the requirement. | V17: Transaction Description | W17: The transaction description is not a text value complying to the character length constraints. | X17: AND(ISTEXT(C90),LEN(C90)>=5) | AB17: 15 | AC17: Mongo | AE17: 15 | AF17: IBM WebSphere ND | AH17: 15 | AI17: Flask Web Server
A18: 16 | B18: Response Times - Data – Requirements | C18: Data Management – Requirements | D18: Row Position | E18: =MATCH(C18, Performance!$B$2:$B$313,0)+1 | G18: 2 | H18: Adhoc | L18: 1 | M18: DB Server | N18: =MATCH(M18, Performance!$B$21:$B$310,0)-1 | O18: =MATCH(M18, Performance!$B$2:$B$310,0)+1 | Q18: 14 | R18: Response Times - Online Txns – Requirements | S18: No of pages visited per transaction | T18: No of pages visited per transaction | U18: Pages visited per transaction must be either a numeric integer value or "NA". | V18: No of pages visited per transaction | W18: Pages visited per transaction is neither a numeric integer value, nor entered as "NA". | X18: OR(D90="NA", IF(ISNUMBER(D90), INT(D90)=D90, FALSE)) | AB18: 16 | AC18: Mongo DB | AE18: 6 | AF18: IIS | AH18: 16 | AI18: Gunicorn
A19: 17 | B19: Data Management – Requirements | C19: Data Management – Requirements | D19: Row Position | E19: =MATCH(C19, Performance!$B$2:$B$313,0)+1 | L19: 2 | M19: Software Stack - Information | N19: =MATCH(M19, Performance!$B$2:$B$310,0)+1 | Q19: 15 | R19: Response Times - Online Txns – Requirements | S19: No of Interactions per Transaction | T19: No of Interactions per Transaction | U19: Interactions per transaction must be either a numeric integer value, or it can be "NA" | V19: No of Interactions per Transaction | W19: Interactions per transaction is neither a numeric integer or decimal value, nor entered as "NA". | X19: OR(E90="NA", IF(ISNUMBER(E90), INT(E90)=E90, FALSE)) | AB19: 17 | AC19: MongoDB | AE19: 17 | AF19: inbuilt server of spring boot | AH19: 17 | AI19: http-server
A20: 18 | B20: Data Management – Requirements | C20: Provide this data only if utilization numbers are known from the existing asset deployed in production (or equivalent) - so that the new version should not exceed the existing utilization. | D20: Row Position | E20: =MATCH(C20, Performance!$B$2:$B$313,0)+1 | G20: Sl. No. | H20: Resource Utilization Key | I20: Threshold | L20: 3 | M20: Second occurrence of DB Server | N20: =SUM(N18+N19) | Q20: 16 | R20: Response Times - Online Txns – Requirements | S20: SLA | T20: SLA | U20: SLA must be numeric integer value. | V20: SLA | W20: SLA is not a numeric integer value. | X20: OR(F100="", INT(F100)=F100) | AB20: 8 | AC20: MySQL | AE20: 18 | AF20: JBOSS | AH20: 18 | AI20: IBM HTTP Server
A21: 19 | B21: Resource Utilization – Requirements | C21: Resource Utilization – Requirements | D21: Row Position | E21: =MATCH(C21, Performance!$B$2:$B$313,0)+1 | G21: 1 | H21: CPU Utilization | I21: 60 | L21: 4 | M21: Concurrent users is the count of users who are in the middle of business transactions at any given time. Note that a business transaction can consist of multiple web pages. | N21: =MATCH(M21, Performance!$B$2:$B$310,0)-1 | Q21: 17 | R21: Response Times - Online Txns – Requirements | S21: USLA | T21: USLA | U21: USLA must be a numeric integer value greater than or equal to SLA. | V21: USLA | W21: USLA is neither a numeric integer value, nor is it greater than or equal to SLA. | X21: Whole number >= SLA | AB21: 19 | AC21: Oracle | AE21: 19 | AF21: JBOSS - NA weblogic | AH21: 19 | AI21: IIS
A22: 20 | B22: Resource Utilization – Requirements | D22: Row Position | E22: =E21+25 | G22: 2 | H22: Memory Utilization | I22: 70 | L22: 5 | M22: Mention if the product needs to work in alternative technologies as well | N22: =MATCH(M22, Performance!$B$2:$B$310,0)-1 | Q22: 18 | R22: Response Times - Online Txns – Requirements | S22: # of concurrent users accessing the function | T22: # of concurrent users accessing the function | U22: Concurrent users must be a non-zero numeric integer value, or it can be left blank. | V22: # of concurrent users accessing the function | W22: Concurrent users is neither a non-zero numeric integer value, nor blank. | X22: OR(H90="", IF(AND(ISNUMBER(H90),H90<>0), INT(H90)=H90, FALSE)) | AB22: 20 | AC22: Npgsql | AE22: 20 | AF22: JBOSS EAP | AH22: 20 | AI22: Map Server
A23: 21 | B23: Asset Information | C23: Asset Information | D23: Row Position | E23: =MATCH(C23, 'Asset Info'!$A$1:$A$303,0)+1 | L23: Web Server check | Q23: 19 | R23: Response Times - Online Txns – Requirements | S23: Throughput (per hr) | T23: Throughput (per hr) | U23: Throughput (per hr) is not a mandatory field. If known, provide its value as a whole number, else enter "NA". | V23: Throughput (per hr) | W23: Throughput (per hr) is neither a whole number, nor entered as "NA". | X23: IF(ISNUMBER(J90), IF(INT(J90)=J90, TRUE, FALSE), IF(J90="NA", TRUE, FALSE)) | AB23: 21 | AC23: Oracle database | AE23: 21 | AF23: Map Server | AH23: 21 | AI23: Microsoft-IIS
A24: 22 | B24: Asset Information | C24: Provide the technical details of the Asset, answering the following questions | D24: Row Position | E24: =MATCH(C24, 'Asset Info'!$A$1:$A$303,0) | M24: Web Server | N24: =MATCH(M24, Performance!$B$2:$B$310,0)+1 | Q24: 20 | R24: Response Times - Online Txns – Requirements | S24: Throughput % growth-Year 3 | T24: Throughput % growth-Year 3 | U24: Throughput % growth-Year 3 is not a mandatory field. If known, provide its value as a whole number, else enter "NA". | V24: Throughput % growth-Year 3 | W24: Throughput % growth-Year 3 is neither a whole number, nor entered as "NA". | X24: OR(J90="NA", IF(ISNUMBER(J90), INT(J90)=J90, FALSE)) | AB24: 22 | AC24: Oracle Database 12c Enterprise Edition | AE24: 22 | AF24: Maven | AH24: 22 | AI24: NGINX
A25: 23 | B25: Resource Utilization – Requirements | C25: Input / Output devices Utilization | D25: Row Position | E25: =MATCH(C25, Performance!$B$2:$B$306,0)+1 | M25: Software - Web Server | N25: =MATCH(M25, Performance!$B$2:$B$310,0)+1 | Q25: 21 | R25: Response Times - Online Txns – Requirements | S25: Throughput % Growth in size - Year 5 | T25: Throughput % Growth in size - Year 5 | U25: Throughput % Growth in size - Year 5 is not a mandatory field. If known, provide its value as a whole number, else enter "NA". | V25: Throughput % Growth in size - Year 5 | W25: Throughput % Growth in size - Year 5 is neither a whole number, nor entered as "NA". | X25: IF(ISNUMBER(K90), IF(INT(K90)=K90, TRUE, FALSE), IF(K90="NA", TRUE, FALSE)) | AB25: 23 | AC25: Oracle Database 19c Enterprise Edition | AE25: 23 | AF25: NET Core | AH25: 23 | AI25: Nginz
G26: Sl. No. | H26: Application Server | J26: Sl. No. | K26: Web Server | M26: Application Server | N26: =MATCH(M26, Performance!$B$2:$B$310,0)+1 | Q26: 22 | R26: Response Times - Batch Jobs – Requirements | S26: Batch job/Transaction Description | T26: Batch job Description | U26: Provide batch job description - text value of length greater than or equal to 5 is allowed. If the field is left blank, the corresponding row will not be considered part of the requirement. | V26: Batch job Description | W26: The batch job description is not a text value complying to the character length constraints. | X26: AND(ISTEXT(C106),LEN(C106)>=5) | AB26: 24 | AC26: PG Vector | AE26: 24 | AF26: Nginx | AH26: 24 | AI26: Ngnix
G27: 1 | H27: Tomcat | J27: 1 | K27: Apache HTTP Server | M27: Second occurrence of Application Server | N27: =MATCH(M26, Performance!$B$21:$B$310,0)-1+N19-1 | Q27: 23 | R27: Response Times - Batch Jobs – Requirements | S27: Scheduling pattern(hourly/daily/weekly/fortnightly/monthly/on-demand) | T27: Scheduling pattern (hourly / daily / weekly / fortnightly/ monthly/ on-demand) | U27: Select an appropriate scheduling pattern (hourly / daily / weekly / fortnightly/ monthly/ on-demand) | V27: Scheduling pattern (hourly / daily / weekly / fortnightly/ monthly/ on-demand) | W27: Scheduling pattern is not selected | X27: Dropdown list (Hourly,Daily,Weekly,Fortnightly,Monthly,On-demand) is provided in the data validation directly. | AB27: 25 | AC27: Postgres | AE27: 25 | AF27: Node js | AH27: 25 | AI27: node.js
A28: Sl. No. | B28: Table | C28: Valid case Message | D28: Invalid case Message | E28: Column1 | F28: Column2 | G28: 2 | H28: Jboss | J28: 2 | K28: Ngnix | M28: Content/Image server | N28: =MATCH(M28, Performance!$B$2:$B$310,0) | Q28: 24 | R28: Response Times - Batch Jobs – Requirements | S28: SLA | T28: SLA | U28: SLA must be numeric integer value. | V28: SLA | W28: SLA is not a numeric integer value. | X28: OR(E106="", INT(E106)=E106) | AB28: 26 | AC28: PostgreSQL | AE28: 26 | AF28: Python | AH28: 26 | AI28: NodeJS
A29: 1 | B29: Asset Synoptics | C29: Version number for the asset is provided | D29: Cannot find the version number for the asset | G29: 3 | H29: Wildfly | J29: 3 | K29: IIS | M29: Application Server (e.g Jboss) | N29: =MATCH(M29, Performance!$C$21:$C$310,0)-1+N19-1 | Q29: 25 | R29: Response Times - Batch Jobs – Requirements | S29: USLA | T29: USLA | U29: USLA must be a numeric integer value greater than or equal to SLA. | V29: USLA | W29: USLA is neither a numeric integer value, nor is it greater than or equal to SLA. | X29: Whole number >= SLA | AB29: 27 | AC29: PostgresSQL | AE29: 27 | AF29: Python Deck Container | AH29: 27 | AI29: Play
A30: 2 | B30: Asset Synoptics | C30: Description of the asset is provided | D30: Description of the asset is not provided | Q30: 26 | R30: Response Times - Batch Jobs – Requirements | S30: Expected count of records processed | T30: Expected count of records processed | U30: Expected count of records processed must be a numeric integer value. | V30: Expected count of records processed | W30: Expected count of records processed is not a numeric integer value. | X30: IF(ISNUMBER(G106), INT(G106)=G106, FALSE) | AB30: 28 | AC30: Redis | AE30: 28 | AF30: Spring Boot | AH30: 28 | AI30: Power BI
A31: 3 | B31: Deployment Requirements | C31: Deployment Requirements are defined adequately | D31: Deployment Requirements are not defined adequately | Q31: 27 | R31: Response Times - Reports – Requirements | S31: Average size of data processed for the batch job in Mb | T31: Average size of data processed for the batch job in Mb | U31: Average size of data processed for the batch job in Mb must be a numeric integer or decimal value greater than 0. | V31: Average size of data processed for the batch job in Mb | W31: Average size of data processed for the batch job in Mb is neither a numeric integer or decimal value greater than 0, nor entered as "NA". | X31: Decimal > 0 | AB31: 29 | AC31: SQL Server | AE31: 29 | AF31: Spring Boot with embedded tomcat | AH31: 29 | AI31: React
A32: 4 | B32: Software Stack - Information | C32: Software Stack - Information is defined adequately | D32: Software Stack - Information is not defined adequately | Q32: 28 | R32: Response Times - Batch Jobs – Requirements | S32: Where is the bulk of batch output Data written to - DB or File? | T32: Where is the bulk of batch output Data written to - DB or File? | U32: Select an appropriate batch output destination (File/ DB) | V32: Where is the bulk of batch output Data written to - DB or File? | W32: Batch output destination is not selected | X32: Dropdown list (File/ DB) is provided in the data validation directly. | AB32: 30 | AC32: SQLite | AE32: 30 | AF32: Spring Cloud | AH32: 30 | AI32: Tomcat
A33: 5 | B33: Software Stack - Information | C33: Version information is defined adequately | D33: Version information is not defined adequately | Q33: 29 | R33: Response Times - Batch Jobs – Requirements | S33: % Growth in size - Year 3 | T33: % Growth in size - Year 3 | U33: % Growth in size - Year 3 is not a mandatory field. If known, provide its value as a whole number, else enter "NA". | V33: % Growth in size - Year 3 | W33: % Growth in size - Year 3 is neither a whole number, nor entered as "NA". | X33: IF(ISNUMBER(J106), IF(INT(J106)=J106, TRUE, FALSE), IF(J106="NA", TRUE, FALSE)) | AB33: 31 | AE33: 31 | AF33: Tomcat | AH33: 31 | AI33: UVICORN
A34: 6 | B34: User Types – Requirements | C34: User Types – Requirements are defined adequately | D34: User Types – Requirements are not defined adequately | Q34: 30 | R34: Response Times - Batch Jobs – Requirements | S34: % Growth in size - Year 5 | T34: % Growth in size - Year 5 | U34: % Growth in size - Year 5 is not a mandatory field. If known, provide its value as a whole number, else enter "NA". | V34: % Growth in size - Year 5 | W34: % Growth in size - Year 5 is neither a whole number, nor entered as "NA". | X34: IF(ISNUMBER(K106), IF(INT(K106)=K106, TRUE, FALSE), IF(K106="NA", TRUE, FALSE)) | AB34: 32 | AE34: 32 | AF34: Tomcat(Embedded in Spring Boot itself) | AH34: 32
A35: 7 | B35: Channels - Information | C35: Channels - Information is defined adequately | D35: Channels - Information is not defined adequately | Q35: 31 | R35: Response Times - Reports – Requirements | S35: Report Description | T35: Report Description | U35: Provide the report description - text value of length greater than or equal to 5 is allowed. If the field is left blank, the corresponding row will not be considered part of the requirement. | V35: Report Description | W35: The report description is not a text value complying to the character length constraints. | X35: AND(ISTEXT(C114),LEN(C114)>=5) | AB35: 33 | AE35: 33 | AF35: UVICORN | AH35: 33
A36: 8 | B36: Response Times - Online Txns – Requirements | C36: Transaction Description is provided | D36: Transaction Description is not provided | Q36: 32 | R36: Response Times - Reports – Requirements | S36: Report type (adhoc/scheduled) | T36: Report type | U36: Select an appropriate report type (Scheduled/ Adhoc) | V36: Report type | W36: Report type is not selected | X36: Dropdown list (adhoc/scheduled) is provided in the data validation directly. | AE36: 34 | AF36: Wildfly
A37: 9 | B37: Response Times - Online Txns – Requirements | C37: SLA for 90th Percentile Response Time (Sec) of requests is declared | D37: SLA for 90th Percentile Response Time (Sec) of requests is not declared | G37: Sl. No. | H37: Database | J37: Sl. No. | K37: Approval Status | Q37: 33 | R37: Response Times - Reports – Requirements | S37: SLA | T37: SLA | U37: SLA must be numeric integer value. | V37: SLA | W37: SLA is not a numeric integer value. | X37: OR(E114="", INT(E114)=E114) | AE37: 35
A38: 10 | B38: Response Times - Online Txns – Requirements | C38: USLA for 90th Percentile Response Time (Sec) of requests is declared | D38: USLA for 90th Percentile Response Time (Sec) of requests is not declared | G38: 1 | H38: Postgres | J38: 1 | K38: Approved | Q38: 34 | R38: Response Times - Reports – Requirements | S38: Average Report generation per hour | T38: USLA | U38: USLA must be a numeric integer value greater than or equal to SLA. | V38: USLA | W38: USLA is neither a numeric integer value, nor is it greater than or equal to SLA. | X38: Whole number >= SLA | AE38: 36
A39: 11 | B39: Response Times - Online Txns – Requirements | C39: USLA for 90th Percentile Response Time (Sec) is set adequately | D39: USLA for 90th Percentile Response Time (Sec) is not set properly | G39: 2 | H39: Oracle | J39: 2 | K39: Not Approved | Q39: 35 | R39: Response Times - Reports – Requirements | S39: Average Report generation per hour | T39: Average Report generation per hour | U39: For Average Report generation per hour provide its value as a whole number, else enter "NA". | V39: Average Report generation per hour | W39: Average Report generation per hour is neither a whole number, nor entered as "NA". | X39: IF(ISNUMBER(G114), IF(INT(G114)=G114, TRUE, FALSE), IF(G114="NA", TRUE, FALSE))
A40: 12 | B40: Response Times - Online Txns – Requirements | C40: Number of concurrent users data is a numeric integer value | D40: Number of concurrent users data is not a numeric integer value | G40: 3 | H40: MySQL | J40: 3 | K40: Conditionally Approved | Q40: 36 | R40: Response Times - Reports – Requirements | S40: Number of records in the input data set of the report | X40: No validation
A41: 13 | B41: Response Times - Online Txns – Requirements | C41: Number of concurrent users is distributed properly | D41: Number of concurrent users is not distributed properly | G41: 4 | H41: DB2 | J41: 4 | K41: Fully Approved | Q41: 37 | R41: Response Times - Reports – Requirements | S41: Number of records in the output data set of the report | X41: No validation
A42: 14 | B42: Response Times - Online Txns – Requirements | C42: 90th Percentile is above 5 secs, and rationale for the same is provided | D42: 90th Percentile is above 5 secs, and rationale for the same is not provided | G42: 5 | H42: SQL Server | Q42: 38 | R42: Response Times - Reports – Requirements | S42: Average size of Report data generated in Mb | T42: Average size of Report data generated in Mb | U42: Average size of Report data generated in Mb must be a numeric integer or decimal value greater than 0. | V42: Average size of Report data generated in Mb | W42: Average size of Report data generated in Mb is neither a numeric integer or decimal value greater than 0, nor entered as "NA". | X42: Decimal > 0
A43: 15 | B43: Response Times - Batch Jobs – Requirements | C43: Time for completion of batch job is set at or above the standard threshold of 1 min | D43: Time for completion of batch job is set below the standard threshold of 1 min | Q43: 39 | R43: Response Times - Reports – Requirements | S43: # of Concurrent Report users | T43: # of Concurrent Report users | U43: # of Concurrent Report users must be a numeric integer value, or it can be left blank. | V43: # of Concurrent Report users | W43: # of Concurrent Report users is neither a numeric integer value nor blank. | X43: OR(K114="", IF(AND(ISNUMBER(K114),K114<>0), INT(K114)=K114, FALSE))
A44: 16 | B44: Response Times - Reports – Requirements | C44: Report type of the report is set adequately | D44: Report type of the report is not set adequately | Q44: 40 | R44: Response Times - Reports – Requirements | S44: %Growth in record count or size - Year 3 | T44: %Growth in record count or size - Year 3 | U44: %Growth in record count or size - Year 3 is not a mandatory field. If known, provide its value as a whole number, else enter "NA". | V44: %Growth in record count or size - Year 3 | W44: %Growth in record count or size - Year 3 is neither a whole number, nor entered as "NA". | X44: IF(ISNUMBER(L114), IF(INT(L114)=L114, TRUE, FALSE), IF(L114="NA", TRUE, FALSE))
A45: 17 | B45: Response Times - Data – Requirements | C45: Response Times - Data - Requirements are defined adequately | D45: Response Times - Data - Requirements are not defined adequately | E45: Response Times - Data - Requirements are not defined adequately (Estimated records column range is blank) | F45: Response Times - Data - Requirements are not defined adequately (Table size is not a number) | G45: Response Times - Data - Requirements are not defined adequately (Table size upper limit is not a number) | H45: Response Times - Data - Requirements are not defined adequately (Table size upper limit is less than current table size) | I45: Response Times - Data - Requirements are not defined adequately (Estimated records is less than 100, and rationale for the same is not provided) | J45: Response Times - Data - Requirements are not defined adequately (Avoid duplicate table names) | K45: No need to fill Response Times - Data - Requirements since there is no db entries in Software stack requirements table | Q45: 41 | R45: Response Times - Reports – Requirements | S45: %Growth in record count or size - Year 5 | T45: %Growth in record count or size - Year 5 | U45: %Growth in record count or size - Year 5 is not a mandatory field. If known, provide its value as a whole number, else enter "NA". | V45: %Growth in record count or size - Year 5 | W45: %Growth in record count or size - Year 5 is neither a whole number, nor entered as "NA". | X45: IF(ISNUMBER(M114), IF(INT(M114)=M114, TRUE, FALSE), IF(M114="NA", TRUE, FALSE))
A46: 18 | B46: Data Management – Requirements | C46: Data Management – Requirements are defined adequately | D46: Data Management – Requirements are not defined adequately | Q46: 42 | R46: Response Times - Data – Requirements | S46: Transaction Description (either Online, Batch, or Report) | T46: Transaction Description (either Online, Batch, or Report) | U46: Select an appropriate transaction description (either online, batch or report) | V46: Transaction Description (either Online, Batch, or Report) | W46: Transaction description is not selected | X46: Dropdown list (online/ batch/ report) is provided in the data validation directly.
A47: 19 | B47: Resource Utilization – Requirements | C47: CPU Utilization requirement is within the healthy threshold | D47: CPU Utilization requirement exceeds the healthy threshold | Q47: 43 | R47: Response Times - Data – Requirements | S47: Tables accessed for the performance critical transactions (Online, Batch, or Report) | T47: Table accessed | U47: Provide the name of table accessed - text value of length greater than or equal to 5 is allowed. If the field is left blank, the corresponding row will not be considered part of the requirement. | V47: Table accessed | W47: The name of table accessed is not a text value complying to the character length constraints. | X47: AND(ISTEXT(D122),LEN(D122)>=5)
A48: 20 | B48: Resource Utilization – Requirements | C48: Memory Utilization requirement is within the healthy threshold | D48: Memory Utilization requirement exceeds the healthy threshold | G48: Sl. No. | H48: Programming Language | J48: Sl. No. | K48: Deployment Category | Q48: 44 | R48: Response Times - Data – Requirements | S48: Estimated No. Of Records per table | T48: Estimated No. Of Records per table | U48: Estimated No. Of Records per table must be a numeric integer value. | V48: Estimated No. Of Records per table | W48: Estimated No. Of Records per table is not a numeric integer value. | X48: OR(E122="NA", IF(ISNUMBER(E122), INT(E122)=E122, FALSE))
A49: 21 | B49: Global | C49: Application type is distributed web-based data centric | D49: Application type is not distributed web-based data centric | G49: 1 | H49: Java | J49: 1 | K49: Standalone Desktop | Q49: 45 | R49: Response Times - Data – Requirements | S49: Table size in MB | T49: Table size in MB | U49: Table size in MB must be a numeric integer or decimal value greater than 0. | V49: Table size in MB | W49: Table size in MB is neither a numeric integer nor a decimal value greater than 0. | X49: Decimal > 0
A50: 22 | B50: Global | C50: Total concurrent users for peak load testing is within the limits for auto-approval | D50: Total concurrent users for peak load testing is not within the limits for auto-approval | G50: 2 | H50: Python | J50: 2 | K50: On-premise Web | Q50: 46 | R50: Response Times - Data – Requirements | S50: Upper limit for the table size | T50: Upper limit for the table size | U50: Upper limit for the table size must be a numeric integer or decimal value greater than 0. | V50: Upper limit for the table size | W50: Upper limit for the table size is neither a numeric integer nor a decimal value greater than 0. | X50: Decimal > 0
A51: 23 | B51: Global | C51: Conditions for auto-approval are met | D51: Consult with CoE for manual review and closure of gaps | J51: 3 | K51: Cloud | Q51: 47 | R51: Response Times - Data – Requirements | S51: Archival plans for this table? | X51: No validation
A52: 24 | B52: User Types – Requirements | D52: User Types (col 'B') and Total number of users (col 'C') for each User Type must be provided. | J52: 4 | K52: Others | Q52: 48 | R52: Response Times - Data – Requirements | S52: %Growth in record count or size- Year 3 | T52: %Growth in record count or size- Year 3 | U52: %Growth in record count or size- Year 3 is not a mandatory field. If known, provide its value as a whole number, else enter "NA". | V52: %Growth in record count or size- Year 3 | W52: %Growth in record count or size- Year 3 is neither a whole number, nor entered as "NA". | X52: IF(ISNUMBER(I122), IF(INT(I122)=I122, TRUE, FALSE), IF(I122="NA", TRUE, FALSE))
A53: 25 | B53: User Types – Requirements | D53: Total number of users is not a numeric data | Q53: 49 | R53: Response Times - Data – Requirements | S53: %Growth in record count or size- Year 5 | T53: %Growth in record count or size- Year 5 | U53: %Growth in record count or size- Year 5 is not a mandatory field. If known, provide its value as a whole number, else enter "NA". | V53: %Growth in record count or size- Year 5 | W53: %Growth in record count or size- Year 5 is neither a whole number, nor entered as "NA". | X53: IF(ISNUMBER(J122), IF(INT(J122)=J122, TRUE, FALSE), IF(J122="NA", TRUE, FALSE))
A54: 26 | B54: User Types – Requirements | D54: Total number of users at peak is not a numeric data | Q54: 50 | R54: Data Management – Requirements | X54: No validation
A55: 27 | B55: User Types – Requirements | D55: There are more concurrent users than allowed by the Total number of users set | Q55: 51 | R55: Resource Utilization – Requirements | S55: Requirement | T55: Requirement | U55: Requirement must be a whole number | V55: Requirement | W55: Requirement is not a whole number value | X55: IF(D148<>"",IF(D148<>"NA",IF(ISNUMBER(D148), TRUE, FALSE)))
A56: 28 | B56: Response Times - Reports – Requirements | C56: Response Times - Reports – Requirements are not defined | D56: Response Times - Reports – Requirements are not defined adequately | G56: Sl. No. | H56: Cloud Vendor | Q56: 52 | R56: Response Times - Data – Requirements | S56: Requirement | T56: Requirement | U56: Provide the requirements if applicable, else enter "NA". | X56: No validation
A57: 29 | B57: Global | C57: Application complexity is within the scope of auto-approval | D57: Application complexity is beyond the scope of auto-approval | G57: 1 | H57: AWS | Q57: 52 | R57: Response Times - Data – Requirements
A58: 30 | B58: Response Times - Batch Jobs – Requirements | C58: SLA for available time for completion of batch job(Min) is declared | D58: SLA for available time for completion of batch job(Min) is not declared | G58: 2 | H58: Azure
A59: 31 | B59: Response Times - Batch Jobs – Requirements | C59: USLA for available time for completion of batch job(Min) is declared | D59: USLA for available time for completion of batch job(Min) is not declared | G59: 3 | H59: Google Cloud | J59: Sl. No. | K59: Cloud Computing Stack Model
A60: 32 | B60: Response Times - Batch Jobs – Requirements | C60: USLA for available time for completion of batch job(Min) is set adequately | D60: USLA for available time for completion of batch job(Min) is not set properly | G60: 4 | H60: IBM | J60: 1 | K60: IAAS
A61: 33 | B61: Response Times - Reports – Requirements | C61: SLA for 90th Percentile Response Time (Sec) of report is declared | D61: SLA for 90th Percentile Response Time (Sec) of report is not declared | G61: 5 | H61: Vistara | J61: 2 | K61: PAAS
A62: 34 | B62: Response Times - Reports – Requirements | C62: USLA for 90th Percentile Response Time (Sec) of report is declared | D62: USLA for 90th Percentile Response Time (Sec) of report is not declared | G62: 6 | H62: Others | J62: 3 | K62: SAAS
A63: 35 | B63: Response Times - Reports – Requirements | C63: USLA for 90th Percentile Response Time (Sec) of report is set adequately | D63: USLA for 90th Percentile Response Time (Sec) of report is not set properly | G63: 7 | H63: NA | J63: 4 | K63: NA
A64: 36 | B64: Response Times - Reports – Requirements | C64: Response Times - Reports – Requirements are not defined adequately
A65: 37 | B65: Response Times - Batch Jobs – Requirements | C65: Response Times - Batch Jobs – Requirements are not defined | D65: Response Times - Batch Jobs – Requirements not defined adequately
A66: 38 | B66: Resource Utilization – Requirements | D66: CPU Utilization requirement is not defined adequately
A67: 39 | B67: Resource Utilization – Requirements | D67: Memory Utilization requirement is not defined adequately | G67: Sl. No. | H67: Boolean Choice
A68: 40 | B68: Response Times - Online Txns – Requirements | C68: 90th Percentile SLA is set adequately | G68: 1 | H68: Yes | J68: Sl. No. | K68: Load balancing and clustering strategy
A69: 41 | B69: Deployment Requirements | D69: Db Server entry appears in the Software Stack. Please mention the Db server details in Deployment table. | E69: Db Server entry appears in the Software Stack. If there is an alternate way Db Server can be hosted, mention that in the remarks column of the Deployment table. | G69: 2 | H69: No | J69: 1 | K69: Auto-scaling VM instance pool
A70: 42 | B70: Deployment Requirements | C70: DB Server data entered properly in Deployment & Software stack tables | D70: Db Server entries missed in Deployment & Software Stack tables. | J70: 2 | K70: Auto-scaling Containers
A71: 43 | B71: Deployment Requirements | D71: This will not happen | J71: 3 | K71: Others
A72: 44 | B72: Software Stack - Information | D72: Db Server entry appears in the Deployment table. Please mention softwares on Db Server in the Software Stack table. | J72: 4 | K72: NA
A73: 45 | B73: Data Management – Requirements | D73: As Database component is not part of the asset, Data Management Requirements can be left empty
A74: 46 | B74: Response Times - Data – Requirements | D74: As Database component is not part of the asset, Data Requirements can be left empty | G74: Sl. No. | H74: Technology Stack
A75: 47 | B75: Asset Synoptics | C75: Name of the asset is provided | D75: Name of the asset is not provided | G75: 1 | H75: Normal Web
A76: 48 | B76: Asset Synoptics | C76: Brand name of the asset is provided | D76: Brand name of the asset is not provided | G76: 2 | H76: Big Data
A77: 49 | B77: Software Stack - Information | D77: Web Server entry appears in the Deployment table. Please mention softwares on Web Server in the Software Stack table. | G77: 3 | H77: Blockchain | J77: Sl. No. | K77: Application Type
A78: 50 | B78: Deployment Requirements | D78: Web Server entry appears in the Software Stack. Please mention the Web server details in Deployment table. | E78: Web Server entry appears in the Software Stack. If there is an alternate way Web Server can be hosted, mention that in the remarks column of the Deployment table. | G78: 4 | H78: AI-ML | J78: 1 | K78: Web-based
A79: 51 | B79: Deployment Requirements | C79: Web Server data entered properly in Deployment & Software stack tables | D79: Web Server entries missed in Deployment & Software Stack tables. | G79: 5 | H79: IoT | J79: 2 | K79: Desktop
A80: 52 | B80: Deployment Requirements | D80: App Server entry appears in the Deployment table. Please mention softwares on App Server in the Software Stack table. | G80: 6 | H80: Google API - Firebase | J80: 3 | K80: Mobile
A81: 53 | B81: Deployment Requirements | D81: App Server entry appears in the Software Stack. Please mention the App server details in Deployment table. | E81: App Server entry appears in the Software Stack. If there is an alternate way App Server can be hosted, mention that in the remarks column of the Deployment table. | G81: 7 | H81: Power BI | J81: 4 | K81: API-based
A82: 54 | B82: Deployment Requirements | C82: App Server data entered properly in Deployment & Software stack tables | D82: App Server entries missed in Deployment & Software Stack tables. | G82: 8 | H82: Salesforce.com | J82: 5 | K82: Web Services
A83: 55 | B83: Response Times - Online Txns – Requirements | C83: Response Times - Online Txns – Requirements are not defined | D83: Response Times - Online Txns – Requirements not defined adequately | G83: 9 | H83: SAP-based | J83: 6 | K83: Batch
A84: 56 | B84: Asset Synoptics | C84: TIPAR ID of the asset is valid | D84: TIPAR ID of the asset is not valid | G84: 10 | H84: AR-VR | J84: 7 | K84: Rich client
A85: 57 | B85: Response Times - Online Txns – Requirements | C85: Transaction description/s are provided adequately | D85: Avoid duplicate transaction descriptions | G85: 11 | H85: Video Recording | J85: 8 | K85: Others
A86: 58 | B86: Response Times - Batch Jobs – Requirements | C86: Batch job description/s are provided adequately | D86: Avoid duplicate batch job descriptions | G86: 12 | H86: Streaming
A87: 59 | B87: Response Times - Reports – Requirements | C87: Report description/s are provided adequately | D87: Avoid duplicate report descriptions | G87: 13 | H87: Gen AI
A88: 60 | B88: Response Times - Data – Requirements | D88: Representing multiple tables in comma separated format is disallowed. Use only a single table name. | G88: 14 | H88: Microservices
G89: 15 | H89: Others
G91: Sl. No. | H91: Sheet Name
G92: 1 | H92: Cover Page
G93: 2 | H93: Read me
G94: 3 | H94: Asset Info
G95: 4 | H95: Performance
G96: 5 | H96: Data_Validations
G97: 6 | H97: Data_Constants
G98: 7 | H98: Internal_Release
G99: 8 | H99: Report
A100: Sl. No. | B100: Table | C100: Intended Purpose of validation | D100: Column1
A101: 1 | B101: Asset Information | C101: Checks if proper version number is present for the asset
A102: 2 | B102: Asset Information | C102: Checks if description length is greater than 100 characters
...

Sheet Internal_Release
B2: Sl. No | C2: QOPD Release Number | D2: Date | E2: Changes
B3: 1 | C3: 4.1.0 | D3: 45582 | E3: 1. Auto-approval has been extended for Desktop type application. 2. Auto-approval has been extended for applications deployed in Cloud SAAS and PAAS, which is on top of IAAS, 3. In the 'Asset Info' tab, for the question on Technology Stack, the following new entries have been added - Gen AI and Microservices, 4. A new condition check is added to the validation logic linked with 'Response Times - Data Requirements' table to check if remarks is provided when the count of records in the table is less than 100. In such a case, positive validation will occur if the remarks are provided. The validation outcome message is also changed to reflect that the rationale for less than 100 records in the table is not provided whenever a negative validation outcome results. 5. Fixed the following issues I. In the case when online transaction table is empty (i.e., without any transaction), the validation to check if the User Concurrency distribution is proper across online transactions and online report transactions as a whole was not happening. This was fixed, and the linked changes required in the validation messages and their formatting have been made. II. The App server, Webserver, and DB server List validations were refactored to avoid making changes in the validation logic whenever the list was updated.
B4: 2 | C4: 4.0.0 | D4: 45504 | E4: 1. Introduced additional set of Servers applicable for rule evaluation in the Web Server Pool, 2. Introduced additional set of Servers applicable for rule evaluation in the Application Server Pool, 3. Introduced additional set of Servers applicable for rule evaluation in the DB Server Pool, 4. Expanded the range of concurrent users applicable for rule evaluation. From 15 to 150, the range has been expanded to between 1 and 200, 5. 5. In the 'Response Times - Data – Requirements' table, the column heading for 'Estimated No. Of Records per table' has been updated to imply that the number of records mentioned must be of the Performance testing environment. The Input Message in that column has also been changed to inform the end user about this expectation so while filling the performance requirements of the target asset, it is clear on what data must be filled. 6. Derive the name of the QOPD file based on the conventions outlined in the 'Read me' tab. The name is kept in the 'Data_Validations' tab for future use. 7. Prevent a spill error occurring in 'Deployment Requirements' table validation due to an extra entry added between Web Server and App Server line items in the 'Software Stack - Information' table.
B5: 3 | C5: 3.1.0 | D5: 45299 | E5: 1. Cross table data dependency validations are added i. "Deployment Requirements" v/s "Software Stack - Information" table a. If there is a Web Server, related software must be present against "Software - Web Server" entry in the "Software Stack - Information" table. b. If there is a Application Server, related software must be present against "Application Server" entry in the "Software Stack - Information" table. c. If there is a DB Server, related software must be present against "DB Server" entry in the "Software Stack - Information" table. Reverse relationships are also similarly covered by the validation. ii. "Software Stack - Information" v/s "Response Times - Data-Requirements" table a. If there is a DB Server, corresponding DB data requirements must be present in the "Response Times - Data-Requirements" table. b. If there is no DB Server, "Response Times - Data-Requirements" table can be empty. 2. Allow a scenario where "Response Times - Online Txns-Requirements" table is empty In the previous release of the QOPD, an Asset with no requirements in this table, results in an error message and "Not Appproved" outcome for the table in the "Report" sheet. With the change, it allows this table to be empty when any one of "Response Times - Batch Jobs-Requirements"/"Response Times - Reports-Requirements" tables, or both are non-empty with respect to requirements. 3. Validation messages across tables that must reflect the same context have been re-written for uniformity E.g., messages such as "No batch jobs are defined" and "Response time Report requirements are not filled" 4. Changes to basic validation and message output for couple requirements tables and conditional formatting changes i. Brand name (in the "Asset Info" tab) - it must be non-blank and atleast 3 characters in length, or "NA" ii. Disallow duplicate values for the following a. "Transaction Description" column in "Response Times - Online Txns-Requirements" table b. "Batch job/Transaction Description" column in "Response Times - Batch Jobs-Requirements" table c. "Report Description" column in "Response Times - Reports-Requirements" table d. "Transaction Description" column in "Response Times - Data – Requirements" table iii. Generic messages have been modified for specificity - column based error messages are applied for "Response Times - Data-Requirements" table, rather than showing generic messages like "***table is not filled adequately" iv. Validation message is changed for "Report type" column in "Response Times - Reports – Requirements" table v. In "Response Times - Data – Requirements" table, following validations are added a. to check if the "Tables accessed for the performance critical transactions" column does not allow multiple table names separated by comma, b. to check and ensure that empty values are disallowed for "Table size in MB" column. vi. TIPAR ID validation for its allowed length, and that the first 5 characters starts with "TIPAR" (which is case sensitive). vii. Corrected wrongly resolved conditional formatting in the Data_Validation sheet. 5. Changes or addition in Usage guidelines ("Read me" tab) i. Usage guidelines: Added file format to be used and formats that are not supported ii. Usage guidelines: Added QOPD file naming convention to be followed iii. Updates to existing guidelines to include a. the case of auto-approval for Cloud IaaS based VM deployments, b. the exclusion of validation rules on requirement line items that have blank value for description type column.
B6: 3 | C6: 3.0.0 | D6: 45211 | E6: 1. Allow deployments in Cloud-IAAS (GCP/ AWS/ Azure) for auto approval of requirements similar to on-premise deployments 2. Added the following in the 'Asset Info' tab i. In 'Asset Information' table, separate rows for 'Asset Name' and 'Version', ii. In 'Asset Information' table, a new row for 'Brand Name', iii. In 'Technical Details' table, added the following questions a. Which is the Geographic location of the cloud datacenter? b. Is the response time requirement Transaction wise or request wise? c. Is the expected response/ completion time SLA of all online, report, and batch transactions of the asset known? 3. Modified the following i. In 'Response Times - Data – Requirements' table, the column header for upper limit for the table size, expects data to be filled in unit of mega bytes (MB) ii. Disallow comma (',') character in 'Name' and 'Version' fields of 'Software Stack - Information' table. iii. Content in the requirements table - 'Data Management – Requirements' 4. Fixed the following issues i. If 'DB Server' cell placeholder in 'Deployment Requirements' table is having 'NA' values for 'Number of Instances'/ 'CPU cores'/ 'RAM in GB' with remarks under 'Remarks'column, it is wrongly interpreted as application with no DB, and showing wrong validation message for 'Response Times - Data – Requirements' and 'Data Management – Requirements' tables. ii. In 'Response Times - Online Txns – Requirements' table, incorrect data validations for SLA/ USLA fields. iii. Validation error is not shown when concurrent users distribution is done with 0 users.
B7: 4 | C7: 2.0.5 | D7: 45155 | E7: 1. When either of the 'Software Stack - Information' or the 'Deployment Requirements' table is missing data related to DB Server or DB Software, alert the user with the validation message to enter missing details. [In the 'Data_Constants' table, a new table 'DB Server check' was introduced to identify the position of 'DB Server' entry in both 'Deployment Requirements' and 'Software Stack - Information' tables. Similarly in this sheet where data for validation is filtered from the respective source tables in 'Asset Info' and 'Performance' sheets, two tables for filtering 'DB Server' data are newly introduced.] 2. In 'Response Times - Online Txns – Requirements' table, validation and message display for the case when response time is above 5 secs are refactored for ensuring correctness. 3. In 'Data Management – Requirements' table, the case where a 'NA' value in column 'D' (Requirement) was resulting in exclusion of the corresponding row of the table for validation checks is remediated.
B8: 5 | C8: 2.0.4 | D8: 45127 | E8: 1. Included editable rows for adding more of Web, App, Content/ Image, and DB Servers in 'Deployment Requirements' table. 2. In 'Channels - Information' table included editable rows for adding one or more new channels applicable to the asset. 3. Changed the name of the Apache family web server to correctly reflect that in the 'Software Stack - Information' table. 4. Excluded the need for having a Web Server in the deployment stack for considering it as a Web-based data-centric Application.
B9: 6 | C9: 2.0.3 | D9: 45120 | E9: 1. To refactor & fix the filter function that extracts asset information. 2. Add an experimental validation to check if there are additional requirements outside of the scope of current auto-approval mode.
B10: 7 | C10: 2.0.2 | D10: 45114 | E10: 1. To fix the Deployment Requirements table validation - Conditionally validating the values of CPU cores and RAM based on the value of number of instances - Fix the filter formula to pull all Servers entered in the table. 2. To fix the out of context error message appearing while entering requirements in 'Data – Requirements' table.
C11: 2.0.1 | D11: 45111 | E11: 1. Javascript libraries/packages (extJs etc) - Updated with an example Javascript library - 'extJs 4.2' 2. Concurrent users range validation for auto-approval - Changed the formula to have the validation work even if the online and/or report transaction data set is blank 3. A minor change in the valid case message for batch job completion time (cell# - C43) 4. A minor change in the text for 'Intended purpose of validation' (cell# - C116) 5. A corresponding change in the 'Input Message' linked to #3 & #4 above

Sheet Report
A1: Asset Registration ID | B1: ='Asset Info'!B11
A2: QOPD Evaluation Status | B2: =IF(OR(AND(B8=0,B24,B25, B26), AND('Asset Info'!C16= Data_Constants!K49, B8=0, Data_Validations!Y3=TRUE)), "Cleared", "Not Cleared")
A3: Reviewer Evaluation Status
A4: Reviewer Final Comments
A6: Total Applicable Checklist Items | B6: =COUNTIFS(B11:B21,"Approved")+COUNTIFS(B11:B21,"Not Approved")
A7: Total Autoapproved | B7: =COUNTIFS(B11:B21,"Approved")
A8: Total Not Autoapproved | B8: =COUNTIFS(B11:B21,"Not Approved")
A10: Performance Requirement Category | B10: Approval Status
A11: Asset Information | B11: =IF(AND(Data_Validations!F3, Data_Validations!F4, Data_Validations!F35,Data_Validations!F36,Data_Validations!F39), "Approved", "Not Approved")
A12: Deployment Requirements | B12: =IF(Data_Validations!F5, "Approved", "Not Approved")
A13: Software Stack - Information | B13: =IF(AND(Data_Validations!F6, Data_Validations!F7), "Approved", "Not Approved")
A14: User Types – Requirements | B14: =IF(Data_Validations!F8, "Approved", "Not Approved")
A15: Channels - Information | B15: =IF(Data_Validations!F9, "Approved", "Not Approved")
A16: Response Times - Online Txns – Requirements | B16: =IF(AND(Data_Validations!F10, Data_Validations!F11, Data_Validations!F12, Data_Validations!F13, Data_Validations!F14, Data_Validations!F15, Data_Validations!F16, Data_Validations!F40), "Approved", "Not Approved")
A17: Response Times - Batch Jobs – Requirements | B17: =IF(AND(Data_Validations!F17,Data_Validations!F23,Data_Validations!F24,Data_Validations!F25, Data_Validations!F41),"Approved", "Not Approved")
A18: Response Times - Reports – Requirements | B18: =IF(AND(Data_Validations!F18,Data_Validations!F31,Data_Validations!F32,Data_Validations!F33, Data_Validations!F42, Data_Validations!F43), "Approved", "Not Approved")
A19: Response Times - Data – Requirements | B19: =IF(Data_Validations!F19, "Approved", "Not Approved")
A20: Data Management – Requirements | B20: =IF(Data_Validations!F20, "Approved", "Not Approved")
A21: Resource Utilization – Requirements | B21: =IF(AND(Data_Validations!F21, Data_Validations!F22), "Approved", "Not Approved")
A23: Contextual Background | B23: Status
A24: Is it a Web-based data-centric Application? | B24: =IF(Data_Validations!K3, TRUE, FALSE)
A25: Is User concurrency for peak load within the limits for auto-approval of requirements? | B25: =IF(Data_Validations!K4, TRUE, FALSE)
A26: Is the asset a normal web application based on the answers to the questionnaire in the 'Asset Info' sheet? | B26: =IF(Data_Validations!K5, TRUE, FALSE)
